Workbook

Sheet Données MSDL
B6: UNION DES JEUNES DE DOUKA SELEYABE
G8: =+TODAY() -> 46001
B10: LISTE OFFICIELLE DES MEMBRES
M12: 2000 | T12: A JOUR | U12: GUINEE | V12: NT | W12: DETTE
B13: N° | C13: Code | D13: Téléphone | E13: Titre | F13: Désignation | G13: Missidé | H13: Pays/région | I13: Téléphone | J13: Montant mensuel MSD | K13: Montant mensuel UJDS | L13: Nbre de mois retard | M13: Amande | N13: Avance | O13: Montant dû au 15 01 25 | P13: UJDS | Q13: MOUSSIDAL | R13: STATUT | Y13: 45444 | Z13: 45474 | AA13: 45505 | AB13: 45536 | AC13: 45566 | AD13: 45597 | AE13: 45627 | AF13: 45658 | AG13: 45689 | AH13: 45717 | AI13: 45748 | AJ13: 45778 | AK13: 45809 | AL13: 45839 | AM13: 45870 | AN13: 45901 | AO13: 45931 | AP13: 45962 | AQ13: 45992
B14: 1 | C14: =CONCATENATE("N°-","000",B14,"-2024") -> N°-0001-2024 | D14: 778779867 | E14: Mr | F14: Abdoul aziz ibn Elhadji Ibrahima | G14: Pétel | H14: Dakar | I14: 77 877 98 67 | J14: 1000 | K14: N/A | L14: =+SUM($Y14:$AQ14) -> -56 | M14: =IF(L14>=0,"A JOUR",($L14*($M$12))) -> -112000 | O14: =IF(L14>=0,"A JOUR",($L14*($M$12+J14)+N14)) -> -168000 | Q14: x | T14: #N/A | U14: #N/A | V14: #N/A | W14: 1000 | X14: 56 | Y14: -52 | Z14: -1 | AA14: -1 | AB14: -1 | AC14: 0 | AD14: -1
B15: 2 | C15: =CONCATENATE("N°-","000",B15,"-2024") -> N°-0002-2024 | D15: 772175292 | E15: Koto | F15: Abdoul ghadry | G15: Leysaré | H15: Dakar | I15: 77 217 52 92 | J15: 2000 | K15: 1000 | L15: 0 | M15: =IF(L15>=0,"A JOUR",($L15*($M$12))) -> A JOUR | O15: =IF(L15>=0,"A JOUR",($L15*($M$12+J15)+N15)) -> A JOUR | P15: x | Q15: x | T15: A JOUR | Y15: 0 | Z15: 0 | AA15: 0 | AB15: 0 | AC15: 0 | AD15: 0
B16: 3 | C16: =CONCATENATE("N°-","000",B16,"-2024") -> N°-0003-2024 | D16: xxxxxxxx | E16: Mr | F16: Abdoul goudoussy | G16: Kourawoye | H16: Guinée | I16: xxxxxxxx | K16: 1000 | L16: VG | M16: =IF(L16>=0,"A JOUR",($L16*($M$12))) -> A JOUR | O16: =IF(L16>=0,"A JOUR",($L16*($M$12+J16)+N16)) -> A JOUR | P16: x | R16: VG | T16: #N/A | U16: #N/A | V16: #N/A | W16: #N/A | X16: #N/A | Y16: 0 | Z16: 0 | AA16: 0 | AB16: 0 | AC16: 0 | AD16: 0
B17: 4 | C17: =CONCATENATE("N°-","000",B17,"-2024") -> N°-0004-2024 | D17: 773528333 | E17: Kaou | F17: Abdoul malipan | G17: Dowsaré | H17: Dakar | I17: 77 352 83 33 | J17: 2000 | K17: N/A | L17: =+SUM($Y17:$AQ17) -> -25 | M17: =IF(L17>=0,"A JOUR",($L17*($M$12))) -> -50000 | O17: =IF(L17>=0,"A JOUR",($L17*($M$12+J17)+N17)) -> -100000 | Q17: x | T17: #N/A | U17: #N/A | V17: #N/A | W17: 2000 | X17: 25 | Y17: -21 | Z17: -1 | AA17: -1 | AB17: -1 | AC17: 0 | AD17: -1
B18: 5 | C18: =CONCATENATE("N°-","000",B18,"-2024") -> N°-0005-2024 | D18: xxxxxxxx | E18: Koto | F18: Abdoul salam | G18: Gobihi | H18: Gambie | I18: xxxxxxxx | J18: 2000 | K18: 1000 | M18: =IF(L18>=0,"A JOUR",($L18*($M$12))) -> A JOUR | O18: =IF(L18>=0,"A JOUR",($L18*($M$12+J18)+N18)) -> A JOUR | Q18: x | T18: #N/A | U18: #N/A | V18: #N/A | W18: #N/A | X18: #N/A | Y18: 0 | Z18: 0 | AA18: 0 | AB18: 0 | AC18: 0 | AD18: 0
B19: 6 | C19: =CONCATENATE("N°-","000",B19,"-2024") -> N°-0006-2024 | D19: 774789094 | E19: Mr | F19: Abdoul salam petit ibn bappa bala | G19: Pétel | H19: Dakar | I19: 77 478 90 94 | J19: 2000 | K19: 1000 | L19: 0 | M19: =IF(L19>=0,"A JOUR",($L19*($M$12))) -> A JOUR | O19: =IF(L19>=0,"A JOUR",($L19*($M$12+J19)+N19)) -> A JOUR | P19: x | Q19: x | T19: A JOUR | Y19: 0 | Z19: 0 | AA19: 0 | AB19: 0 | AC19: 0 | AD19: 0
B20: 7 | C20: =CONCATENATE("N°-","000",B20,"-2024") -> N°-0007-2024 | D20: 781050363 | E20: Koto | F20: Abdoul salam ibn Elhadji M. Woury VP | G20: Pétel | H20: Dakar | I20: 78 105 03 63 | J20: 2000 | K20: 1000 | L20: 0 | M20: =IF(L20>=0,"A JOUR",($L20*($M$12))) -> A JOUR | O20: =IF(L20>=0,"A JOUR",($L20*($M$12+J20)+N20)) -> A JOUR | P20: x | Q20: x | T20: A JOUR | Y20: 0 | Z20: 0 | AA20: 0 | AB20: 0 | AC20: 0 | AD20: 0
B21: 8 | C21: =CONCATENATE("N°-","000",B21,"-2024") -> N°-0008-2024 | D21: +24104506555 | E21: Mr | F21: Abdoul salam ibn karamoko Daouda | G21: Pétel | H21: Gabon | I21: +241 04 50 65 55 | J21: 5000 | K21: N/A | M21: =IF(L21>=0,"A JOUR",($L21*($M$12))) -> A JOUR | O21: =IF(L21>=0,"A JOUR",($L21*($M$12+J21)+N21)) -> A JOUR | Q21: x | T21: #N/A | U21: #N/A | V21: #N/A | W21: #N/A | X21: #N/A | Y21: 0 | Z21: 0 | AA21: 0 | AB21: 0 | AC21: 0 | AD21: 0
B22: 9 | C22: =CONCATENATE("N°-","000",B22,"-2024") -> N°-0009-2024 | D22: 774789094 | E22: Mr | F22: Abdoul salam petit | G22: Pétel | H22: Dakar | I22: 77 478 90 94 | J22: 2000 | K22: 1000 | L22: 0 | M22: =IF(L22>=0,"A JOUR",($L22*($M$12))) -> A JOUR | O22: =IF(L22>=0,"A JOUR",($L22*($M$12+J22)+N22)) -> A JOUR | P22: x | Q22: x | T22: A JOUR | Y22: 0 | Z22: 0 | AA22: 0 | AB22: 0 | AC22: 0 | AD22: 0
B23: 10 | C23: =CONCATENATE("N°-","00",B23,"-2024") -> N°-0010-2024 | D23: 776792624 | E23: Mr | F23: Abdoul salam PP | G23: Dieydiyabhe | H23: Dakar | I23: 77 679 26 24 | J23: 1000 | K23: 1000 | L23: 0 | M23: =IF(L23>=0,"A JOUR",($L23*($M$12))) -> A JOUR | O23: =IF(L23>=0,"A JOUR",($L23*($M$12+J23)+N23)) -> A JOUR | P23: x | Q23: x | T23: A JOUR | Y23: 0 | Z23: 0 | AA23: 0 | AB23: 0 | AC23: 0 | AD23: 0
B24: 11 | C24: =CONCATENATE("N°-","00",B24,"-2024") -> N°-0011-2024 | D24: 775779980 | E24: Mr | F24: Abdoul salam PP (ivoire) | G24: Dowsaré | H24: Dakar | I24: 77 577 99 80 | J24: 1000 | K24: 1000 | L24: =+SUM($Y24:$AQ24) -> -2 | M24: =IF(L24>=0,"A JOUR",($L24*($M$12))) -> -4000 | O24: =IF(L24>=0,"A JOUR",($L24*($M$12+J24)+N24)) -> -6000 | P24: x | Q24: x | T24: #N/A | U24: #N/A | V24: #N/A | W24: 1000 | X24: 2 | Y24: 0 | Z24: 0 | AA24: 0 | AB24: -1 | AC24: 0 | AD24: -1
B25: 12 | C25: =CONCATENATE("N°-","00",B25,"-2024") -> N°-0012-2024 | E25: Mr | F25: Abdoulaye | G25: Daandé Mboully | H25: Guinée | K25: 1000 | L25: VG | M25: =IF(L25>=0,"A JOUR",($L25*($M$12))) -> A JOUR | O25: =IF(L25>=0,"A JOUR",($L25*($M$12+J25)+N25)) -> A JOUR | P25: x | R25: VG | T25: #N/A | U25: #N/A | V25: #N/A | W25: #N/A | X25: #N/A | Y25: 0 | Z25: 0 | AA25: 0 | AB25: 0 | AC25: 0 | AD25: 0
B26: 13 | C26: =CONCATENATE("N°-","00",B26,"-2024") -> N°-0013-2024 | D26: xxxxxxxx | E26: Mr | F26: Abdoulaye | G26: Kourawoye | H26: Côte d'ivoire | I26: xxxxxxxx | J26: 1000 | K26: N/A | M26: =IF(L26>=0,"A JOUR",($L26*($M$12))) -> A JOUR | O26: =IF(L26>=0,"A JOUR",($L26*($M$12+J26)+N26)) -> A JOUR | P26: x | T26: #N/A | U26: #N/A | V26: #N/A | W26: #N/A | X26: #N/A | Y26: 0 | Z26: 0 | AA26: 0 | AB26: 0 | AC26: 0 | AD26: 0
B27: 14 | C27: =CONCATENATE("N°-","00",B27,"-2024") -> N°-0014-2024 | D27: 781413617 | E27: Grand | F27: Abdoulaye (Laye) | G27: Biilaa | H27: Dakar | I27: 78 141 36 17 | J27: 1000 | K27: 1000 | L27: 0 | M27: =IF(L27>=0,"A JOUR",($L27*($M$12))) -> A JOUR | O27: =IF(L27>=0,"A JOUR",($L27*($M$12+J27)+N27)) -> A JOUR | P27: x | Q27: x | T27: #N/A | U27: GUINEE | Y27: 0 | Z27: 0 | AA27: 0 | AB27: 0 | AC27: 0 | AD27: 0
B28: 15 | C28: =CONCATENATE("N°-","00",B28,"-2024") -> N°-0015-2024 | D28: +24106399421 | E28: Grand | F28: Abdoulaye (Laye) gabonais | G28: Pétel | H28: Dakar | I28: +241 06 39 94 21 | J28: 2000 | K28: N/A | L28: =+SUM($Y28:$AQ28) -> -4 | M28: =IF(L28>=0,"A JOUR",($L28*($M$12))) -> -8000 | O28: =IF(L28>=0,"A JOUR",($L28*($M$12+J28)+N28)) -> -16000 | Q28: x | T28: #N/A | U28: #N/A | V28: #N/A | W28: 2000 | X28: 4 | Y28: 0 | Z28: -1 | AA28: -1 | AB28: -1 | AC28: 0 | AD28: -1
B29: 16 | C29: =CONCATENATE("N°-","00",B29,"-2024") -> N°-0016-2024 | D29: 777255426 | E29: Mr | F29: Abdoulaye djibril KZA ibnou samara | G29: Dowsaré | H29: Casamance | I29: 77 725 54 26 | J29: 1500 | K29: N/A | L29: 0 | M29: =IF(L29>=0,"A JOUR",($L29*($M$12))) -> A JOUR | O29: =IF(L29>=0,"A JOUR",($L29*($M$12+J29)+N29)) -> A JOUR | P29: x | Q29: x | T29: A JOUR | Y29: 0 | Z29: 0 | AA29: 0 | AB29: 0 | AC29: 0 | AD29: 0
B30: 17 | C30: =CONCATENATE("N°-","00",B30,"-2024") -> N°-0017-2024 | E30: Mr | F30: Abdoulaye ka gallé | G30: Biilaa | H30: Guinée | K30: N/A | L30: VG | M30: =IF(L30>=0,"A JOUR",($L30*($M$12))) -> A JOUR | O30: =IF(L30>=0,"A JOUR",($L30*($M$12+J30)+N30)) -> A JOUR | R30: VG | T30: #N/A | U30: #N/A | V30: #N/A | W30: #N/A | X30: #N/A | Y30: 0 | Z30: 0 | AA30: 0 | AB30: 0 | AC30: 0 | AD30: 0
B31: 18 | C31: =CONCATENATE("N°-","00",B31,"-2024") -> N°-0018-2024 | D31: 774042497 | E31: Mr | F31: Abdourahmane TRS | G31: Mamasamba | H31: Dakar | I31: 77 404 24 97 | J31: 5000 | K31: 1000 | L31: 0 | M31: =IF(L31>=0,"A JOUR",($L31*($M$12))) -> A JOUR | O31: =IF(L31>=0,"A JOUR",($L31*($M$12+J31)+N31)) -> A JOUR | P31: x | Q31: x | T31: #N/A | U31: #N/A | V31: #N/A | W31: #N/A | X31: #N/A | Y31: 0 | Z31: 0 | AA31: 0 | AB31: 0 | AC31: 0 | AD31: 0
B32: 19 | C32: =CONCATENATE("N°-","00",B32,"-2024") -> N°-0019-2024 | D32: 774473167 | E32: Koto | F32: Ablaye TSA | G32: Bolorrou | H32: Dakar | I32: 77 447 31 67 | J32: 1500 | K32: 1000 | L32: 0 | M32: =IF(L32>=0,"A JOUR",($L32*($M$12))) -> A JOUR | O32: =IF(L32>=0,"A JOUR",($L32*($M$12+J32)+N32)) -> A JOUR | P32: x | Q32: x | T32: A JOUR | Y32: 0 | Z32: 0 | AA32: 0 | AB32: 0 | AC32: 0 | AD32: 0
B33: 20 | C33: =CONCATENATE("N°-","00",B33,"-2024") -> N°-0020-2024 | D33: 777119328 | E33: Kaou | F33: Ahmadou Korka ibn bappa bala | G33: Pétel | H33: Dakar | I33: 777119328 | J33: 1000 | K33: 1000 | L33: =+SUM($Y33:$AQ33) -> -3 | M33: =IF(L33>=0,"A JOUR",($L33*($M$12))) -> -6000 | O33: =IF(L33>=0,"A JOUR",($L33*($M$12+J33)+N33)) -> -9000 | T33: #N/A | U33: #N/A | V33: #N/A | W33: 1000 | X33: 3 | Y33: 0 | Z33: 0 | AA33: -1 | AB33: -1 | AC33: 0 | AD33: -1
B34: 21 | C34: =CONCATENATE("N°-","00",B34,"-2024") -> N°-0021-2024 | D34: 783520425 | E34: Mr | F34: Alassana ibn Elhadji M. Woury | G34: Pétel | H34: Dakar | I34: 78 352 04 25 | J34: 1000 | K34: 1000 | L34: 0 | M34: =IF(L34>=0,"A JOUR",($L34*($M$12))) -> A JOUR | O34: =IF(L34>=0,"A JOUR",($L34*($M$12+J34)+N34)) -> A JOUR | Q34: x | R34: NT | T34: #N/A | U34: #N/A | V34: NT | Y34: 0 | Z34: 0 | AA34: 0 | AB34: 0 | AC34: 0 | AD34: 0
B35: 22 | C35: =CONCATENATE("N°-","00",B35,"-2024") -> N°-0022-2024 | D35: 767652193 | E35: Mr | F35: Alassana Macoss | G35: Dowsaré | H35: Dakar | I35: 76 765 21 93 | J35: 1000 | K35: 1000 | L35: 0 | M35: =IF(L35>=0,"A JOUR",($L35*($M$12))) -> A JOUR | O35: =IF(L35>=0,"A JOUR",($L35*($M$12+J35)+N35)) -> A JOUR | P35: x | Q35: x | R35: NT | T35: #N/A | U35: #N/A | V35: NT | Y35: 0 | Z35: 0 | AA35: 0 | AB35: 0 | AC35: 0 | AD35: 0
B36: 23 | C36: =CONCATENATE("N°-","00",B36,"-2024") -> N°-0023-2024 | D36: 783520425 | E36: Mr | F36: Alousseynou ibn Elhadji M. Woury | G36: Pétel | H36: Dakar | I36: 78 352 04 25 | J36: 1000 | K36: 1000 | L36: 0 | M36: =IF(L36>=0,"A JOUR",($L36*($M$12))) -> A JOUR | O36: =IF(L36>=0,"A JOUR",($L36*($M$12+J36)+N36)) -> A JOUR | Q36: x | R36: NT | T36: #N/A | U36: #N/A | V36: NT | Y36: 0 | Z36: 0 | AA36: 0 | AB36: 0 | AC36: 0 | AD36: 0
B37: 24 | C37: =CONCATENATE("N°-","00",B37,"-2024") -> N°-0024-2024 | E37: Mr | F37: Alousseynou Pecosse | G37: Dowsaré | H37: Guinée | K37: N/A | L37: VG | M37: =IF(L37>=0,"A JOUR",($L37*($M$12))) -> A JOUR | O37: =IF(L37>=0,"A JOUR",($L37*($M$12+J37)+N37)) -> A JOUR | P37: x | R37: VG | T37: #N/A | U37: #N/A | V37: #N/A | W37: #N/A | X37: #N/A | Y37: 0 | Z37: 0 | AA37: 0 | AB37: 0 | AC37: 0 | AD37: 0
B38: 25 | C38: =CONCATENATE("N°-","00",B38,"-2024") -> N°-0025-2024 | E38: Mr | F38: Alpha (France) | G38: Dieydiyabhe | H38: France | K38: 1000 | M38: =IF(L38>=0,"A JOUR",($L38*($M$12))) -> A JOUR | O38: =IF(L38>=0,"A JOUR",($L38*($M$12+J38)+N38)) -> A JOUR | T38: #N/A | U38: #N/A | V38: #N/A | W38: #N/A | X38: #N/A | Y38: 0 | Z38: 0 | AA38: 0 | AB38: 0 | AC38: 0 | AD38: 0
B39: 26 | C39: =CONCATENATE("N°-","00",B39,"-2024") -> N°-0026-2024 | D39: 772289487 | E39: Mr | F39: Alpha amadou ibn bappa bala | G39: Pétel | H39: Dakar | I39: 77 228 94 87 | J39: 1000 | K39: 1000 | L39: 0 | M39: =IF(L39>=0,"A JOUR",($L39*($M$12))) -> A JOUR | O39: =IF(L39>=0,"A JOUR",($L39*($M$12+J39)+N39)) -> A JOUR | P39: x | Q39: x | T39: A JOUR | Y39: 0 | Z39: 0 | AA39: 0 | AB39: 0 | AC39: 0 | AD39: 0
B40: 27 | C40: =CONCATENATE("N°-","00",B40,"-2024") -> N°-0027-2024 | D40: 781261182 | E40: Mr | F40: Alpha Amirou ibn Elhadji Ibrahima | G40: Pétel | H40: Dakar | I40: 78 126 11 82 | J40: 1000 | K40: 1000 | L40: =+SUM($Y40:$AQ40) -> -6 | M40: =IF(L40>=0,"A JOUR",($L40*($M$12))) -> -12000 | O40: =IF(L40>=0,"A JOUR",($L40*($M$12+J40)+N40)) -> -18000 | Q40: x | R40: NT | T40: #N/A | U40: #N/A | V40: #N/A | W40: 1000 | X40: 6 | Y40: -2 | Z40: -1 | AA40: -1 | AB40: -1 | AC40: 0 | AD40: -1
B41: 28 | C41: =CONCATENATE("N°-","00",B41,"-2024") -> N°-0028-2024 | D41: 772202046 | E41: Koto | F41: alpha KZA ibnou samara | G41: Dowsaré | H41: Casamance | I41: 77 220 20 46 | J41: 2000 | K41: 1000 | L41: 1 | M41: =IF(L41>=0,"A JOUR",($L41*($M$12))) -> A JOUR | N41: =+L41*J41 -> 2000 | O41: =IF(L41>=0,"A JOUR",($L41*($M$12+J41)+N41)) -> A JOUR | P41: x | Q41: x | T41: A JOUR | Y41: 0 | Z41: 0 | AA41: 0 | AB41: 0 | AC41: 0 | AD41: 0
B42: 29 | C42: =CONCATENATE("N°-","00",B42,"-2024") -> N°-0029-2024 | D42: 781346347 | E42: Bappa | F42: Alpha oumar | G42: Mamasamba | H42: Dakar | I42: 78 134 63 47 | J42: 2000 | K42: 1000 | L42: =4-4 -> 0 | M42: =IF(L42>=0,"A JOUR",($L42*($M$12))) -> A JOUR | O42: =IF(L42>=0,"A JOUR",($L42*($M$12+J42)+N42)) -> A JOUR | P42: x | Q42: x | T42: A JOUR | Y42: 0 | Z42: 0 | AA42: 0 | AB42: 0 | AC42: 0 | AD42: 0
B43: 30 | C43: =CONCATENATE("N°-","00",B43,"-2024") -> N°-0030-2024 | D43: xxxxxxxx | E43: Koto | F43: Alpha oumar gabonais | G43: Dowsaré | H43: Togo | I43: xxxxxxxx | J43: 4000 | K43: 1000 | M43: =IF(L43>=0,"A JOUR",($L43*($M$12))) -> A JOUR | O43: =IF(L43>=0,"A JOUR",($L43*($M$12+J43)+N43)) -> A JOUR | P43: x | Q43: x | T43: #N/A | U43: #N/A | V43: #N/A | W43: #N/A | X43: #N/A | Y43: 0 | Z43: 0 | AA43: 0 | AB43: 0 | AC43: 0 | AD43: 0
B44: 31 | C44: =CONCATENATE("N°-","00",B44,"-2024") -> N°-0031-2024 | D44: +24102253222 | E44: Koto | F44: Alpha oumar ibn karamoko Daouda | G44: Pétel | H44: Gabon | I44: +241 02 25 32 22 | J44: 5000 | K44: N/A | M44: =IF(L44>=0,"A JOUR",($L44*($M$12))) -> A JOUR | O44: =IF(L44>=0,"A JOUR",($L44*($M$12+J44)+N44)) -> A JOUR | Q44: x | T44: #N/A | U44: #N/A | V44: #N/A | W44: #N/A | X44: #N/A | Y44: 0 | Z44: 0 | AA44: 0 | AB44: 0 | AC44: 0 | AD44: 0
B45: 32 | C45: =CONCATENATE("N°-","00",B45,"-2024") -> N°-0032-2024 | D45: 774997775 | E45: Koto | F45: Alpha Oumar togolais | G45: Dowsaré | H45: Dakar | I45: 77 499 77 75 | J45: 2000 | K45: 1000 | L45: =2-1 -> 1 | M45: =IF(L45>=0,"A JOUR",($L45*($M$12))) -> A JOUR | N45: =+L45*J45 -> 2000 | O45: =IF(L45>=0,"A JOUR",($L45*($M$12+J45)+N45)) -> A JOUR | P45: x | Q45: x | T45: A JOUR | Y45: 0 | Z45: 0 | AA45: 0 | AB45: 0 | AC45: 0 | AD45: 0
B46: 33 | C46: =CONCATENATE("N°-","00",B46,"-2024") -> N°-0033-2024 | E46: Mr | F46: Alpha Saliou ibn Elhadji M. Woury | G46: Pétel | H46: Guinée | K46: 1000 | L46: VG | M46: =IF(L46>=0,"A JOUR",($L46*($M$12))) -> A JOUR | O46: =IF(L46>=0,"A JOUR",($L46*($M$12+J46)+N46)) -> A JOUR | R46: VG | T46: #N/A | U46: #N/A | V46: #N/A | W46: #N/A | X46: #N/A | Y46: 0 | Z46: 0 | AA46: 0 | AB46: 0 | AC46: 0 | AD46: 0
B47: 34 | C47: =CONCATENATE("N°-","00",B47,"-2024") -> N°-0034-2024 | D47: 776709584 | E47: Oustaz | F47: Amadou | G47: Bowell | H47: Guinée | I47: 77 670 95 84 | J47: 2500 | K47: 1000 | L47: 0 | M47: =IF(L47>=0,"A JOUR",($L47*($M$12))) -> A JOUR | O47: =IF(L47>=0,"A JOUR",($L47*($M$12+J47)+N47)) -> A JOUR | P47: x | Q47: x | R47: NT | T47: #N/A | U47: GUINEE | Y47: 0 | Z47: 0 | AA47: 0 | AB47: 0 | AC47: 0 | AD47: 0
B48: 35 | C48: =CONCATENATE("N°-","00",B48,"-2024") -> N°-0035-2024 | D48: 776623868 | E48: Mr | F48: Amadou bobo (mariste) | G48: Dowsaré | H48: Dakar | I48: 77 662 38 68 | J48: 2000 | K48: 1000 | L48: 0 | M48: =IF(L48>=0,"A JOUR",($L48*($M$12))) -> A JOUR | O48: =IF(L48>=0,"A JOUR",($L48*($M$12+J48)+N48)) -> A JOUR | P48: x | Q48: x | T48: A JOUR | Y48: 0 | Z48: 0 | AA48: 0 | AB48: 0 | AC48: 0 | AD48: 0
B49: 36 | C49: =CONCATENATE("N°-","00",B49,"-2024") -> N°-0036-2024 | D49: 774272026 | E49: Koto | F49: Amadou bobo N°1 | G49: Dowsaré | H49: Dakar | I49: 77 427 20 26 | J49: 2000 | K49: 1000 | L49: =+SUM($Y49:$AQ49) -> -4 | M49: =IF(L49>=0,"A JOUR",($L49*($M$12))) -> -8000 | O49: =IF(L49>=0,"A JOUR",($L49*($M$12+J49)+N49)) -> -16000 | P49: x | Q49: x | T49: #N/A | U49: #N/A | V49: #N/A | W49: 2000 | X49: 4 | Y49: 0 | Z49: -1 | AA49: -1 | AB49: -1 | AC49: 0 | AD49: -1
B50: 37 | C50: =CONCATENATE("N°-","00",B50,"-2024") -> N°-0037-2024 | D50: xxxxxxxx | E50: Mr | F50: Amadou diogo | G50: Gobihi | H50: Guinée | I50: xxxxxxxx | J50: 2000 | K50: 1000 | M50: =IF(L50>=0,"A JOUR",($L50*($M$12))) -> A JOUR | O50: =IF(L50>=0,"A JOUR",($L50*($M$12+J50)+N50)) -> A JOUR | Q50: x | R50: VG | T50: #N/A | U50: #N/A | V50: #N/A | W50: #N/A | X50: #N/A | Y50: 0 | Z50: 0 | AA50: 0 | AB50: 0 | AC50: 0 | AD50: 0
B51: 38 | C51: =CONCATENATE("N°-","00",B51,"-2024") -> N°-0038-2024 | D51: 775218573 | E51: Mr | F51: Amadou Djoulde - PR | G51: Dowsaré | H51: Dakar | I51: 77 521 85 73 | J51: 3000 | K51: 1000 | L51: 0 | M51: =IF(L51>=0,"A JOUR",($L51*($M$12))) -> A JOUR | O51: =IF(L51>=0,"A JOUR",($L51*($M$12+J51)+N51)) -> A JOUR | P51: x | Q51: x | T51: A JOUR | Y51: 0 | Z51: 0 | AA51: 0 | AB51: 0 | AC51: 0 | AD51: 0
B52: 39 | C52: =CONCATENATE("N°-","00",B52,"-2024") -> N°-0039-2024 | D52: 778550234 | E52: Koto | F52: Amadou korka CC | G52: Diabbhéhi | H52: Dakar | I52: 77 855 02 34 | J52: 2000 | K52: 1000 | L52: 0 | M52: =IF(L52>=0,"A JOUR",($L52*($M$12))) -> A JOUR | O52: =IF(L52>=0,"A JOUR",($L52*($M$12+J52)+N52)) -> A JOUR | P52: x | Q52: x | T52: A JOUR | Y52: 0 | Z52: 0 | AA52: 0 | AB52: 0 | AC52: 0 | AD52: 0
B53: 40 | C53: =CONCATENATE("N°-","00",B53,"-2024") -> N°-0040-2024 | D53: 778151869 | E53: Koto | F53: Amadou korka | G53: Biilaa | H53: Dakar | I53: 77 815 18 69 | J53: 1000 | K53: 1000 | L53: 0 | M53: =IF(L53>=0,"A JOUR",($L53*($M$12))) -> A JOUR | O53: =IF(L53>=0,"A JOUR",($L53*($M$12+J53)+N53)) -> A JOUR | P53: x | Q53: x | T53: A JOUR | Y53: 0 | Z53: 0 | AA53: 0 | AB53: 0 | AC53: 0 | AD53: 0
B54: 41 | C54: =CONCATENATE("N°-","00",B54,"-2024") -> N°-0041-2024 | D54: 786333092 | E54: Mr | F54: Amadou korka | G54: Porétély | H54: Dakar | I54: 78 633 30 92 | J54: 1000 | K54: N/A | L54: =+SUM($Y54:$AQ54) -> -21 | M54: =IF(L54>=0,"A JOUR",($L54*($M$12))) -> -42000 | O54: =IF(L54>=0,"A JOUR",($L54*($M$12+J54)+N54)) -> -63000 | P54: x | Q54: x | S54: Avance 8000 | T54: #N/A | U54: #N/A | V54: #N/A | W54: 1000 | X54: 21 | Y54: -17 | Z54: -1 | AA54: -1 | AB54: -1 | AC54: 0 | AD54: -1
B55: 42 | C55: =CONCATENATE("N°-","00",B55,"-2024") -> N°-0042-2024 | D55: 778021767 | E55: Mr | F55: Amadou mouctar | G55: Yayemadou | H55: Dakar | I55: 77 802 17 67 | J55: 2000 | K55: N/A | L55: =+SUM($Y55:$AQ55) -> -45 | M55: =IF(L55>=0,"A JOUR",($L55*($M$12))) -> -90000 | O55: =IF(L55>=0,"A JOUR",($L55*($M$12+J55)+N55)) -> -180000 | P55: x | Q55: x | T55: #N/A | U55: #N/A | V55: #N/A | W55: 2000 | X55: 45 | Y55: -41 | Z55: -1 | AA55: -1 | AB55: -1 | AC55: 0 | AD55: -1
B56: 43 | C56: =CONCATENATE("N°-","00",B56,"-2024") -> N°-0043-2024 | D56: 771009642 | E56: Mr | F56: Amadou mouctar ibn Elhadji Ibrahima | G56: Pétel | H56: Dakar | I56: 77 100 96 42 | J56: 1000 | K56: N/A | L56: =+SUM($Y56:$AQ56) -> -45 | M56: =IF(L56>=0,"A JOUR",($L56*($M$12))) -> -90000 | O56: =IF(L56>=0,"A JOUR",($L56*($M$12+J56)+N56)) -> -135000 | Q56: x | T56: #N/A | U56: #N/A | V56: #N/A | W56: 1000 | X56: 45 | Y56: -41 | Z56: -1 | AA56: -1 | AB56: -1 | AC56: 0 | AD56: -1
B57: 44 | C57: =CONCATENATE("N°-","00",B57,"-2024") -> N°-0044-2024 | D57: 778637835 | E57: Mr | F57: Amadou tanou | G57: Dieydiyabhe | H57: Dakar | I57: 77 863 78 35 | J57: 1000 | K57: 1000 | L57: 0 | M57: =IF(L57>=0,"A JOUR",($L57*($M$12))) -> A JOUR | O57: =IF(L57>=0,"A JOUR",($L57*($M$12+J57)+N57)) -> A JOUR | P57: x | Q57: x | R57: NT | T57: #N/A | U57: #N/A | V57: NT | Y57: 0 | Z57: 0 | AA57: 0 | AB57: 0 | AC57: 0 | AD57: 0
B58: 45 | C58: =CONCATENATE("N°-","00",B58,"-2024") -> N°-0045-2024 | D58: 773499877 | E58: Mody | F58: Amadou TC | G58: Mamasamba | H58: Dakar | I58: 77 349 98 77 | J58: 2000 | K58: 1000 | L58: 0 | M58: =IF(L58>=0,"A JOUR",($L58*($M$12))) -> A JOUR | O58: =IF(L58>=0,"A JOUR",($L58*($M$12+J58)+N58)) -> A JOUR | P58: x | Q58: x | T58: #N/A | U58: GUINEE | Y58: 0 | Z58: 0 | AA58: 0 | AB58: 0 | AC58: 0 | AD58: 0
B59: 46 | C59: =CONCATENATE("N°-","00",B59,"-2024") -> N°-0046-2024 | D59: xxxxxxxx | E59: Mr | F59: Amadou Woury | G59: Ka missidé | H59: Côte d'ivoire | I59: xxxxxxxx | J59: 2000 | K59: 1000 | L59: 0 | M59: =IF(L59>=0,"A JOUR",($L59*($M$12))) -> A JOUR | O59: =IF(L59>=0,"A JOUR",($L59*($M$12+J59)+N59)) -> A JOUR | Q59: x | T59: #N/A | U59: #N/A | V59: #N/A | W59: #N/A | X59: #N/A | Y59: 0 | Z59: 0 | AA59: 0 | AB59: 0 | AC59: 0 | AD59: 0
B60: 47 | C60: =CONCATENATE("N°-","00",B60,"-2024") -> N°-0047-2024 | D60: 772392440 | E60: Mr | F60: Amadou Woury | G60: Yayemadou | H60: Dakar | I60: 77 239 24 40 | J60: 2000 | K60: N/A | L60: =+SUM($Y60:$AQ60) -> -40 | M60: =IF(L60>=0,"A JOUR",($L60*($M$12))) -> -80000 | O60: =IF(L60>=0,"A JOUR",($L60*($M$12+J60)+N60)) -> -160000 | Q60: x | T60: #N/A | U60: #N/A | V60: #N/A | W60: 2000 | X60: 40 | Y60: -36 | Z60: -1 | AA60: -1 | AB60: -1 | AC60: 0 | AD60: -1
B61: 48 | C61: =CONCATENATE("N°-","00",B61,"-2024") -> N°-0048-2024 | D61: 779593845 | E61: Mr | F61: Boubacar | G61: Biilaa | H61: Dakar | I61: 77 959 38 45 | J61: 1000 | K61: N/A | L61: =+SUM($Y61:$AQ61) -> -5 | M61: =IF(L61>=0,"A JOUR",($L61*($M$12))) -> -10000 | O61: =IF(L61>=0,"A JOUR",($L61*($M$12+J61)+N61)) -> -15000 | P61: x | Q61: x | T61: #N/A | U61: #N/A | V61: #N/A | W61: 1000 | X61: 5 | Y61: -1 | Z61: -1 | AA61: -1 | AB61: -1 | AC61: 0 | AD61: -1
B62: 49 | C62: =CONCATENATE("N°-","00",B62,"-2024") -> N°-0049-2024 | D62: 778018331 | E62: Mr | F62: Boubacar (mariste ) | G62: Kourawoye | H62: Dakar | I62: 77 801 83 31 | J62: 2000 | K62: 1000 | L62: 0 | M62: =IF(L62>=0,"A JOUR",($L62*($M$12))) -> A JOUR | O62: =IF(L62>=0,"A JOUR",($L62*($M$12+J62)+N62)) -> A JOUR | P62: x | Q62: x | T62: #N/A | U62: #N/A | V62: #N/A | W62: #N/A | X62: #N/A | Y62: 0 | Z62: 0 | AA62: 0 | AB62: 0 | AC62: 0 | AD62: 0
B63: 50 | C63: =CONCATENATE("N°-","00",B63,"-2024") -> N°-0050-2024 | D63: 774494968 | E63: Mr | F63: Boubacar ibn bappa bala CC | G63: Pétel | H63: Dakar | I63: 77 449 49 68 | J63: 3000 | K63: 1000 | L63: 0 | M63: =IF(L63>=0,"A JOUR",($L63*($M$12))) -> A JOUR | O63: =IF(L63>=0,"A JOUR",($L63*($M$12+J63)+N63)) -> A JOUR | P63: x | Q63: x | T63: A JOUR | Y63: 0 | Z63: 0 | AA63: 0 | AB63: 0 | AC63: 0 | AD63: 0
B64: 51 | C64: =CONCATENATE("N°-","00",B64,"-2024") -> N°-0051-2024 | D64: 779862991 | E64: Koto | F64: Boubacar ibn Elhadji Ibrahima | G64: Pétel | H64: Dakar | I64: 77 986 29 91 | J64: 2000 | K64: N/A | L64: 0 | M64: =IF(L64>=0,"A JOUR",($L64*($M$12))) -> A JOUR | O64: =IF(L64>=0,"A JOUR",($L64*($M$12+J64)+N64)) -> A JOUR | Q64: x | T64: A JOUR | Y64: 0 | Z64: 0 | AA64: 0 | AB64: 0 | AC64: 0 | AD64: 0
B65: 52 | C65: =CONCATENATE("N°-","00",B65,"-2024") -> N°-0052-2024 | D65: 776779519 | E65: Mr | F65: Boubacar Kowloun | G65: Kowloune | H65: Dakar | I65: 77 677 95 19 | J65: 1000 | K65: 1000 | L65: 0 | M65: =IF(L65>=0,"A JOUR",($L65*($M$12))) -> A JOUR | O65: =IF(L65>=0,"A JOUR",($L65*($M$12+J65)+N65)) -> A JOUR | T65: A JOUR | Y65: 0 | Z65: 0 | AA65: 0 | AB65: 0 | AC65: 0 | AD65: 0
B66: 53 | C66: =CONCATENATE("N°-","00",B66,"-2024") -> N°-0053-2024 | D66: 773137431 | E66: Koto | F66: Boubacar méékohi | G66: Dowsaré | H66: Dakar | I66: 77 313 74 31 | J66: 2000 | K66: 1000 | L66: =+SUM($Y66:$AQ66) -> -2 | M66: =IF(L66>=0,"A JOUR",($L66*($M$12))) -> -4000 | O66: =IF(L66>=0,"A JOUR",($L66*($M$12+J66)+N66)) -> -8000 | P66: x | Q66: x | R66: NT | T66: #N/A | U66: #N/A | V66: #N/A | W66: 2000 | X66: 2 | Y66: 0 | Z66: 0 | AA66: 0 | AB66: -1 | AC66: 0 | AD66: -1
B67: 54 | C67: =CONCATENATE("N°-","00",B67,"-2024") -> N°-0054-2024 | E67: Mr | F67: Boubacar Ngarahi | G67: Dowsaré | H67: Dakar | J67: 1000 | K67: 1000 | M67: =IF(L67>=0,"A JOUR",($L67*($M$12))) -> A JOUR | O67: =IF(L67>=0,"A JOUR",($L67*($M$12+J67)+N67)) -> A JOUR | T67: #N/A | U67: #N/A | V67: #N/A | W67: #N/A | X67: #N/A | Y67: 0 | Z67: 0 | AA67: 0 | AB67: 0 | AC67: 0 | AD67: 0
B68: 55 | C68: =CONCATENATE("N°-","00",B68,"-2024") -> N°-0055-2024 | D68: 776669090 | E68: Mr | F68: Bourhane | G68: Pétel | H68: Dakar | I68: 77 666 90 90 | J68: 1000 | K68: 1000 | L68: =+SUM($Y68:$AQ68) -> -8 | M68: =IF(L68>=0,"A JOUR",($L68*($M$12))) -> -16000 | O68: =IF(L68>=0,"A JOUR",($L68*($M$12+J68)+N68)) -> -24000 | P68: x | Q68: x | T68: #N/A | U68: #N/A | V68: #N/A | W68: 1000 | X68: 8 | Y68: -8 | Z68: 0 | AA68: 0 | AB68: 0 | AC68: 0 | AD68: 0
B69: 56 | C69: =CONCATENATE("N°-","00",B69,"-2024") -> N°-0056-2024 | E69: Mr | F69: Cheikh ibn Elhadji Aliou | G69: Kourawoye | H69: Dakar | J69: N/A | K69: N/A | M69: =IF(L69>=0,"A JOUR",($L69*($M$12))) -> A JOUR | O69: =IF(L69>=0,"A JOUR",($L69*($M$12+J69)+N69)) -> A JOUR | P69: x | Q69: x | R69: NT | T69: #N/A | U69: #N/A | V69: #N/A | W69: #N/A | X69: #N/A | Y69: 0 | Z69: 0 | AA69: 0 | AB69: 0 | AC69: 0 | AD69: 0
B70: 57 | C70: =CONCATENATE("N°-","00",B70,"-2024") -> N°-0057-2024 | D70: 774885353 | E70: Mr | F70: Cheikh tidiane ibn Elhadji Ibrahima | G70: Pétel | H70: Dakar | I70: 77 488 53 53 | J70: 1000 | K70: 1000 | L70: =+SUM($Y70:$AQ70) -> -4 | M70: =IF(L70>=0,"A JOUR",($L70*($M$12))) -> -8000 | O70: =IF(L70>=0,"A JOUR",($L70*($M$12+J70)+N70)) -> -12000 | P70: x | Q70: x | T70: #N/A | U70: #N/A | V70: #N/A | W70: 1000 | X70: 4 | Y70: 0 | Z70: -1 | AA70: -1 | AB70: -1 | AC70: 0 | AD70: -1
B71: 58 | C71: =CONCATENATE("N°-","00",B71,"-2024") -> N°-0058-2024 | E71: Mr | F71: Daouda | G71: Dowsaré | H71: Casamance | J71: N/A | K71: N/A | M71: =IF(L71>=0,"A JOUR",($L71*($M$12))) -> A JOUR | O71: =IF(L71>=0,"A JOUR",($L71*($M$12+J71)+N71)) -> A JOUR | Q71: x | T71: #N/A | U71: #N/A | V71: #N/A | W71: #N/A | X71: #N/A | Y71: 0 | Z71: 0 | AA71: 0 | AB71: 0 | AC71: 0 | AD71: 0
B72: 59 | C72: =CONCATENATE("N°-","00",B72,"-2024") -> N°-0059-2024 | D72: 774767085 | E72: Mr | F72: Daouda (Parcelles) | G72: Kourawoye | H72: Dakar | I72: 77 476 70 85 | J72: 1000 | K72: 1000 | L72: 0 | M72: =IF(L72>=0,"A JOUR",($L72*($M$12))) -> A JOUR | O72: =IF(L72>=0,"A JOUR",($L72*($M$12+J72)+N72)) -> A JOUR | P72: x | Q72: x | T72: A JOUR | Y72: 0 | Z72: 0 | AA72: 0 | AB72: 0 | AC72: 0 | AD72: 0
B73: 60 | C73: =CONCATENATE("N°-","00",B73,"-2024") -> N°-0060-2024 | E73: Mr | F73: Daouda ibn Elhadji M. Woury | G73: Pétel | H73: Guinée | J73: N/A | K73: 1000 | L73: VG | M73: =IF(L73>=0,"A JOUR",($L73*($M$12))) -> A JOUR | O73: =IF(L73>=0,"A JOUR",($L73*($M$12+J73)+N73)) -> A JOUR | P73: x | R73: VG | T73: #N/A | U73: #N/A | V73: #N/A | W73: #N/A | X73: #N/A | Y73: 0 | Z73: 0 | AA73: 0 | AB73: 0 | AC73: 0 | AD73: 0
B74: 61 | C74: =CONCATENATE("N°-","00",B74,"-2024") -> N°-0061-2024 | D74: 776790248 | E74: Mr | F74: Elh ibrahima N°2 ibn karamoko Daouda DC | G74: Pétel | H74: Dakar | I74: 77 679 02 48 | J74: 2000 | K74: 1000 | L74: 0 | M74: =IF(L74>=0,"A JOUR",($L74*($M$12))) -> A JOUR | O74: =IF(L74>=0,"A JOUR",($L74*($M$12+J74)+N74)) -> A JOUR | P74: x | Q74: x | T74: A JOUR | Y74: 0 | Z74: 0 | AA74: 0 | AB74: 0 | AC74: 0 | AD74: 0
B75: 62 | C75: =CONCATENATE("N°-","00",B75,"-2024") -> N°-0062-2024 | D75: 781656755 | E75: Mr | F75: Elhadji abdoulaye | G75: Dieydiyabhe | H75: Dakar | I75: 78 165 67 55 | J75: 1000 | K75: 1000 | L75: 0 | M75: =IF(L75>=0,"A JOUR",($L75*($M$12))) -> A JOUR | O75: =IF(L75>=0,"A JOUR",($L75*($M$12+J75)+N75)) -> A JOUR | P75: x | Q75: x | S75: 78 326 04 13 | T75: A JOUR | Y75: 0 | Z75: 0 | AA75: 0 | AB75: 0 | AC75: 0 | AD75: 0
B76: 63 | C76: =CONCATENATE("N°-","00",B76,"-2024") -> N°-0063-2024 | D76: 781313842 | E76: Mr | F76: Elhadji ablaye coiffeur | G76: Dieydiyabhe | H76: Dakar | I76: 78 131 38 42 | J76: 1000 | K76: 1000 | L76: 0 | M76: =IF(L76>=0,"A JOUR",($L76*($M$12))) -> A JOUR | O76: =IF(L76>=0,"A JOUR",($L76*($M$12+J76)+N76)) -> A JOUR | P76: x | Q76: x | T76: A JOUR | Y76: 0 | Z76: 0 | AA76: 0 | AB76: 0 | AC76: 0 | AD76: 0
B77: 64 | C77: =CONCATENATE("N°-","00",B77,"-2024") -> N°-0064-2024 | D77: xxxxxxxx | E77: Mr | F77: Elhadji aliou ibn bappa Siradio | G77: Dowsaré | H77: France | I77: xxxxxxxx | J77: 5000 | K77: 1000 | M77: =IF(L77>=0,"A JOUR",($L77*($M$12))) -> A JOUR | O77: =IF(L77>=0,"A JOUR",($L77*($M$12+J77)+N77)) -> A JOUR | Q77: x | T77: #N/A | U77: #N/A | V77: #N/A | W77: #N/A | X77: #N/A | Y77: 0 | Z77: 0 | AA77: 0 | AB77: 0 | AC77: 0 | AD77: 0
B78: 65 | C78: =CONCATENATE("N°-","00",B78,"-2024") -> N°-0065-2024 | D78: 773012928 | E78: Mr | F78: Elhadji amadou | G78: Biilaa | H78: Dakar | I78: 77 301 29 28 | J78: 1000 | K78: 1000 | L78: =+SUM($Y78:$AQ78) -> -34 | M78: =IF(L78>=0,"A JOUR",($L78*($M$12))) -> -68000 | O78: =IF(L78>=0,"A JOUR",($L78*($M$12+J78)+N78)) -> -102000 | P78: x | Q78: x | T78: #N/A | U78: #N/A | V78: #N/A | W78: 1000 | X78: 34 | Y78: -30 | Z78: -1 | AA78: -1 | AB78: -1 | AC78: 0 | AD78: -1
B79: 66 | C79: =CONCATENATE("N°-","00",B79,"-2024") -> N°-0066-2024 | D79: 761722302 | E79: Mr | F79: Elhadji Boubacar mo moussou | G79: Pétel | H79: Dakar | I79: 76 172 23 02 | J79: 1000 | K79: 1000 | L79: =+SUM($Y79:$AQ79) -> -44 | M79: =IF(L79>=0,"A JOUR",($L79*($M$12))) -> -88000 | O79: =IF(L79>=0,"A JOUR",($L79*($M$12+J79)+N79)) -> -132000 | P79: x | Q79: x | S79: 2 FOIS | T79: #N/A | U79: #N/A | V79: #N/A | W79: 1000 | X79: 44 | Y79: -41 | Z79: -1 | AA79: -1 | AB79: 0 | AC79: 0 | AD79: -1
B80: 67 | C80: =CONCATENATE("N°-","00",B80,"-2024") -> N°-0067-2024 | D80: 622417844 | E80: Mr | F80: Elhadji douka chauffeur | G80: Dowsaré | H80: Guinée | I80: 622 41 78 44 | J80: 2000 | K80: 1000 | L80: 0 | M80: =IF(L80>=0,"A JOUR",($L80*($M$12))) -> A JOUR | O80: =IF(L80>=0,"A JOUR",($L80*($M$12+J80)+N80)) -> A JOUR | P80: x | Q80: x | R80: VG | T80: #N/A | U80: GUINEE | Y80: 0 | Z80: 0 | AA80: 0 | AB80: 0 | AC80: 0 | AD80: 0
B81: 68 | C81: =CONCATENATE("N°-","00",B81,"-2024") -> N°-0068-2024 | D81: 784087096 | E81: Mr | F81: Elhadji ibrahima ibn Elhadji M. Woury | G81: Pétel | H81: Dakar | I81: 78 408 70 96 | J81: 1000 | K81: 1000 | L81: =+SUM($Y81:$AQ81) -> -4 | M81: =IF(L81>=0,"A JOUR",($L81*($M$12))) -> -8000 | O81: =IF(L81>=0,"A JOUR",($L81*($M$12+J81)+N81)) -> -12000 | Q81: x | T81: #N/A | U81: #N/A | V81: #N/A | W81: 1000 | X81: 4 | Y81: 0 | Z81: -1 | AA81: -1 | AB81: -1 | AC81: 0 | AD81: -1
B82: 69 | C82: =CONCATENATE("N°-","00",B82,"-2024") -> N°-0069-2024 | D82: 776549856 | E82: Bappa | F82: Elhadji siradio | G82: Dowsaré | H82: Dakar | I82: 77 654 98 56 | J82: 5000 | K82: N/A | L82: 0 | M82: =IF(L82>=0,"A JOUR",($L82*($M$12))) -> A JOUR | O82: =IF(L82>=0,"A JOUR",($L82*($M$12+J82)+N82)) -> A JOUR | Q82: x | T82: A JOUR | Y82: 0 | Z82: 0 | AA82: 0 | AB82: 0 | AC82: 0 | AD82: 0
B83: 70 | C83: =CONCATENATE("N°-","00",B83,"-2024") -> N°-0070-2024 | D83: xxxxxxxx | E83: Mr | F83: Elhadji woury | G83: Dowsaré | H83: Gambie | I83: xxxxxxxx | J83: 2000 | K83: 1000 | M83: =IF(L83>=0,"A JOUR",($L83*($M$12))) -> A JOUR | O83: =IF(L83>=0,"A JOUR",($L83*($M$12+J83)+N83)) -> A JOUR | Q83: x | T83: #N/A | U83: #N/A | V83: #N/A | W83: #N/A | X83: #N/A | Y83: 0 | Z83: 0 | AA83: 0 | AB83: 0 | AC83: 0 | AD83: 0
B84: 71 | C84: =CONCATENATE("N°-","00",B84,"-2024") -> N°-0071-2024 | D84: 783260413 | E84: Mr | F84: Elhadji woury ibn bappa korka & yan safietou | G84: Dowsaré | H84: Dakar | I84: 78 326 04 13 | J84: 1000 | K84: 1000 | L84: =+SUM($Y84:$AQ84) -> -4 | M84: =IF(L84>=0,"A JOUR",($L84*($M$12))) -> -8000 | O84: =IF(L84>=0,"A JOUR",($L84*($M$12+J84)+N84)) -> -12000 | P84: x | Q84: x | T84: #N/A | U84: #N/A | V84: #N/A | W84: 1000 | X84: 4 | Y84: 0 | Z84: -1 | AA84: -1 | AB84: -1 | AC84: 0 | AD84: -1
B85: 72 | C85: =CONCATENATE("N°-","00",B85,"-2024") -> N°-0072-2024 | D85: +393314576228 | E85: Mr | F85: Elhadji woury ibn Elhadji Ibrahima | G85: Pétel | H85: Italie | I85: +39 33 14 57 62 28 | J85: 5000 | K85: N/A | M85: =IF(L85>=0,"A JOUR",($L85*($M$12))) -> A JOUR | O85: =IF(L85>=0,"A JOUR",($L85*($M$12+J85)+N85)) -> A JOUR | Q85: x | T85: #N/A | U85: #N/A | V85: #N/A | W85: #N/A | X85: #N/A | Y85: 0 | Z85: 0 | AA85: 0 | AB85: 0 | AC85: 0 | AD85: 0
B86: 73 | C86: =CONCATENATE("N°-","00",B86,"-2024") -> N°-0073-2024 | D86: 776049360 | E86: Mr | F86: Elhadji woury parcelles | G86: Kourawoye | H86: Dakar | I86: 77 604 93 60 | J86: 1000 | K86: 1000 | L86: 0 | M86: =IF(L86>=0,"A JOUR",($L86*($M$12))) -> A JOUR | O86: =IF(L86>=0,"A JOUR",($L86*($M$12+J86)+N86)) -> A JOUR | P86: x | Q86: x | T86: A JOUR | Y86: 0 | Z86: 0 | AA86: 0 | AB86: 0 | AC86: 0 | AD86: 0
B87: 74 | C87: =CONCATENATE("N°-","00",B87,"-2024") -> N°-0074-2024 | D87: 774965371 | E87: Mr | F87: Elhadji woury petel ibn MD hamidou | G87: Pétel | H87: Dakar | I87: 77 496 53 71 | J87: 1000 | K87: 1000 | L87: =+SUM($Y87:$AQ87) -> -3 | M87: =IF(L87>=0,"A JOUR",($L87*($M$12))) -> -6000 | O87: =IF(L87>=0,"A JOUR",($L87*($M$12+J87)+N87)) -> -9000 | P87: x | Q87: x | T87: #N/A | U87: #N/A | V87: #N/A | W87: 1000 | X87: 3 | Y87: 0 | Z87: 0 | AA87: -1 | AB87: -1 | AC87: 0 | AD87: -1
B88: 75 | C88: =CONCATENATE("N°-","00",B88,"-2024") -> N°-0075-2024 | E88: Mr | F88: Elhaji aliou (lazo) | G88: Kourawoye | H88: Guinée | J88: N/A | K88: N/A | L88: VG | M88: =IF(L88>=0,"A JOUR",($L88*($M$12))) -> A JOUR | O88: =IF(L88>=0,"A JOUR",($L88*($M$12+J88)+N88)) -> A JOUR | P88: x | R88: VG | T88: #N/A | U88: #N/A | V88: #N/A | W88: #N/A | X88: #N/A | Y88: 0 | Z88: 0 | AA88: 0 | AB88: 0 | AC88: 0 | AD88: 0
B89: 76 | C89: =CONCATENATE("N°-","00",B89,"-2024") -> N°-0076-2024 | D89: 773851455 | E89: Mr | F89: Hamidou | G89: Dowsaré | H89: Dakar | I89: 77 385 14 55 | J89: 1000 | K89: 1000 | L89: 0 | M89: =IF(L89>=0,"A JOUR",($L89*($M$12))) -> A JOUR | O89: =IF(L89>=0,"A JOUR",($L89*($M$12+J89)+N89)) -> A JOUR | P89: x | Q89: x | T89: A JOUR | Y89: 0 | Z89: 0 | AA89: 0 | AB89: 0 | AC89: 0 | AD89: 0
B90: 77 | C90: =CONCATENATE("N°-","00",B90,"-2024") -> N°-0077-2024 | D90: 776232888 | E90: Oustaz | F90: Ibrahima | G90: Daandé Mboully | H90: Dakar | I90: 77 623 28 88 | J90: 2000 | K90: 1000 | L90: 0 | M90: =IF(L90>=0,"A JOUR",($L90*($M$12))) -> A JOUR | O90: =IF(L90>=0,"A JOUR",($L90*($M$12+J90)+N90)) -> A JOUR | P90: x | Q90: x | T90: A JOUR | Y90: 0 | Z90: 0 | AA90: 0 | AB90: 0 | AC90: 0 | AD90: 0
B91: 78 | C91: =CONCATENATE("N°-","00",B91,"-2024") -> N°-0078-2024 | D91: 775220275 | E91: Koto | F91: Ibrahima | G91: Kourawoye | H91: Dakar | I91: 77 522 02 75 | J91: 2000 | K91: N/A | L91: =+SUM($Y91:$AQ91) -> -41 | M91: =IF(L91>=0,"A JOUR",($L91*($M$12))) -> -82000 | O91: =IF(L91>=0,"A JOUR",($L91*($M$12+J91)+N91)) -> -164000 | P91: x | Q91: x | T91: #N/A | U91: #N/A | V91: #N/A | W91: 2000 | X91: 41 | Y91: -37 | Z91: -1 | AA91: -1 | AB91: -1 | AC91: 0 | AD91: -1
B92: 79 | C92: =CONCATENATE("N°-","00",B92,"-2024") -> N°-0079-2024 | D92: 778018660 | E92: Mr | F92: Ibrahima | G92: Diabbhéhi | H92: Guinée | I92: 77 801 86 60 | J92: 1000 | K92: 1000 | L92: =+SUM($Y92:$AQ92) -> -14 | M92: =IF(L92>=0,"A JOUR",($L92*($M$12))) -> -28000 | O92: =IF(L92>=0,"A JOUR",($L92*($M$12+J92)+N92)) -> -42000 | P92: x | Q92: x | R92: NT | T92: #N/A | U92: #N/A | V92: #N/A | W92: 1000 | X92: 14 | Y92: -10 | Z92: -1 | AA92: -1 | AB92: -1 | AC92: 0 | AD92: -1
B93: 80 | C93: =CONCATENATE("N°-","00",B93,"-2024") -> N°-0080-2024 | D93: 773809784 | E93: Koto | F93: Ibrahima | G93: Leysaré | H93: Dakar | I93: 77 380 97 84 | J93: 2000 | K93: 1000 | L93: 0 | M93: =IF(L93>=0,"A JOUR",($L93*($M$12))) -> A JOUR | O93: =IF(L93>=0,"A JOUR",($L93*($M$12+J93)+N93)) -> A JOUR | P93: x | Q93: x | T93: #N/A | U93: GUINEE | Y93: 0 | Z93: 0 | AA93: 0 | AB93: 0 | AC93: 0 | AD93: 0
B94: 81 | C94: =CONCATENATE("N°-","00",B94,"-2024") -> N°-0081-2024 | D94: 777551504 | E94: Koto | F94: Ibrahima | G94: Porétély | H94: Dakar | I94: 77 755 15 04 | J94: 2000 | K94: 1000 | L94: =+SUM($Y94:$AQ94) -> -35 | M94: =IF(L94>=0,"A JOUR",($L94*($M$12))) -> -70000 | O94: =IF(L94>=0,"A JOUR",($L94*($M$12+J94)+N94)) -> -140000 | P94: x | Q94: x | T94: #N/A | U94: #N/A | V94: #N/A | W94: 2000 | X94: 35 | Y94: -31 | Z94: -1 | AA94: -1 | AB94: -1 | AC94: 0 | AD94: -1
B95: 82 | C95: =CONCATENATE("N°-","00",B95,"-2024") -> N°-0082-2024 | D95: 788380743 | E95: Mr | F95: Ibrahima ibn bappa Siradio | G95: Dowsaré | H95: Dakar | I95: 78 838 07 43 | J95: 1000 | K95: 1000 | L95: 0 | M95: =IF(L95>=0,"A JOUR",($L95*($M$12))) -> A JOUR | O95: =IF(L95>=0,"A JOUR",($L95*($M$12+J95)+N95)) -> A JOUR | T95: A JOUR | Y95: 0 | Z95: 0 | AA95: 0 | AB95: 0 | AC95: 0 | AD95: 0
B96: 83 | C96: =CONCATENATE("N°-","00",B96,"-2024") -> N°-0083-2024 | D96: 781292637 | E96: Koto | F96: Ibrahima KZA ibnou samara | G96: Dowsaré | H96: Casamance | I96: 78 129 26 37 | J96: 2000 | K96: 1000 | L96: =4-3 -> 1 | M96: =IF(L96>=0,"A JOUR",($L96*($M$12))) -> A JOUR | N96: =+L96*J96 -> 2000 | O96: =IF(L96>=0,"A JOUR",($L96*($M$12+J96)+N96)) -> A JOUR | P96: x | Q96: x | T96: A JOUR | Y96: 0 | Z96: 0 | AA96: 0 | AB96: 0 | AC96: 0 | AD96: 0
B97: 84 | C97: =CONCATENATE("N°-","00",B97,"-2024") -> N°-0084-2024 | D97: 774370979 | E97: Koto | F97: Ibrahima N°1 ibn bappa bala | G97: Pétel | H97: Dakar | I97: 77 437 09 79 | J97: 2000 | K97: 1000 | L97: 0 | M97: =IF(L97>=0,"A JOUR",($L97*($M$12))) -> A JOUR | O97: =IF(L97>=0,"A JOUR",($L97*($M$12+J97)+N97)) -> A JOUR | P97: x | Q97: x | R97: NT | T97: #N/A | U97: #N/A | V97: NT | Y97: 0 | Z97: 0 | AA97: 0 | AB97: 0 | AC97: 0 | AD97: 0
B98: 85 | C98: =CONCATENATE("N°-","00",B98,"-2024") -> N°-0085-2024 | D98: 774069087 | E98: Mr | F98: Ibrahima Sory | G98: Biilaa | H98: Dakar | I98: 77 406 90 87 | J98: 2000 | K98: 1000 | L98: 0 | M98: =IF(L98>=0,"A JOUR",($L98*($M$12))) -> A JOUR | O98: =IF(L98>=0,"A JOUR",($L98*($M$12+J98)+N98)) -> A JOUR | P98: x | Q98: x | T98: #N/A | U98: #N/A | V98: NT | Y98: 0 | Z98: 0 | AA98: 0 | AB98: 0 | AC98: 0 | AD98: 0
B99: 86 | C99: =CONCATENATE("N°-","00",B99,"-2024") -> N°-0086-2024 | D99: 750190226 | E99: Koto | F99: Ismaila | G99: Pétel | H99: Dakar | I99: 75 019 02 26 | J99: 1000 | K99: 1000 | L99: 0 | M99: =IF(L99>=0,"A JOUR",($L99*($M$12))) -> A JOUR | O99: =IF(L99>=0,"A JOUR",($L99*($M$12+J99)+N99)) -> A JOUR | P99: x | Q99: x | R99: NT | T99: #N/A | U99: #N/A | V99: NT | Y99: 0 | Z99: 0 | AA99: 0 | AB99: 0 | AC99: 0 | AD99: 0
B100: 87 | C100: =CONCATENATE("N°-","00",B100,"-2024") -> N°-0087-2024 | D100: 775379233 | E100: Dr | F100: Korka | G100: Kourawoye | H100: Dakar | I100: 77 537 92 33 | J100: 5000 | K100: N/A | L100: 0 | M100: =IF(L100>=0,"A JOUR",($L100*($M$12))) -> A JOUR | O100: =IF(L100>=0,"A JOUR",($L100*($M$12+J100)+N100)) -> A JOUR | Q100: x | T100: A JOUR | Y100: 0 | Z100: 0 | AA100: 0 | AB100: 0 | AC100: 0 | AD100: 0
B101: 88 | C101: =CONCATENATE("N°-","00",B101,"-2024") -> N°-0088-2024 | D101: 777814802 | E101: Koto | F101: korka | G101: Bowell | H101: Dakar | I101: 77 781 48 02 | J101: 1500 | K101: N/A | L101: 0 | M101: =IF(L101>=0,"A JOUR",($L101*($M$12))) -> A JOUR | O101: =IF(L101>=0,"A JOUR",($L101*($M$12+J101)+N101)) -> A JOUR | Q101: x | T101: A JOUR | Y101: 0 | Z101: 0 | AA101: 0 | AB101: 0 | AC101: 0 | AD101: 0
B102: 89 | C102: =CONCATENATE("N°-","00",B102,"-2024") -> N°-0089-2024 | D102: 771740329 | E102: Koto | F102: Lamarana | G102: Daandé Mboully | H102: Dakar | I102: 77 174 03 29 | J102: 1500 | K102: N/A | L102: 0 | M102: =IF(L102>=0,"A JOUR",($L102*($M$12))) -> A JOUR | O102: =IF(L102>=0,"A JOUR",($L102*($M$12+J102)+N102)) -> A JOUR | Q102: x | T102: A JOUR | Y102: 0 | Z102: 0 | AA102: 0 | AB102: 0 | AC102: 0 | AD102: 0
B103: 90 | C103: =CONCATENATE("N°-","00",B103,"-2024") -> N°-0090-2024 | D103: 781344236 | E103: Koto | F103: Lamarana | G103: Pétel | H103: Dakar | I103: 78 134 42 36 | J103: 2000 | K103: 1000 | L103: 0 | M103: =IF(L103>=0,"A JOUR",($L103*($M$12))) -> A JOUR | O103: =IF(L103>=0,"A JOUR",($L103*($M$12+J103)+N103)) -> A JOUR | P103: x | Q103: x | R103: NT | T103: #N/A | U103: #N/A | V103: NT | Y103: 0 | Z103: 0 | AA103: 0 | AB103: 0 | AC103: 0 | AD103: 0
B104: 91 | C104: =CONCATENATE("N°-","00",B104,"-2024") -> N°-0091-2024 | D104: 778870311 | E104: Koto | F104: Mamadou Aliou | G104: Biilaa | H104: Dakar | I104: 77 887 03 11 | J104: 1000 | K104: 1000 | L104: =2-2 -> 0 | M104: =IF(L104>=0,"A JOUR",($L104*($M$12))) -> A JOUR | O104: =IF(L104>=0,"A JOUR",($L104*($M$12+J104)+N104)) -> A JOUR | P104: x | Q104: x | T104: A JOUR | Y104: 0 | Z104: 0 | AA104: 0 | AB104: 0 | AC104: 0 | AD104: 0
B105: 92 | C105: =CONCATENATE("N°-","00",B105,"-2024") -> N°-0092-2024 | D105: +393384244960 | E105: Grand | F105: Mamadou aliou ibn Elhadji M. Woury | G105: Pétel | H105: Italie | I105: +39 338 424 49 60 | J105: 5000 | K105: N/A | M105: =IF(L105>=0,"A JOUR",($L105*($M$12))) -> A JOUR | O105: =IF(L105>=0,"A JOUR",($L105*($M$12+J105)+N105)) -> A JOUR | Q105: x | T105: #N/A | U105: #N/A | V105: #N/A | W105: #N/A | X105: #N/A | Y105: 0 | Z105: 0 | AA105: 0 | AB105: 0 | AC105: 0 | AD105: 0
B106: 93 | C106: =CONCATENATE("N°-","00",B106,"-2024") -> N°-0093-2024 | D106: 775957597 | E106: Mr | F106: Mamadou aliou ibnu mamoudou | G106: Biilaa | H106: Dakar | I106: 77 595 75 97 | J106: 1000 | K106: 1000 | L106: =+SUM($Y106:$AQ106) -> -17 | M106: =IF(L106>=0,"A JOUR",($L106*($M$12))) -> -34000 | O106: =IF(L106>=0,"A JOUR",($L106*($M$12+J106)+N106)) -> -51000 | P106: x | T106: #N/A | U106: #N/A | V106: #N/A | W106: 1000 | X106: 17 | Y106: -17 | Z106: VG | AA106: VG | AB106: VG | AC106: 0 | AD106: VG
B107: 94 | C107: =CONCATENATE("N°-","00",B107,"-2024") -> N°-0094-2024 | D107: 781313280 | E107: Koto | F107: Mamadou alpha | G107: Dieydiyabhe | H107: Dakar | I107: 78 131 32 80 | J107: 2000 | K107: N/A | L107: 0 | M107: =IF(L107>=0,"A JOUR",($L107*($M$12))) -> A JOUR | O107: =IF(L107>=0,"A JOUR",($L107*($M$12+J107)+N107)) -> A JOUR | Q107: x | T107: A JOUR | Y107: 0 | Z107: 0 | AA107: 0 | AB107: 0 | AC107: 0 | AD107: 0
B108: 95 | C108: =CONCATENATE("N°-","00",B108,"-2024") -> N°-0095-2024 | D108: 773138810 | E108: Mr | F108: Mamadou alpha ibn Elhadji Ibrahima | G108: Pétel | H108: Dakar | I108: 77 313 88 10 | J108: 1000 | K108: 1000 | L108: =-34+9+25 -> 0 | M108: =IF(L108>=0,"A JOUR",($L108*($M$12))) -> A JOUR | O108: =IF(L108>=0,"A JOUR",($L108*($M$12+J108)+N108)) -> A JOUR | Q108: x | T108: A JOUR | Y108: 0 | Z108: 0 | AA108: 0 | AB108: 0 | AC108: 0 | AD108: 0
...

Sheet Données UJDS
B6: UNION DES JEUNES DE DOUKA SELEYABE
G8: =+TODAY() -> 46001
B10: LISTE OFFICIELLE DES MEMBRES
M12: 2000 | T12: A JOUR | U12: GUINEE | V12: NT | W12: DETTE
B13: N° | C13: Code | D13: Téléphone | E13: Titre | F13: Désignation | G13: Missidé | H13: Pays/région | I13: Téléphone | J13: Montant mensuel MSD | K13: Montant mensuel UJDS | L13: Nbre de mois retard | M13: Amande | N13: Avance | O13: Montant dû au 15 01 25 | P13: UJDS | Q13: MOUSSIDAL | R13: STATUT | Y13: 45444 | Z13: 45474 | AA13: 45505 | AB13: 45536 | AC13: 45566 | AD13: 45597 | AE13: 45627 | AF13: 45658 | AG13: 45689 | AH13: 45717 | AI13: 45748 | AJ13: 45778 | AK13: 45809 | AL13: 45839 | AM13: 45870 | AN13: 45901 | AO13: 45931 | AP13: 45962 | AQ13: 45992
B14: 2 | C14: =CONCATENATE("N°-","000",B14,"-2024") -> N°-0002-2024 | D14: 772175292 | E14: Koto | F14: Abdoul ghadry | G14: Leysaré | H14: Dakar | I14: 77 217 52 92 | J14: 2000 | K14: 1000 | L14: 0 | M14: =IF(L14>=0,"A JOUR",($L14*($M$12))) -> A JOUR | O14: =IF(L14>=0,"A JOUR",($L14*($M$12+J14))) -> A JOUR | P14: x | Q14: x | T14: A JOUR | Y14: 0 | Z14: 0 | AA14: 0 | AB14: 0 | AC14: 0 | AD14: 0
B15: 3 | C15: =CONCATENATE("N°-","000",B15,"-2024") -> N°-0003-2024 | D15: xxxxxxxx | E15: Mr | F15: Abdoul goudoussy | G15: Kourawoye | H15: Guinée | I15: xxxxxxxx | K15: 1000 | L15: VG | M15: =IF(L15>=0,"A JOUR",($L15*($M$12))) -> A JOUR | O15: =IF(L15>=0,"A JOUR",($L15*($M$12+J15))) -> A JOUR | P15: x | R15: VG | T15: #N/A | U15: #N/A | V15: #N/A | W15: #N/A | X15: #N/A | Y15: 0 | Z15: 0 | AA15: 0 | AB15: 0 | AC15: 0 | AD15: 0
B16: 5 | C16: =CONCATENATE("N°-","000",B16,"-2024") -> N°-0005-2024 | D16: xxxxxxxx | E16: Koto | F16: Abdoul salam | G16: Gobihi | H16: Gambie | I16: xxxxxxxx | J16: 2000 | K16: 1000 | M16: =IF(L16>=0,"A JOUR",($L16*($M$12))) -> A JOUR | O16: =IF(L16>=0,"A JOUR",($L16*($M$12+J16))) -> A JOUR | Q16: x | T16: #N/A | U16: #N/A | V16: #N/A | W16: #N/A | X16: #N/A | Y16: 0 | Z16: 0 | AA16: 0 | AB16: 0 | AC16: 0 | AD16: 0
B17: 6 | C17: =CONCATENATE("N°-","000",B17,"-2024") -> N°-0006-2024 | D17: 774789094 | E17: Mr | F17: Abdoul salam petit ibn bappa bala | G17: Pétel | H17: Dakar | I17: 77 478 90 94 | J17: 2000 | K17: 1000 | L17: 0 | M17: =IF(L17>=0,"A JOUR",($L17*($M$12))) -> A JOUR | O17: =IF(L17>=0,"A JOUR",($L17*($M$12+J17))) -> A JOUR | P17: x | Q17: x | T17: A JOUR | Y17: 0 | Z17: 0 | AA17: 0 | AB17: 0 | AC17: 0 | AD17: 0
B18: 7 | C18: =CONCATENATE("N°-","000",B18,"-2024") -> N°-0007-2024 | D18: 781050363 | E18: Koto | F18: Abdoul salam ibn Elhadji M. Woury VP | G18: Pétel | H18: Dakar | I18: 78 105 03 63 | J18: 2000 | K18: 1000 | L18: 0 | M18: =IF(L18>=0,"A JOUR",($L18*($M$12))) -> A JOUR | O18: =IF(L18>=0,"A JOUR",($L18*($M$12+J18))) -> A JOUR | P18: x | Q18: x | T18: A JOUR | Y18: 0 | Z18: 0 | AA18: 0 | AB18: 0 | AC18: 0 | AD18: 0
B19: 9 | C19: =CONCATENATE("N°-","000",B19,"-2024") -> N°-0009-2024 | D19: 774789094 | E19: Mr | F19: Abdoul salam petit | G19: Pétel | H19: Dakar | I19: 77 478 90 94 | J19: 2000 | K19: 1000 | L19: 0 | M19: =IF(L19>=0,"A JOUR",($L19*($M$12))) -> A JOUR | O19: =IF(L19>=0,"A JOUR",($L19*($M$12+J19))) -> A JOUR | P19: x | Q19: x | T19: A JOUR | Y19: 0 | Z19: 0 | AA19: 0 | AB19: 0 | AC19: 0 | AD19: 0
B20: 10 | C20: =CONCATENATE("N°-","00",B20,"-2024") -> N°-0010-2024 | D20: 776792624 | E20: Mr | F20: Abdoul salam PP | G20: Dieydiyabhe | H20: Dakar | I20: 77 679 26 24 | J20: 1000 | K20: 1000 | L20: 0 | M20: =IF(L20>=0,"A JOUR",($L20*($M$12))) -> A JOUR | O20: =IF(L20>=0,"A JOUR",($L20*($M$12+J20))) -> A JOUR | P20: x | Q20: x | T20: A JOUR | Y20: 0 | Z20: 0 | AA20: 0 | AB20: 0 | AC20: 0 | AD20: 0
B21: 11 | C21: =CONCATENATE("N°-","00",B21,"-2024") -> N°-0011-2024 | D21: 775779980 | E21: Mr | F21: Abdoul salam PP (ivoire) | G21: Dowsaré | H21: Dakar | I21: 77 577 99 80 | J21: 1000 | K21: 1000 | L21: =+SUM($Y21:$AQ21) -> -2 | M21: =IF(L21>=0,"A JOUR",($L21*($M$12))) -> -4000 | O21: =IF(L21>=0,"A JOUR",($L21*($M$12+J21)+N21)) -> -6000 | P21: x | Q21: x | T21: #N/A | U21: #N/A | V21: #N/A | W21: 1000 | X21: 2 | Y21: 0 | Z21: 0 | AA21: 0 | AB21: -1 | AC21: 0 | AD21: -1
B22: 12 | C22: =CONCATENATE("N°-","00",B22,"-2024") -> N°-0012-2024 | E22: Mr | F22: Abdoulaye | G22: Daandé Mboully | H22: Guinée | K22: 1000 | L22: VG | M22: =IF(L22>=0,"A JOUR",($L22*($M$12))) -> A JOUR | O22: =IF(L22>=0,"A JOUR",($L22*($M$12+J22))) -> A JOUR | P22: x | R22: VG | T22: #N/A | U22: #N/A | V22: #N/A | W22: #N/A | X22: #N/A | Y22: 0 | Z22: 0 | AA22: 0 | AB22: 0 | AC22: 0 | AD22: 0
B23: 14 | C23: =CONCATENATE("N°-","00",B23,"-2024") -> N°-0014-2024 | D23: 781413617 | E23: Grand | F23: Abdoulaye (Laye) | G23: Biilaa | H23: Dakar | I23: 78 141 36 17 | J23: 1000 | K23: 1000 | L23: 0 | M23: =IF(L23>=0,"A JOUR",($L23*($M$12))) -> A JOUR | O23: =IF(L23>=0,"A JOUR",($L23*($M$12+J23))) -> A JOUR | P23: x | Q23: x | T23: #N/A | U23: GUINEE | Y23: 0 | Z23: 0 | AA23: 0 | AB23: 0 | AC23: 0 | AD23: 0
B24: 18 | C24: =CONCATENATE("N°-","00",B24,"-2024") -> N°-0018-2024 | D24: 774042497 | E24: Mr | F24: Abdourahmane TRS | G24: Mamasamba | H24: Dakar | I24: 77 404 24 97 | J24: 5000 | K24: 1000 | L24: 0 | M24: =IF(L24>=0,"A JOUR",($L24*($M$12))) -> A JOUR | O24: =IF(L24>=0,"A JOUR",($L24*($M$12+J24))) -> A JOUR | P24: x | Q24: x | T24: #N/A | U24: #N/A | V24: #N/A | W24: #N/A | X24: #N/A | Y24: 0 | Z24: 0 | AA24: 0 | AB24: 0 | AC24: 0 | AD24: 0
B25: 19 | C25: =CONCATENATE("N°-","00",B25,"-2024") -> N°-0019-2024 | D25: 774473167 | E25: Koto | F25: Ablaye TSA | G25: Bolorrou | H25: Dakar | I25: 77 447 31 67 | J25: 1500 | K25: 1000 | L25: 0 | M25: =IF(L25>=0,"A JOUR",($L25*($M$12))) -> A JOUR | O25: =IF(L25>=0,"A JOUR",($L25*($M$12+J25))) -> A JOUR | P25: x | Q25: x | T25: A JOUR | Y25: 0 | Z25: 0 | AA25: 0 | AB25: 0 | AC25: 0 | AD25: 0
B26: 20 | C26: =CONCATENATE("N°-","00",B26,"-2024") -> N°-0020-2024 | D26: 777119328 | E26: Kaou | F26: Ahmadou Korka ibn bappa bala | G26: Pétel | H26: Dakar | I26: 777119328 | J26: 1000 | K26: 1000 | L26: =+SUM($Y26:$AQ26) -> -3 | M26: =IF(L26>=0,"A JOUR",($L26*($M$12))) -> -6000 | O26: =IF(L26>=0,"A JOUR",($L26*($M$12+J26)+N26)) -> -9000 | T26: #N/A | U26: #N/A | V26: #N/A | W26: 1000 | X26: 3 | Y26: 0 | Z26: 0 | AA26: -1 | AB26: -1 | AC26: 0 | AD26: -1
B27: 21 | C27: =CONCATENATE("N°-","00",B27,"-2024") -> N°-0021-2024 | D27: 783520425 | E27: Mr | F27: Alassana ibn Elhadji M. Woury | G27: Pétel | H27: Dakar | I27: 78 352 04 25 | J27: 1000 | K27: 1000 | L27: 0 | M27: =IF(L27>=0,"A JOUR",($L27*($M$12))) -> A JOUR | O27: =IF(L27>=0,"A JOUR",($L27*($M$12+J27))) -> A JOUR | Q27: x | R27: NT | T27: #N/A | U27: #N/A | V27: NT | Y27: 0 | Z27: 0 | AA27: 0 | AB27: 0 | AC27: 0 | AD27: 0
B28: 22 | C28: =CONCATENATE("N°-","00",B28,"-2024") -> N°-0022-2024 | D28: 767652193 | E28: Mr | F28: Alassana Macoss | G28: Dowsaré | H28: Dakar | I28: 76 765 21 93 | J28: 1000 | K28: 1000 | L28: 0 | M28: =IF(L28>=0,"A JOUR",($L28*($M$12))) -> A JOUR | O28: =IF(L28>=0,"A JOUR",($L28*($M$12+J28))) -> A JOUR | P28: x | Q28: x | R28: NT | T28: #N/A | U28: #N/A | V28: NT | Y28: 0 | Z28: 0 | AA28: 0 | AB28: 0 | AC28: 0 | AD28: 0
B29: 23 | C29: =CONCATENATE("N°-","00",B29,"-2024") -> N°-0023-2024 | D29: 783520425 | E29: Mr | F29: Alousseynou ibn Elhadji M. Woury | G29: Pétel | H29: Dakar | I29: 78 352 04 25 | J29: 1000 | K29: 1000 | L29: 0 | M29: =IF(L29>=0,"A JOUR",($L29*($M$12))) -> A JOUR | O29: =IF(L29>=0,"A JOUR",($L29*($M$12+J29))) -> A JOUR | Q29: x | R29: NT | T29: #N/A | U29: #N/A | V29: NT | Y29: 0 | Z29: 0 | AA29: 0 | AB29: 0 | AC29: 0 | AD29: 0
B30: 25 | C30: =CONCATENATE("N°-","00",B30,"-2024") -> N°-0025-2024 | E30: Mr | F30: Alpha (France) | G30: Dieydiyabhe | H30: France | K30: 1000 | M30: =IF(L30>=0,"A JOUR",($L30*($M$12))) -> A JOUR | O30: =IF(L30>=0,"A JOUR",($L30*($M$12+J30))) -> A JOUR | T30: #N/A | U30: #N/A | V30: #N/A | W30: #N/A | X30: #N/A | Y30: 0 | Z30: 0 | AA30: 0 | AB30: 0 | AC30: 0 | AD30: 0
B31: 26 | C31: =CONCATENATE("N°-","00",B31,"-2024") -> N°-0026-2024 | D31: 772289487 | E31: Mr | F31: Alpha amadou ibn bappa bala | G31: Pétel | H31: Dakar | I31: 77 228 94 87 | J31: 1000 | K31: 1000 | L31: 0 | M31: =IF(L31>=0,"A JOUR",($L31*($M$12))) -> A JOUR | O31: =IF(L31>=0,"A JOUR",($L31*($M$12+J31))) -> A JOUR | P31: x | Q31: x | T31: A JOUR | Y31: 0 | Z31: 0 | AA31: 0 | AB31: 0 | AC31: 0 | AD31: 0
B32: 27 | C32: =CONCATENATE("N°-","00",B32,"-2024") -> N°-0027-2024 | D32: 781261182 | E32: Mr | F32: Alpha Amirou ibn Elhadji Ibrahima | G32: Pétel | H32: Dakar | I32: 78 126 11 82 | J32: 1000 | K32: 1000 | L32: =+SUM($Y32:$AQ32) -> -6 | M32: =IF(L32>=0,"A JOUR",($L32*($M$12))) -> -12000 | O32: =IF(L32>=0,"A JOUR",($L32*($M$12+J32)+N32)) -> -18000 | Q32: x | R32: NT | T32: #N/A | U32: #N/A | V32: #N/A | W32: 1000 | X32: 6 | Y32: -2 | Z32: -1 | AA32: -1 | AB32: -1 | AC32: 0 | AD32: -1
B33: 28 | C33: =CONCATENATE("N°-","00",B33,"-2024") -> N°-0028-2024 | D33: 772202046 | E33: Koto | F33: alpha KZA ibnou samara | G33: Dowsaré | H33: Casamance | I33: 77 220 20 46 | J33: 2000 | K33: 1000 | L33: 1 | M33: =IF(L33>=0,"A JOUR",($L33*($M$12))) -> A JOUR | N33: =+L33*J33 -> 2000 | O33: =IF(L33>=0,"A JOUR",($L33*($M$12+J33))) -> A JOUR | P33: x | Q33: x | T33: A JOUR | Y33: 0 | Z33: 0 | AA33: 0 | AB33: 0 | AC33: 0 | AD33: 0
B34: 29 | C34: =CONCATENATE("N°-","00",B34,"-2024") -> N°-0029-2024 | D34: 781346347 | E34: Bappa | F34: Alpha oumar | G34: Mamasamba | H34: Dakar | I34: 78 134 63 47 | J34: 2000 | K34: 1000 | L34: =4-4 -> 0 | M34: =IF(L34>=0,"A JOUR",($L34*($M$12))) -> A JOUR | O34: =IF(L34>=0,"A JOUR",($L34*($M$12+J34))) -> A JOUR | P34: x | Q34: x | T34: A JOUR | Y34: 0 | Z34: 0 | AA34: 0 | AB34: 0 | AC34: 0 | AD34: 0
B35: 30 | C35: =CONCATENATE("N°-","00",B35,"-2024") -> N°-0030-2024 | D35: xxxxxxxx | E35: Koto | F35: Alpha oumar gabonais | G35: Dowsaré | H35: Togo | I35: xxxxxxxx | J35: 4000 | K35: 1000 | M35: =IF(L35>=0,"A JOUR",($L35*($M$12))) -> A JOUR | O35: =IF(L35>=0,"A JOUR",($L35*($M$12+J35))) -> A JOUR | P35: x | Q35: x | T35: #N/A | U35: #N/A | V35: #N/A | W35: #N/A | X35: #N/A | Y35: 0 | Z35: 0 | AA35: 0 | AB35: 0 | AC35: 0 | AD35: 0
B36: 32 | C36: =CONCATENATE("N°-","00",B36,"-2024") -> N°-0032-2024 | D36: 774997775 | E36: Koto | F36: Alpha Oumar togolais | G36: Dowsaré | H36: Dakar | I36: 77 499 77 75 | J36: 2000 | K36: 1000 | L36: =2-1 -> 1 | M36: =IF(L36>=0,"A JOUR",($L36*($M$12))) -> A JOUR | N36: =+L36*J36 -> 2000 | O36: =IF(L36>=0,"A JOUR",($L36*($M$12+J36))) -> A JOUR | P36: x | Q36: x | T36: A JOUR | Y36: 0 | Z36: 0 | AA36: 0 | AB36: 0 | AC36: 0 | AD36: 0
B37: 33 | C37: =CONCATENATE("N°-","00",B37,"-2024") -> N°-0033-2024 | E37: Mr | F37: Alpha Saliou ibn Elhadji M. Woury | G37: Pétel | H37: Guinée | K37: 1000 | L37: VG | M37: =IF(L37>=0,"A JOUR",($L37*($M$12))) -> A JOUR | O37: =IF(L37>=0,"A JOUR",($L37*($M$12+J37))) -> A JOUR | R37: VG | T37: #N/A | U37: #N/A | V37: #N/A | W37: #N/A | X37: #N/A | Y37: 0 | Z37: 0 | AA37: 0 | AB37: 0 | AC37: 0 | AD37: 0
B38: 34 | C38: =CONCATENATE("N°-","00",B38,"-2024") -> N°-0034-2024 | D38: 776709584 | E38: Oustaz | F38: Amadou | G38: Bowell | H38: Guinée | I38: 77 670 95 84 | J38: 2500 | K38: 1000 | L38: 0 | M38: =IF(L38>=0,"A JOUR",($L38*($M$12))) -> A JOUR | O38: =IF(L38>=0,"A JOUR",($L38*($M$12+J38))) -> A JOUR | P38: x | Q38: x | R38: NT | T38: #N/A | U38: GUINEE | Y38: 0 | Z38: 0 | AA38: 0 | AB38: 0 | AC38: 0 | AD38: 0
B39: 35 | C39: =CONCATENATE("N°-","00",B39,"-2024") -> N°-0035-2024 | D39: 776623868 | E39: Mr | F39: Amadou bobo (mariste) | G39: Dowsaré | H39: Dakar | I39: 77 662 38 68 | J39: 2000 | K39: 1000 | L39: 0 | M39: =IF(L39>=0,"A JOUR",($L39*($M$12))) -> A JOUR | O39: =IF(L39>=0,"A JOUR",($L39*($M$12+J39))) -> A JOUR | P39: x | Q39: x | T39: A JOUR | Y39: 0 | Z39: 0 | AA39: 0 | AB39: 0 | AC39: 0 | AD39: 0
B40: 36 | C40: =CONCATENATE("N°-","00",B40,"-2024") -> N°-0036-2024 | D40: 774272026 | E40: Koto | F40: Amadou bobo N°1 | G40: Dowsaré | H40: Dakar | I40: 77 427 20 26 | J40: 2000 | K40: 1000 | L40: =+SUM($Y40:$AQ40) -> -4 | M40: =IF(L40>=0,"A JOUR",($L40*($M$12))) -> -8000 | O40: =IF(L40>=0,"A JOUR",($L40*($M$12+J40)+N40)) -> -16000 | P40: x | Q40: x | T40: #N/A | U40: #N/A | V40: #N/A | W40: 2000 | X40: 4 | Y40: 0 | Z40: -1 | AA40: -1 | AB40: -1 | AC40: 0 | AD40: -1
B41: 37 | C41: =CONCATENATE("N°-","00",B41,"-2024") -> N°-0037-2024 | D41: xxxxxxxx | E41: Mr | F41: Amadou diogo | G41: Gobihi | H41: Guinée | I41: xxxxxxxx | J41: 2000 | K41: 1000 | M41: =IF(L41>=0,"A JOUR",($L41*($M$12))) -> A JOUR | O41: =IF(L41>=0,"A JOUR",($L41*($M$12+J41))) -> A JOUR | Q41: x | R41: VG | T41: #N/A | U41: #N/A | V41: #N/A | W41: #N/A | X41: #N/A | Y41: 0 | Z41: 0 | AA41: 0 | AB41: 0 | AC41: 0 | AD41: 0
B42: 38 | C42: =CONCATENATE("N°-","00",B42,"-2024") -> N°-0038-2024 | D42: 775218573 | E42: Mr | F42: Amadou Djoulde - PR | G42: Dowsaré | H42: Dakar | I42: 77 521 85 73 | J42: 3000 | K42: 1000 | L42: 0 | M42: =IF(L42>=0,"A JOUR",($L42*($M$12))) -> A JOUR | O42: =IF(L42>=0,"A JOUR",($L42*($M$12+J42))) -> A JOUR | P42: x | Q42: x | T42: A JOUR | Y42: 0 | Z42: 0 | AA42: 0 | AB42: 0 | AC42: 0 | AD42: 0
B43: 39 | C43: =CONCATENATE("N°-","00",B43,"-2024") -> N°-0039-2024 | D43: 778550234 | E43: Koto | F43: Amadou korka CC | G43: Diabbhéhi | H43: Dakar | I43: 77 855 02 34 | J43: 2000 | K43: 1000 | L43: 0 | M43: =IF(L43>=0,"A JOUR",($L43*($M$12))) -> A JOUR | O43: =IF(L43>=0,"A JOUR",($L43*($M$12+J43))) -> A JOUR | P43: x | Q43: x | T43: A JOUR | Y43: 0 | Z43: 0 | AA43: 0 | AB43: 0 | AC43: 0 | AD43: 0
B44: 40 | C44: =CONCATENATE("N°-","00",B44,"-2024") -> N°-0040-2024 | D44: 778151869 | E44: Koto | F44: Amadou korka | G44: Biilaa | H44: Dakar | I44: 77 815 18 69 | J44: 1000 | K44: 1000 | L44: 0 | M44: =IF(L44>=0,"A JOUR",($L44*($M$12))) -> A JOUR | O44: =IF(L44>=0,"A JOUR",($L44*($M$12+J44))) -> A JOUR | P44: x | Q44: x | T44: A JOUR | Y44: 0 | Z44: 0 | AA44: 0 | AB44: 0 | AC44: 0 | AD44: 0
B45: 44 | C45: =CONCATENATE("N°-","00",B45,"-2024") -> N°-0044-2024 | D45: 778637835 | E45: Mr | F45: Amadou tanou | G45: Dieydiyabhe | H45: Dakar | I45: 77 863 78 35 | J45: 1000 | K45: 1000 | L45: 0 | M45: =IF(L45>=0,"A JOUR",($L45*($M$12))) -> A JOUR | O45: =IF(L45>=0,"A JOUR",($L45*($M$12+J45))) -> A JOUR | P45: x | Q45: x | R45: NT | T45: #N/A | U45: #N/A | V45: NT | Y45: 0 | Z45: 0 | AA45: 0 | AB45: 0 | AC45: 0 | AD45: 0
B46: 45 | C46: =CONCATENATE("N°-","00",B46,"-2024") -> N°-0045-2024 | D46: 773499877 | E46: Mody | F46: Amadou TC | G46: Mamasamba | H46: Dakar | I46: 77 349 98 77 | J46: 2000 | K46: 1000 | L46: 0 | M46: =IF(L46>=0,"A JOUR",($L46*($M$12))) -> A JOUR | O46: =IF(L46>=0,"A JOUR",($L46*($M$12+J46))) -> A JOUR | P46: x | Q46: x | T46: #N/A | U46: GUINEE | Y46: 0 | Z46: 0 | AA46: 0 | AB46: 0 | AC46: 0 | AD46: 0
B47: 46 | C47: =CONCATENATE("N°-","00",B47,"-2024") -> N°-0046-2024 | D47: xxxxxxxx | E47: Mr | F47: Amadou Woury | G47: Ka missidé | H47: Côte d'ivoire | I47: xxxxxxxx | J47: 2000 | K47: 1000 | L47: 0 | M47: =IF(L47>=0,"A JOUR",($L47*($M$12))) -> A JOUR | O47: =IF(L47>=0,"A JOUR",($L47*($M$12+J47))) -> A JOUR | Q47: x | T47: #N/A | U47: #N/A | V47: #N/A | W47: #N/A | X47: #N/A | Y47: 0 | Z47: 0 | AA47: 0 | AB47: 0 | AC47: 0 | AD47: 0
B48: 49 | C48: =CONCATENATE("N°-","00",B48,"-2024") -> N°-0049-2024 | D48: 778018331 | E48: Mr | F48: Boubacar (mariste ) | G48: Kourawoye | H48: Dakar | I48: 77 801 83 31 | J48: 2000 | K48: 1000 | L48: 0 | M48: =IF(L48>=0,"A JOUR",($L48*($M$12))) -> A JOUR | O48: =IF(L48>=0,"A JOUR",($L48*($M$12+J48))) -> A JOUR | P48: x | Q48: x | T48: #N/A | U48: #N/A | V48: #N/A | W48: #N/A | X48: #N/A | Y48: 0 | Z48: 0 | AA48: 0 | AB48: 0 | AC48: 0 | AD48: 0
B49: 50 | C49: =CONCATENATE("N°-","00",B49,"-2024") -> N°-0050-2024 | D49: 774494968 | E49: Mr | F49: Boubacar ibn bappa bala CC | G49: Pétel | H49: Dakar | I49: 77 449 49 68 | J49: 3000 | K49: 1000 | L49: 0 | M49: =IF(L49>=0,"A JOUR",($L49*($M$12))) -> A JOUR | O49: =IF(L49>=0,"A JOUR",($L49*($M$12+J49))) -> A JOUR | P49: x | Q49: x | T49: A JOUR | Y49: 0 | Z49: 0 | AA49: 0 | AB49: 0 | AC49: 0 | AD49: 0
B50: 52 | C50: =CONCATENATE("N°-","00",B50,"-2024") -> N°-0052-2024 | D50: 776779519 | E50: Mr | F50: Boubacar Kowloun | G50: Kowloune | H50: Dakar | I50: 77 677 95 19 | J50: 1000 | K50: 1000 | L50: 0 | M50: =IF(L50>=0,"A JOUR",($L50*($M$12))) -> A JOUR | O50: =IF(L50>=0,"A JOUR",($L50*($M$12+J50))) -> A JOUR | T50: A JOUR | Y50: 0 | Z50: 0 | AA50: 0 | AB50: 0 | AC50: 0 | AD50: 0
B51: 53 | C51: =CONCATENATE("N°-","00",B51,"-2024") -> N°-0053-2024 | D51: 773137431 | E51: Koto | F51: Boubacar méékohi | G51: Dowsaré | H51: Dakar | I51: 77 313 74 31 | J51: 2000 | K51: 1000 | L51: =+SUM($Y51:$AQ51) -> -2 | M51: =IF(L51>=0,"A JOUR",($L51*($M$12))) -> -4000 | O51: =IF(L51>=0,"A JOUR",($L51*($M$12+J51)+N51)) -> -8000 | P51: x | Q51: x | R51: NT | T51: #N/A | U51: #N/A | V51: #N/A | W51: 2000 | X51: 2 | Y51: 0 | Z51: 0 | AA51: 0 | AB51: -1 | AC51: 0 | AD51: -1
B52: 54 | C52: =CONCATENATE("N°-","00",B52,"-2024") -> N°-0054-2024 | E52: Mr | F52: Boubacar Ngarahi | G52: Dowsaré | H52: Dakar | J52: 1000 | K52: 1000 | M52: =IF(L52>=0,"A JOUR",($L52*($M$12))) -> A JOUR | O52: =IF(L52>=0,"A JOUR",($L52*($M$12+J52))) -> A JOUR | T52: #N/A | U52: #N/A | V52: #N/A | W52: #N/A | X52: #N/A | Y52: 0 | Z52: 0 | AA52: 0 | AB52: 0 | AC52: 0 | AD52: 0
B53: 55 | C53: =CONCATENATE("N°-","00",B53,"-2024") -> N°-0055-2024 | D53: 776669090 | E53: Mr | F53: Bourhane | G53: Pétel | H53: Dakar | I53: 77 666 90 90 | J53: 1000 | K53: 1000 | L53: =+SUM($Y53:$AQ53) -> -8 | M53: =IF(L53>=0,"A JOUR",($L53*($M$12))) -> -16000 | O53: =IF(L53>=0,"A JOUR",($L53*($M$12+J53)+N53)) -> -24000 | P53: x | Q53: x | T53: #N/A | U53: #N/A | V53: #N/A | W53: 1000 | X53: 8 | Y53: -8 | Z53: 0 | AA53: 0 | AB53: 0 | AC53: 0 | AD53: 0
B54: 57 | C54: =CONCATENATE("N°-","00",B54,"-2024") -> N°-0057-2024 | D54: 774885353 | E54: Mr | F54: Cheikh tidiane ibn Elhadji Ibrahima | G54: Pétel | H54: Dakar | I54: 77 488 53 53 | J54: 1000 | K54: 1000 | L54: =+SUM($Y54:$AQ54) -> -4 | M54: =IF(L54>=0,"A JOUR",($L54*($M$12))) -> -8000 | O54: =IF(L54>=0,"A JOUR",($L54*($M$12+J54)+N54)) -> -12000 | P54: x | Q54: x | T54: #N/A | U54: #N/A | V54: #N/A | W54: 1000 | X54: 4 | Y54: 0 | Z54: -1 | AA54: -1 | AB54: -1 | AC54: 0 | AD54: -1
B55: 59 | C55: =CONCATENATE("N°-","00",B55,"-2024") -> N°-0059-2024 | D55: 774767085 | E55: Mr | F55: Daouda (Parcelles) | G55: Kourawoye | H55: Dakar | I55: 77 476 70 85 | J55: 1000 | K55: 1000 | L55: 0 | M55: =IF(L55>=0,"A JOUR",($L55*($M$12))) -> A JOUR | O55: =IF(L55>=0,"A JOUR",($L55*($M$12+J55))) -> A JOUR | P55: x | Q55: x | T55: A JOUR | Y55: 0 | Z55: 0 | AA55: 0 | AB55: 0 | AC55: 0 | AD55: 0
B56: 60 | C56: =CONCATENATE("N°-","00",B56,"-2024") -> N°-0060-2024 | E56: Mr | F56: Daouda ibn Elhadji M. Woury | G56: Pétel | H56: Guinée | J56: N/A | K56: 1000 | L56: VG | M56: =IF(L56>=0,"A JOUR",($L56*($M$12))) -> A JOUR | O56: =IF(L56>=0,"A JOUR",($L56*($M$12+J56))) -> A JOUR | P56: x | R56: VG | T56: #N/A | U56: #N/A | V56: #N/A | W56: #N/A | X56: #N/A | Y56: 0 | Z56: 0 | AA56: 0 | AB56: 0 | AC56: 0 | AD56: 0
B57: 61 | C57: =CONCATENATE("N°-","00",B57,"-2024") -> N°-0061-2024 | D57: 776790248 | E57: Mr | F57: Elh ibrahima N°2 ibn karamoko Daouda DC | G57: Pétel | H57: Dakar | I57: 77 679 02 48 | J57: 2000 | K57: 1000 | L57: 0 | M57: =IF(L57>=0,"A JOUR",($L57*($M$12))) -> A JOUR | O57: =IF(L57>=0,"A JOUR",($L57*($M$12+J57))) -> A JOUR | P57: x | Q57: x | T57: A JOUR | Y57: 0 | Z57: 0 | AA57: 0 | AB57: 0 | AC57: 0 | AD57: 0
B58: 62 | C58: =CONCATENATE("N°-","00",B58,"-2024") -> N°-0062-2024 | D58: 781656755 | E58: Mr | F58: Elhadji abdoulaye | G58: Dieydiyabhe | H58: Dakar | I58: 78 165 67 55 | J58: 1000 | K58: 1000 | L58: 0 | M58: =IF(L58>=0,"A JOUR",($L58*($M$12))) -> A JOUR | O58: =IF(L58>=0,"A JOUR",($L58*($M$12+J58))) -> A JOUR | P58: x | Q58: x | S58: 78 326 04 13 | T58: A JOUR | Y58: 0 | Z58: 0 | AA58: 0 | AB58: 0 | AC58: 0 | AD58: 0
B59: 63 | C59: =CONCATENATE("N°-","00",B59,"-2024") -> N°-0063-2024 | D59: 781313842 | E59: Mr | F59: Elhadji ablaye coiffeur | G59: Dieydiyabhe | H59: Dakar | I59: 78 131 38 42 | J59: 1000 | K59: 1000 | L59: 0 | M59: =IF(L59>=0,"A JOUR",($L59*($M$12))) -> A JOUR | O59: =IF(L59>=0,"A JOUR",($L59*($M$12+J59))) -> A JOUR | P59: x | Q59: x | T59: A JOUR | Y59: 0 | Z59: 0 | AA59: 0 | AB59: 0 | AC59: 0 | AD59: 0
B60: 64 | C60: =CONCATENATE("N°-","00",B60,"-2024") -> N°-0064-2024 | D60: xxxxxxxx | E60: Mr | F60: Elhadji aliou ibn bappa Siradio | G60: Dowsaré | H60: France | I60: xxxxxxxx | J60: 5000 | K60: 1000 | M60: =IF(L60>=0,"A JOUR",($L60*($M$12))) -> A JOUR | O60: =IF(L60>=0,"A JOUR",($L60*($M$12+J60))) -> A JOUR | Q60: x | T60: #N/A | U60: #N/A | V60: #N/A | W60: #N/A | X60: #N/A | Y60: 0 | Z60: 0 | AA60: 0 | AB60: 0 | AC60: 0 | AD60: 0
B61: 65 | C61: =CONCATENATE("N°-","00",B61,"-2024") -> N°-0065-2024 | D61: 773012928 | E61: Mr | F61: Elhadji amadou | G61: Biilaa | H61: Dakar | I61: 77 301 29 28 | J61: 1000 | K61: 1000 | L61: =+SUM($Y61:$AQ61) -> -34 | M61: =IF(L61>=0,"A JOUR",($L61*($M$12))) -> -68000 | O61: =IF(L61>=0,"A JOUR",($L61*($M$12+J61)+N61)) -> -102000 | P61: x | Q61: x | T61: #N/A | U61: #N/A | V61: #N/A | W61: 1000 | X61: 34 | Y61: -30 | Z61: -1 | AA61: -1 | AB61: -1 | AC61: 0 | AD61: -1
B62: 66 | C62: =CONCATENATE("N°-","00",B62,"-2024") -> N°-0066-2024 | D62: 761722302 | E62: Mr | F62: Elhadji Boubacar mo moussou | G62: Pétel | H62: Dakar | I62: 76 172 23 02 | J62: 1000 | K62: 1000 | L62: =+SUM($Y62:$AQ62) -> -44 | M62: =IF(L62>=0,"A JOUR",($L62*($M$12))) -> -88000 | O62: =IF(L62>=0,"A JOUR",($L62*($M$12+J62)+N62)) -> -132000 | P62: x | Q62: x | S62: 2 FOIS | T62: #N/A | U62: #N/A | V62: #N/A | W62: 1000 | X62: 44 | Y62: -41 | Z62: -1 | AA62: -1 | AB62: 0 | AC62: 0 | AD62: -1
B63: 67 | C63: =CONCATENATE("N°-","00",B63,"-2024") -> N°-0067-2024 | D63: 622417844 | E63: Mr | F63: Elhadji douka chauffeur | G63: Dowsaré | H63: Guinée | I63: 622 41 78 44 | J63: 2000 | K63: 1000 | L63: 0 | M63: =IF(L63>=0,"A JOUR",($L63*($M$12))) -> A JOUR | O63: =IF(L63>=0,"A JOUR",($L63*($M$12+J63))) -> A JOUR | P63: x | Q63: x | R63: VG | T63: #N/A | U63: GUINEE | Y63: 0 | Z63: 0 | AA63: 0 | AB63: 0 | AC63: 0 | AD63: 0
B64: 68 | C64: =CONCATENATE("N°-","00",B64,"-2024") -> N°-0068-2024 | D64: 784087096 | E64: Mr | F64: Elhadji ibrahima ibn Elhadji M. Woury | G64: Pétel | H64: Dakar | I64: 78 408 70 96 | J64: 1000 | K64: 1000 | L64: =+SUM($Y64:$AQ64) -> -4 | M64: =IF(L64>=0,"A JOUR",($L64*($M$12))) -> -8000 | O64: =IF(L64>=0,"A JOUR",($L64*($M$12+J64)+N64)) -> -12000 | Q64: x | T64: #N/A | U64: #N/A | V64: #N/A | W64: 1000 | X64: 4 | Y64: 0 | Z64: -1 | AA64: -1 | AB64: -1 | AC64: 0 | AD64: -1
B65: 70 | C65: =CONCATENATE("N°-","00",B65,"-2024") -> N°-0070-2024 | D65: xxxxxxxx | E65: Mr | F65: Elhadji woury | G65: Dowsaré | H65: Gambie | I65: xxxxxxxx | J65: 2000 | K65: 1000 | M65: =IF(L65>=0,"A JOUR",($L65*($M$12))) -> A JOUR | O65: =IF(L65>=0,"A JOUR",($L65*($M$12+J65))) -> A JOUR | Q65: x | T65: #N/A | U65: #N/A | V65: #N/A | W65: #N/A | X65: #N/A | Y65: 0 | Z65: 0 | AA65: 0 | AB65: 0 | AC65: 0 | AD65: 0
B66: 71 | C66: =CONCATENATE("N°-","00",B66,"-2024") -> N°-0071-2024 | D66: 783260413 | E66: Mr | F66: Elhadji woury ibn bappa korka & yan safietou | G66: Dowsaré | H66: Dakar | I66: 78 326 04 13 | J66: 1000 | K66: 1000 | L66: =+SUM($Y66:$AQ66) -> -4 | M66: =IF(L66>=0,"A JOUR",($L66*($M$12))) -> -8000 | O66: =IF(L66>=0,"A JOUR",($L66*($M$12+J66)+N66)) -> -12000 | P66: x | Q66: x | T66: #N/A | U66: #N/A | V66: #N/A | W66: 1000 | X66: 4 | Y66: 0 | Z66: -1 | AA66: -1 | AB66: -1 | AC66: 0 | AD66: -1
B67: 73 | C67: =CONCATENATE("N°-","00",B67,"-2024") -> N°-0073-2024 | D67: 776049360 | E67: Mr | F67: Elhadji woury parcelles | G67: Kourawoye | H67: Dakar | I67: 77 604 93 60 | J67: 1000 | K67: 1000 | L67: 0 | M67: =IF(L67>=0,"A JOUR",($L67*($M$12))) -> A JOUR | O67: =IF(L67>=0,"A JOUR",($L67*($M$12+J67))) -> A JOUR | P67: x | Q67: x | T67: A JOUR | Y67: 0 | Z67: 0 | AA67: 0 | AB67: 0 | AC67: 0 | AD67: 0
B68: 74 | C68: =CONCATENATE("N°-","00",B68,"-2024") -> N°-0074-2024 | D68: 774965371 | E68: Mr | F68: Elhadji woury petel ibn MD hamidou | G68: Pétel | H68: Dakar | I68: 77 496 53 71 | J68: 1000 | K68: 1000 | L68: =+SUM($Y68:$AQ68) -> -3 | M68: =IF(L68>=0,"A JOUR",($L68*($M$12))) -> -6000 | O68: =IF(L68>=0,"A JOUR",($L68*($M$12+J68)+N68)) -> -9000 | P68: x | Q68: x | T68: #N/A | U68: #N/A | V68: #N/A | W68: 1000 | X68: 3 | Y68: 0 | Z68: 0 | AA68: -1 | AB68: -1 | AC68: 0 | AD68: -1
B69: 76 | C69: =CONCATENATE("N°-","00",B69,"-2024") -> N°-0076-2024 | D69: 773851455 | E69: Mr | F69: Hamidou | G69: Dowsaré | H69: Dakar | I69: 77 385 14 55 | J69: 1000 | K69: 1000 | L69: 0 | M69: =IF(L69>=0,"A JOUR",($L69*($M$12))) -> A JOUR | O69: =IF(L69>=0,"A JOUR",($L69*($M$12+J69))) -> A JOUR | P69: x | Q69: x | T69: A JOUR | Y69: 0 | Z69: 0 | AA69: 0 | AB69: 0 | AC69: 0 | AD69: 0
B70: 77 | C70: =CONCATENATE("N°-","00",B70,"-2024") -> N°-0077-2024 | D70: 776232888 | E70: Oustaz | F70: Ibrahima | G70: Daandé Mboully | H70: Dakar | I70: 77 623 28 88 | J70: 2000 | K70: 1000 | L70: 0 | M70: =IF(L70>=0,"A JOUR",($L70*($M$12))) -> A JOUR | O70: =IF(L70>=0,"A JOUR",($L70*($M$12+J70))) -> A JOUR | P70: x | Q70: x | T70: A JOUR | Y70: 0 | Z70: 0 | AA70: 0 | AB70: 0 | AC70: 0 | AD70: 0
B71: 79 | C71: =CONCATENATE("N°-","00",B71,"-2024") -> N°-0079-2024 | D71: 778018660 | E71: Mr | F71: Ibrahima | G71: Diabbhéhi | H71: Guinée | I71: 77 801 86 60 | J71: 1000 | K71: 1000 | L71: =+SUM($Y71:$AQ71) -> -14 | M71: =IF(L71>=0,"A JOUR",($L71*($M$12))) -> -28000 | O71: =IF(L71>=0,"A JOUR",($L71*($M$12+J71)+N71)) -> -42000 | P71: x | Q71: x | R71: NT | T71: #N/A | U71: #N/A | V71: #N/A | W71: 1000 | X71: 14 | Y71: -10 | Z71: -1 | AA71: -1 | AB71: -1 | AC71: 0 | AD71: -1
B72: 80 | C72: =CONCATENATE("N°-","00",B72,"-2024") -> N°-0080-2024 | D72: 773809784 | E72: Koto | F72: Ibrahima | G72: Leysaré | H72: Dakar | I72: 77 380 97 84 | J72: 2000 | K72: 1000 | L72: 0 | M72: =IF(L72>=0,"A JOUR",($L72*($M$12))) -> A JOUR | O72: =IF(L72>=0,"A JOUR",($L72*($M$12+J72))) -> A JOUR | P72: x | Q72: x | T72: #N/A | U72: GUINEE | Y72: 0 | Z72: 0 | AA72: 0 | AB72: 0 | AC72: 0 | AD72: 0
B73: 81 | C73: =CONCATENATE("N°-","00",B73,"-2024") -> N°-0081-2024 | D73: 777551504 | E73: Koto | F73: Ibrahima | G73: Porétély | H73: Dakar | I73: 77 755 15 04 | J73: 2000 | K73: 1000 | L73: =+SUM($Y73:$AQ73) -> -35 | M73: =IF(L73>=0,"A JOUR",($L73*($M$12))) -> -70000 | O73: =IF(L73>=0,"A JOUR",($L73*($M$12+J73)+N73)) -> -140000 | P73: x | Q73: x | T73: #N/A | U73: #N/A | V73: #N/A | W73: 2000 | X73: 35 | Y73: -31 | Z73: -1 | AA73: -1 | AB73: -1 | AC73: 0 | AD73: -1
B74: 82 | C74: =CONCATENATE("N°-","00",B74,"-2024") -> N°-0082-2024 | D74: 788380743 | E74: Mr | F74: Ibrahima ibn bappa Siradio | G74: Dowsaré | H74: Dakar | I74: 78 838 07 43 | J74: 1000 | K74: 1000 | L74: 0 | M74: =IF(L74>=0,"A JOUR",($L74*($M$12))) -> A JOUR | O74: =IF(L74>=0,"A JOUR",($L74*($M$12+J74))) -> A JOUR | T74: A JOUR | Y74: 0 | Z74: 0 | AA74: 0 | AB74: 0 | AC74: 0 | AD74: 0
B75: 83 | C75: =CONCATENATE("N°-","00",B75,"-2024") -> N°-0083-2024 | D75: 781292637 | E75: Koto | F75: Ibrahima KZA ibnou samara | G75: Dowsaré | H75: Casamance | I75: 78 129 26 37 | J75: 2000 | K75: 1000 | L75: =4-3 -> 1 | M75: =IF(L75>=0,"A JOUR",($L75*($M$12))) -> A JOUR | N75: =+L75*J75 -> 2000 | O75: =IF(L75>=0,"A JOUR",($L75*($M$12+J75))) -> A JOUR | P75: x | Q75: x | T75: A JOUR | Y75: 0 | Z75: 0 | AA75: 0 | AB75: 0 | AC75: 0 | AD75: 0
B76: 84 | C76: =CONCATENATE("N°-","00",B76,"-2024") -> N°-0084-2024 | D76: 774370979 | E76: Koto | F76: Ibrahima N°1 ibn bappa bala | G76: Pétel | H76: Dakar | I76: 77 437 09 79 | J76: 2000 | K76: 1000 | L76: 0 | M76: =IF(L76>=0,"A JOUR",($L76*($M$12))) -> A JOUR | O76: =IF(L76>=0,"A JOUR",($L76*($M$12+J76))) -> A JOUR | P76: x | Q76: x | R76: NT | T76: #N/A | U76: #N/A | V76: NT | Y76: 0 | Z76: 0 | AA76: 0 | AB76: 0 | AC76: 0 | AD76: 0
B77: 85 | C77: =CONCATENATE("N°-","00",B77,"-2024") -> N°-0085-2024 | D77: 774069087 | E77: Mr | F77: Ibrahima Sory | G77: Biilaa | H77: Dakar | I77: 77 406 90 87 | J77: 2000 | K77: 1000 | L77: 0 | M77: =IF(L77>=0,"A JOUR",($L77*($M$12))) -> A JOUR | O77: =IF(L77>=0,"A JOUR",($L77*($M$12+J77))) -> A JOUR | P77: x | Q77: x | T77: #N/A | U77: #N/A | V77: NT | Y77: 0 | Z77: 0 | AA77: 0 | AB77: 0 | AC77: 0 | AD77: 0
B78: 86 | C78: =CONCATENATE("N°-","00",B78,"-2024") -> N°-0086-2024 | D78: 750190226 | E78: Koto | F78: Ismaila | G78: Pétel | H78: Dakar | I78: 75 019 02 26 | J78: 1000 | K78: 1000 | L78: 0 | M78: =IF(L78>=0,"A JOUR",($L78*($M$12))) -> A JOUR | O78: =IF(L78>=0,"A JOUR",($L78*($M$12+J78))) -> A JOUR | P78: x | Q78: x | R78: NT | T78: #N/A | U78: #N/A | V78: NT | Y78: 0 | Z78: 0 | AA78: 0 | AB78: 0 | AC78: 0 | AD78: 0
B79: 90 | C79: =CONCATENATE("N°-","00",B79,"-2024") -> N°-0090-2024 | D79: 781344236 | E79: Koto | F79: Lamarana | G79: Pétel | H79: Dakar | I79: 78 134 42 36 | J79: 2000 | K79: 1000 | L79: 0 | M79: =IF(L79>=0,"A JOUR",($L79*($M$12))) -> A JOUR | O79: =IF(L79>=0,"A JOUR",($L79*($M$12+J79))) -> A JOUR | P79: x | Q79: x | R79: NT | T79: #N/A | U79: #N/A | V79: NT | Y79: 0 | Z79: 0 | AA79: 0 | AB79: 0 | AC79: 0 | AD79: 0
B80: 91 | C80: =CONCATENATE("N°-","00",B80,"-2024") -> N°-0091-2024 | D80: 778870311 | E80: Koto | F80: Mamadou Aliou | G80: Biilaa | H80: Dakar | I80: 77 887 03 11 | J80: 1000 | K80: 1000 | L80: =2-2 -> 0 | M80: =IF(L80>=0,"A JOUR",($L80*($M$12))) -> A JOUR | O80: =IF(L80>=0,"A JOUR",($L80*($M$12+J80))) -> A JOUR | P80: x | Q80: x | T80: A JOUR | Y80: 0 | Z80: 0 | AA80: 0 | AB80: 0 | AC80: 0 | AD80: 0
B81: 93 | C81: =CONCATENATE("N°-","00",B81,"-2024") -> N°-0093-2024 | D81: 775957597 | E81: Mr | F81: Mamadou aliou ibnu mamoudou | G81: Biilaa | H81: Dakar | I81: 77 595 75 97 | J81: 1000 | K81: 1000 | L81: =+SUM($Y81:$AQ81) -> -17 | M81: =IF(L81>=0,"A JOUR",($L81*($M$12))) -> -34000 | O81: =IF(L81>=0,"A JOUR",($L81*($M$12+J81)+N81)) -> -51000 | P81: x | T81: #N/A | U81: #N/A | V81: #N/A | W81: 1000 | X81: 17 | Y81: -17 | Z81: VG | AA81: VG | AB81: VG | AC81: 0 | AD81: VG
B82: 95 | C82: =CONCATENATE("N°-","00",B82,"-2024") -> N°-0095-2024 | D82: 773138810 | E82: Mr | F82: Mamadou alpha ibn Elhadji Ibrahima | G82: Pétel | H82: Dakar | I82: 77 313 88 10 | J82: 1000 | K82: 1000 | L82: =-34+9+25 -> 0 | M82: =IF(L82>=0,"A JOUR",($L82*($M$12))) -> A JOUR | O82: =IF(L82>=0,"A JOUR",($L82*($M$12+J82))) -> A JOUR | Q82: x | T82: A JOUR | Y82: 0 | Z82: 0 | AA82: 0 | AB82: 0 | AC82: 0 | AD82: 0
B83: 96 | C83: =CONCATENATE("N°-","00",B83,"-2024") -> N°-0096-2024 | D83: 772097607 | E83: Mr | F83: Mamadou bobo | G83: Biilaa | H83: Dakar | I83: 77 209 76 07 | J83: 1000 | K83: 1000 | L83: =+SUM($Y83:$AQ83) -> -30 | M83: =IF(L83>=0,"A JOUR",($L83*($M$12))) -> -60000 | O83: =IF(L83>=0,"A JOUR",($L83*($M$12+J83)+N83)) -> -90000 | P83: x | Q83: x | T83: #N/A | U83: #N/A | V83: #N/A | W83: 1000 | X83: 30 | Y83: -29 | Z83: 0 | AA83: 0 | AB83: 0 | AC83: 0 | AD83: -1
B84: 98 | C84: =CONCATENATE("N°-","00",B84,"-2024") -> N°-0098-2024 | D84: 766883758 | E84: Mr | F84: Mamadou lamarana | G84: Kourawoye | H84: Dakar | I84: 76 688 37 58 | J84: 1000 | K84: 1000 | L84: =2-1 -> 1 | M84: =IF(L84>=0,"A JOUR",($L84*($M$12))) -> A JOUR | N84: =+L84*J84 -> 1000 | O84: =IF(L84>=0,"A JOUR",($L84*($M$12+J84))) -> A JOUR | Q84: x | T84: A JOUR | Y84: 0 | Z84: 0 | AA84: 0 | AB84: 0 | AC84: 0 | AD84: 0
B85: 100 | C85: =CONCATENATE("N°-","0",B85,"-2024") -> N°-0100-2024 | D85: 776294040 | E85: Mr | F85: Mamadou missbaou | G85: Pétel | H85: Dakar | I85: 77 629 40 40 | J85: 2500 | K85: 1000 | L85: 0 | M85: =IF(L85>=0,"A JOUR",($L85*($M$12))) -> A JOUR | O85: =IF(L85>=0,"A JOUR",($L85*($M$12+J85))) -> A JOUR | P85: x | Q85: x | T85: A JOUR | Y85: 0 | Z85: 0 | AA85: 0 | AB85: 0 | AC85: 0 | AD85: 0
B86: 101 | C86: =CONCATENATE("N°-","0",B86,"-2024") -> N°-0101-2024 | D86: 785271042 | E86: Mr | F86: Mamadou saliou | G86: Dieydiyabhe | H86: Dakar | I86: 78 527 10 42 | J86: 1000 | K86: 1000 | L86: 0 | M86: =IF(L86>=0,"A JOUR",($L86*($M$12))) -> A JOUR | O86: =IF(L86>=0,"A JOUR",($L86*($M$12+J86))) -> A JOUR | P86: x | Q86: x | T86: A JOUR | Y86: 0 | Z86: 0 | AA86: 0 | AB86: 0 | AC86: 0 | AD86: 0
B87: 102 | C87: =CONCATENATE("N°-","0",B87,"-2024") -> N°-0102-2024 | D87: 776790254 | E87: Koto | F87: Mamadou Saliou | G87: Biilaa | H87: Dakar | I87: 77 679 02 54 | J87: 2000 | K87: 1000 | L87: =+SUM($Y87:$AQ87) -> -2 | M87: =IF(L87>=0,"A JOUR",($L87*($M$12))) -> -4000 | O87: =IF(L87>=0,"A JOUR",($L87*($M$12+J87)+N87)) -> -8000 | P87: x | Q87: x | T87: #N/A | U87: #N/A | V87: #N/A | W87: 2000 | X87: 2 | Y87: 0 | Z87: 0 | AA87: 0 | AB87: -1 | AC87: 0 | AD87: -1
B88: 104 | C88: =CONCATENATE("N°-","0",B88,"-2024") -> N°-0104-2024 | D88: 773092460 | E88: Koto | F88: Mamadou saliou | G88: Leysaré | H88: Dakar | I88: 77 309 24 60 | J88: XXX | K88: 1000 | L88: 0 | M88: =IF(L88>=0,"A JOUR",($L88*($M$12))) -> A JOUR | O88: =IF(L88>=0,"A JOUR",($L88*($M$12+J88))) -> A JOUR | Q88: x | T88: #N/A | U88: GUINEE | Y88: 0 | Z88: 0 | AA88: 0 | AB88: 0 | AC88: 0 | AD88: 0
B89: 106 | C89: =CONCATENATE("N°-","0",B89,"-2024") -> N°-0106-2024 | D89: 781245566 | E89: Kaou | F89: Mamadou Samba | G89: Dowsaré | H89: Dakar | I89: 78 124 55 66 | J89: 2000 | K89: 1000 | L89: 0 | M89: =IF(L89>=0,"A JOUR",($L89*($M$12))) -> A JOUR | O89: =IF(L89>=0,"A JOUR",($L89*($M$12+J89))) -> A JOUR | P89: x | Q89: x | T89: A JOUR | Y89: 0 | Z89: 0 | AA89: 0 | AB89: 0 | AC89: 0 | AD89: 0
B90: 108 | C90: =CONCATENATE("N°-","0",B90,"-2024") -> N°-0108-2024 | D90: 771581515 | E90: Mr | F90: Mamadou woury | G90: Dieydiyabhe | H90: Dakar | I90: 77 158 15 15 | J90: 2000 | K90: 1000 | L90: 0 | M90: =IF(L90>=0,"A JOUR",($L90*($M$12))) -> A JOUR | O90: =IF(L90>=0,"A JOUR",($L90*($M$12+J90))) -> A JOUR | P90: x | Q90: x | T90: A JOUR | Y90: 0 | Z90: 0 | AA90: 0 | AB90: 0 | AC90: 0 | AD90: 0
B91: 111 | C91: =CONCATENATE("N°-","0",B91,"-2024") -> N°-0111-2024 | D91: 778903424 | E91: Koto | F91: Mamoudou | G91: Mamasamba | H91: Dakar | I91: 77 890 34 24 | J91: 2000 | K91: 1000 | L91: =-1+1 -> 0 | M91: =IF(L91>=0,"A JOUR",($L91*($M$12))) -> A JOUR | O91: =IF(L91>=0,"A JOUR",($L91*($M$12+J91))) -> A JOUR | Q91: x | T91: A JOUR | Y91: 0 | Z91: 0 | AA91: 0 | AB91: 0 | AC91: 0 | AD91: 0
B92: 112 | C92: =CONCATENATE("N°-","0",B92,"-2024") -> N°-0112-2024 | D92: 776186896 | E92: Oustaz | F92: Mamoudou | G92: Dieydiyabhe | H92: Guinée | I92: 77 618 68 96 | J92: 2000 | K92: 1000 | L92: 0 | M92: =IF(L92>=0,"A JOUR",($L92*($M$12))) -> A JOUR | O92: =IF(L92>=0,"A JOUR",($L92*($M$12+J92))) -> A JOUR | Q92: x | R92: NT | T92: #N/A | U92: GUINEE | Y92: 0 | Z92: 0 | AA92: 0 | AB92: 0 | AC92: 0 | AD92: 0
B93: 113 | C93: =CONCATENATE("N°-","0",B93,"-2024") -> N°-0113-2024 | D93: 776541531 | E93: Grand | F93: Morlaye | G93: Kourawoye | H93: Dakar | I93: 77 654 15 31 | J93: 2000 | K93: 1000 | L93: =+SUM($Y93:$AQ93) -> -26 | M93: =IF(L93>=0,"A JOUR",($L93*($M$12))) -> -52000 | N93: 40000 | O93: =IF(L93>=0,"A JOUR",($L93*($M$12+J93)+N93)) -> -64000 | P93: x | Q93: x | T93: #N/A | U93: #N/A | V93: #N/A | W93: 2000 | X93: 26 | Y93: -22 | Z93: -1 | AA93: -1 | AB93: -1 | AC93: 0 | AD93: -1
B94: 114 | C94: =CONCATENATE("N°-","0",B94,"-2024") -> N°-0114-2024 | D94: 775359986 | E94: Bappa | F94: Mounirou | G94: Pétel | H94: Dakar | I94: 77 535 99 86 | J94: 2000 | K94: 1000 | L94: =3-3 -> 0 | M94: =IF(L94>=0,"A JOUR",($L94*($M$12))) -> A JOUR | O94: =IF(L94>=0,"A JOUR",($L94*($M$12+J94))) -> A JOUR | P94: x | Q94: x | T94: A JOUR | Y94: 0 | Z94: 0 | AA94: 0 | AB94: 0 | AC94: 0 | AD94: 0
B95: 116 | C95: =CONCATENATE("N°-","0",B95,"-2024") -> N°-0116-2024 | D95: 769651320 | E95: Mr | F95: Moussa bory | G95: Porétély | H95: Guinée | I95: 76 965 13 20 | J95: 1000 | K95: 1000 | L95: =+SUM($Y95:$AQ95) -> -15 | M95: =IF(L95>=0,"A JOUR",($L95*($M$12))) -> -30000 | O95: =IF(L95>=0,"A JOUR",($L95*($M$12+J95)+N95)) -> -45000 | P95: x | Q95: x | R95: NT | T95: #N/A | U95: #N/A | V95: #N/A | W95: 1000 | X95: 15 | Y95: -15 | Z95: VG | AA95: VG | AB95: VG | AC95: VG | AD95: VG
B96: 118 | C96: =CONCATENATE("N°-","0",B96,"-2024") -> N°-0118-2024 | D96: 708734775 | E96: Koto | F96: Saidou | G96: Pétédji | H96: Dakar | I96: 70 873 47 75 | J96: 2000 | K96: 1000 | L96: 0 | M96: =IF(L96>=0,"A JOUR",($L96*($M$12))) -> A JOUR | O96: =IF(L96>=0,"A JOUR",($L96*($M$12+J96))) -> A JOUR | P96: x | Q96: x | R96: NT | T96: #N/A | U96: #N/A | V96: NT | Y96: 0 | Z96: 0 | AA96: 0 | AB96: 0 | AC96: 0 | AD96: 0
B97: 120 | C97: =CONCATENATE("N°-","0",B97,"-2024") -> N°-0120-2024 | D97: 777934580 | E97: Mody | F97: Souleymane | G97: Dieydiyabhe | H97: Guinée | I97: 77 793 45 80 | J97: 2000 | K97: 1000 | L97: 0 | M97: =IF(L97>=0,"A JOUR",($L97*($M$12))) -> A JOUR | O97: =IF(L97>=0,"A JOUR",($L97*($M$12+J97))) -> A JOUR | Q97: x | R97: NT | T97: #N/A | U97: GUINEE | Y97: 0 | Z97: 0 | AA97: 0 | AB97: 0 | AC97: 0 | AD97: 0
B98: 121 | C98: =CONCATENATE("N°-","0",B98,"-2024") -> N°-0121-2024 | D98: 773154627 | E98: Mr | F98: Souleymane ibn Elhadji Ibrahima | G98: Pétel | H98: Dakar | I98: 77 315 46 27 | J98: 1000 | K98: 1000 | L98: =+SUM($Y98:$AQ98) -> -32 | M98: =IF(L98>=0,"A JOUR",($L98*($M$12))) -> -64000 | N98: 44000 | O98: =IF(L98>=0,"A JOUR",($L98*($M$12+J98)+N98)) -> -52000 | Q98: x | T98: #N/A | U98: #N/A | V98: #N/A | W98: 1000 | X98: 32 | Y98: -32 | Z98: 0 | AA98: 0 | AB98: 0 | AC98: 0 | AD98: 0
B99: 122 | C99: =CONCATENATE("N°-","0",B99,"-2024") -> N°-0122-2024 | D99: 775044149 | E99: Mr | F99: Souleymane PH | G99: Pétel | H99: Guinée | I99: 77 504 41 49 | J99: 1000 | K99: 1000 | L99: 0 | M99: =IF(L99>=0,"A JOUR",($L99*($M$12))) -> A JOUR | O99: =IF(L99>=0,"A JOUR",($L99*($M$12+J99))) -> A JOUR | P99: x | Q99: x | R99: NT | T99: #N/A | U99: #N/A | V99: NT | Y99: 0 | Z99: 0 | AA99: 0 | AB99: 0 | AC99: 0 | AD99: 0
B100: 123 | C100: =CONCATENATE("N°-","0",B100,"-2024") -> N°-0123-2024 | D100: 779821894 | E100: Mr | F100: Thierno Amadou bente malipan | G100: Dowsaré | H100: Dakar | I100: 77 982 18 94 | J100: 1000 | K100: 1000 | L100: =+SUM($Y100:$AQ100) -> -15 | M100: =IF(L100>=0,"A JOUR",($L100*($M$12))) -> -30000 | O100: =IF(L100>=0,"A JOUR",($L100*($M$12+J100)+N100)) -> -45000 | P100: x | Q100: x | T100: #N/A | U100: #N/A | V100: #N/A | W100: 1000 | X100: 15 | Y100: -11 | Z100: -1 | AA100: -1 | AB100: -1 | AC100: 0 | AD100: -1
B101: 124 | C101: =CONCATENATE("N°-","0",B101,"-2024") -> N°-0124-2024 | D101: 777289658 | E101: Mr | F101: Thierno boubacar ibn Elhadji M. Woury | G101: Pétel | H101: Dakar | I101: 77 728 96 58 | J101: 2500 | K101: 1000 | L101: 0 | M101: =IF(L101>=0,"A JOUR",($L101*($M$12))) -> A JOUR | O101: =IF(L101>=0,"A JOUR",($L101*($M$12+J101))) -> A JOUR | P101: x | Q101: x | T101: #N/A | U101: #N/A | V101: #N/A | W101: #N/A | X101: #N/A | Y101: 0 | Z101: 0 | AA101: 0 | AB101: 0 | AC101: 0 | AD101: 0
B102: 125 | C102: =CONCATENATE("N°-","0",B102,"-2024") -> N°-0125-2024 | D102: 772244914 | E102: Mr | F102: Thierno boubacar SG | G102: Kourawoye | H102: Dakar | I102: 77 224 49 14 | J102: 1000 | K102: 1000 | L102: 0 | M102: =IF(L102>=0,"A JOUR",($L102*($M$12))) -> A JOUR | O102: =IF(L102>=0,"A JOUR",($L102*($M$12+J102))) -> A JOUR | P102: x | Q102: x | T102: #N/A | U102: GUINEE | Y102: 0 | Z102: 0 | AA102: 0 | AB102: 0 | AC102: 0 | AD102: 0
B103: 126 | C103: =CONCATENATE("N°-","0",B103,"-2024") -> N°-0126-2024 | E103: Mr | F103: Thierno Daouda | G103: Kourawoye | H103: Guinée | J103: 1000 | K103: 1000 | L103: VG | M103: =IF(L103>=0,"A JOUR",($L103*($M$12))) -> A JOUR | O103: =IF(L103>=0,"A JOUR",($L103*($M$12+J103))) -> A JOUR | P103: x | R103: VG | T103: #N/A | U103: #N/A | V103: #N/A | W103: #N/A | X103: #N/A | Y103: 0 | Z103: 0 | AA103: 0 | AB103: 0 | AC103: 0 | AD103: 0
B104: 127 | C104: =CONCATENATE("N°-","0",B104,"-2024") -> N°-0127-2024 | D104: 775754156 | E104: Mr | F104: Thierno hady | G104: Dowsaré | H104: Dakar | I104: 77 575 41 56 | J104: 1000 | K104: 1000 | L104: 0 | M104: =IF(L104>=0,"A JOUR",($L104*($M$12))) -> A JOUR | O104: =IF(L104>=0,"A JOUR",($L104*($M$12+J104))) -> A JOUR | P104: x | Q104: x | T104: #N/A | U104: #N/A | V104: #N/A | W104: #N/A | X104: #N/A | Y104: 0 | Z104: 0 | AA104: 0 | AB104: 0 | AC104: 0 | AD104: 0
B105: 129 | C105: =CONCATENATE("N°-","0",B105,"-2024") -> N°-0129-2024 | D105: 784083809 | E105: Mr | F105: Thierno ibrahima congolais | G105: Kourawoye | H105: Dakar | I105: 78 408 38 09 | J105: 1000 | K105: 1000 | L105: =+SUM($Y105:$AQ105) -> -6 | M105: =IF(L105>=0,"A JOUR",($L105*($M$12))) -> -12000 | O105: =IF(L105>=0,"A JOUR",($L105*($M$12+J105)+N105)) -> -18000 | P105: x | Q105: x | T105: #N/A | U105: #N/A | V105: #N/A | W105: 1000 | X105: 6 | Y105: -3 | Z105: -1 | AA105: -1 | AB105: -1 | AC105: 0 | AD105: 0
B106: 130 | C106: =CONCATENATE("N°-","0",B106,"-2024") -> N°-0130-2024 | D106: 776154531 | E106: Mr | F106: Thierno mamadou Saliou varane | G106: Biilaa | H106: Dakar | I106: 77 615 45 31 | J106: 1000 | K106: 1000 | L106: =+SUM($Y106:$AQ106) -> -15 | M106: =IF(L106>=0,"A JOUR",($L106*($M$12))) -> -30000 | N106: 26000 | O106: =IF(L106>=0,"A JOUR",($L106*($M$12+J106)+N106)) -> -19000 | P106: x | Q106: x | T106: #N/A | U106: #N/A | V106: #N/A | W106: 1000 | X106: 15 | Y106: -12 | Z106: -1 | AA106: -1 | AB106: -1 | AC106: 0 | AD106: 0
B107: 131 | C107: =CONCATENATE("N°-","0",B107,"-2024") -> N°-0131-2024 | D107: xxxxxxxx | E107: Mr | F107: Thierno mamadou Coumba | G107: Dowsaré | H107: Gambie | I107: xxxxxxxx | J107: 1000 | K107: 1000 | L107: 0 | M107: =IF(L107>=0,"A JOUR",($L107*($M$12))) -> A JOUR | O107: =IF(L107>=0,"A JOUR",($L107*($M$12+J107))) -> A JOUR | P107: x | Q107: x | R107: VG | T107: #N/A | U107: #N/A | V107: #N/A | W107: #N/A | X107: #N/A | Y107: 0 | Z107: 0 | AA107: 0 | AB107: 0 | AC107: 0 | AD107: 0

Sheet Feuil1
B4: N° | C4: Code | D4: Titre | E4: Désignation | F4: Missidé | G4: Pays/région | H4: Téléphone | I4: Montant mensuel MSD | J4: Montant mensuel UJDS | K4: Nbre de mois retard | L4: Amande | M4: Avance | N4: Montant dû au 15 01 25 | O4: UJDS | P4: MOUSSIDAL | Q4: STATUT
B5: 1 | C5: N°-0001-2024 | D5: =+VLOOKUP($C5,'Données MSDL'!$C$13:$O$148,3,FALSE) -> Mr | E5: =+VLOOKUP($C5,'Données MSDL'!$C$13:$O$148,4,FALSE) -> Abdoul aziz ibn Elhadji Ibrahima | F5: =+VLOOKUP($C5,'Données MSDL'!$C$13:$O$148,5,FALSE) -> Pétel | G5: =+VLOOKUP($C5,'Données MSDL'!$C$13:$O$148,6,FALSE) -> Dakar | H5: =+VLOOKUP($C5,'Données MSDL'!$C$13:$O$148,7,FALSE) -> 77 877 98 67 | I5: =+VLOOKUP($C5,'Données MSDL'!$C$13:$O$148,8,FALSE) -> 1000 | J5: =+VLOOKUP($C5,'Données MSDL'!$C$13:$O$148,9,FALSE) -> N/A | K5: =+VLOOKUP($C5,'Données MSDL'!$C$13:$O$148,10,FALSE) -> -56 | L5: =+VLOOKUP($C5,'Données MSDL'!$C$13:$O$148,11,FALSE) -> -112000 | M5: =+VLOOKUP($C5,'Données MSDL'!$C$13:$O$148,12,FALSE) -> 0 | N5: =+VLOOKUP($C5,'Données MSDL'!$C$13:$O$148,13,FALSE) -> -168000
B6: 2 | C6: N°-0002-2024 | D6: =+VLOOKUP($C6,'Données MSDL'!$C$13:$O$148,3,FALSE) -> Koto | E6: =+VLOOKUP($C6,'Données MSDL'!$C$13:$O$148,4,FALSE) -> Abdoul ghadry | F6: =+VLOOKUP($C6,'Données MSDL'!$C$13:$O$148,5,FALSE) -> Leysaré | G6: =+VLOOKUP($C6,'Données MSDL'!$C$13:$O$148,6,FALSE) -> Dakar | H6: =+VLOOKUP($C6,'Données MSDL'!$C$13:$O$148,7,FALSE) -> 77 217 52 92 | I6: =+VLOOKUP($C6,'Données MSDL'!$C$13:$O$148,8,FALSE) -> 2000 | J6: =+VLOOKUP($C6,'Données MSDL'!$C$13:$O$148,9,FALSE) -> 1000 | K6: =+VLOOKUP($C6,'Données MSDL'!$C$13:$O$148,10,FALSE) -> 0 | L6: =+VLOOKUP($C6,'Données MSDL'!$C$13:$O$148,11,FALSE) -> A JOUR | M6: =+VLOOKUP($C6,'Données MSDL'!$C$13:$O$148,12,FALSE) -> 0 | N6: =+VLOOKUP($C6,'Données MSDL'!$C$13:$O$148,13,FALSE) -> A JOUR
B7: 3 | C7: N°-0003-2024 | D7: =+VLOOKUP($C7,'Données MSDL'!$C$13:$O$148,3,FALSE) -> Mr | E7: =+VLOOKUP($C7,'Données MSDL'!$C$13:$O$148,4,FALSE) -> Abdoul goudoussy | F7: =+VLOOKUP($C7,'Données MSDL'!$C$13:$O$148,5,FALSE) -> Kourawoye | G7: =+VLOOKUP($C7,'Données MSDL'!$C$13:$O$148,6,FALSE) -> Guinée | H7: =+VLOOKUP($C7,'Données MSDL'!$C$13:$O$148,7,FALSE) -> xxxxxxxx | I7: =+VLOOKUP($C7,'Données MSDL'!$C$13:$O$148,8,FALSE) -> 0 | J7: =+VLOOKUP($C7,'Données MSDL'!$C$13:$O$148,9,FALSE) -> 1000 | K7: =+VLOOKUP($C7,'Données MSDL'!$C$13:$O$148,10,FALSE) -> VG | L7: =+VLOOKUP($C7,'Données MSDL'!$C$13:$O$148,11,FALSE) -> A JOUR | M7: =+VLOOKUP($C7,'Données MSDL'!$C$13:$O$148,12,FALSE) -> 0 | N7: =+VLOOKUP($C7,'Données MSDL'!$C$13:$O$148,13,FALSE) -> A JOUR
B8: 4 | C8: N°-0004-2024 | D8: =+VLOOKUP($C8,'Données MSDL'!$C$13:$O$148,3,FALSE) -> Kaou | E8: =+VLOOKUP($C8,'Données MSDL'!$C$13:$O$148,4,FALSE) -> Abdoul malipan | F8: =+VLOOKUP($C8,'Données MSDL'!$C$13:$O$148,5,FALSE) -> Dowsaré | G8: =+VLOOKUP($C8,'Données MSDL'!$C$13:$O$148,6,FALSE) -> Dakar | H8: =+VLOOKUP($C8,'Données MSDL'!$C$13:$O$148,7,FALSE) -> 77 352 83 33 | I8: =+VLOOKUP($C8,'Données MSDL'!$C$13:$O$148,8,FALSE) -> 2000 | J8: =+VLOOKUP($C8,'Données MSDL'!$C$13:$O$148,9,FALSE) -> N/A | K8: =+VLOOKUP($C8,'Données MSDL'!$C$13:$O$148,10,FALSE) -> -25 | L8: =+VLOOKUP($C8,'Données MSDL'!$C$13:$O$148,11,FALSE) -> -50000 | M8: =+VLOOKUP($C8,'Données MSDL'!$C$13:$O$148,12,FALSE) -> 0 | N8: =+VLOOKUP($C8,'Données MSDL'!$C$13:$O$148,13,FALSE) -> -100000
B9: 5 | C9: N°-0005-2024 | D9: =+VLOOKUP($C9,'Données MSDL'!$C$13:$O$148,3,FALSE) -> Koto | E9: =+VLOOKUP($C9,'Données MSDL'!$C$13:$O$148,4,FALSE) -> Abdoul salam | F9: =+VLOOKUP($C9,'Données MSDL'!$C$13:$O$148,5,FALSE) -> Gobihi | G9: =+VLOOKUP($C9,'Données MSDL'!$C$13:$O$148,6,FALSE) -> Gambie | H9: =+VLOOKUP($C9,'Données MSDL'!$C$13:$O$148,7,FALSE) -> xxxxxxxx | I9: =+VLOOKUP($C9,'Données MSDL'!$C$13:$O$148,8,FALSE) -> 2000 | J9: =+VLOOKUP($C9,'Données MSDL'!$C$13:$O$148,9,FALSE) -> 1000 | K9: =+VLOOKUP($C9,'Données MSDL'!$C$13:$O$148,10,FALSE) -> 0 | L9: =+VLOOKUP($C9,'Données MSDL'!$C$13:$O$148,11,FALSE) -> A JOUR | M9: =+VLOOKUP($C9,'Données MSDL'!$C$13:$O$148,12,FALSE) -> 0 | N9: =+VLOOKUP($C9,'Données MSDL'!$C$13:$O$148,13,FALSE) -> A JOUR
B10: 6 | C10: N°-0006-2024 | D10: =+VLOOKUP($C10,'Données MSDL'!$C$13:$O$148,3,FALSE) -> Mr | E10: =+VLOOKUP($C10,'Données MSDL'!$C$13:$O$148,4,FALSE) -> Abdoul salam petit ibn bappa bala | F10: =+VLOOKUP($C10,'Données MSDL'!$C$13:$O$148,5,FALSE) -> Pétel | G10: =+VLOOKUP($C10,'Données MSDL'!$C$13:$O$148,6,FALSE) -> Dakar | H10: =+VLOOKUP($C10,'Données MSDL'!$C$13:$O$148,7,FALSE) -> 77 478 90 94 | I10: =+VLOOKUP($C10,'Données MSDL'!$C$13:$O$148,8,FALSE) -> 2000 | J10: =+VLOOKUP($C10,'Données MSDL'!$C$13:$O$148,9,FALSE) -> 1000 | K10: =+VLOOKUP($C10,'Données MSDL'!$C$13:$O$148,10,FALSE) -> 0 | L10: =+VLOOKUP($C10,'Données MSDL'!$C$13:$O$148,11,FALSE) -> A JOUR | M10: =+VLOOKUP($C10,'Données MSDL'!$C$13:$O$148,12,FALSE) -> 0 | N10: =+VLOOKUP($C10,'Données MSDL'!$C$13:$O$148,13,FALSE) -> A JOUR
B11: 7 | C11: N°-0007-2024 | D11: =+VLOOKUP($C11,'Données MSDL'!$C$13:$O$148,3,FALSE) -> Koto | E11: =+VLOOKUP($C11,'Données MSDL'!$C$13:$O$148,4,FALSE) -> Abdoul salam ibn Elhadji M. Woury VP | F11: =+VLOOKUP($C11,'Données MSDL'!$C$13:$O$148,5,FALSE) -> Pétel | G11: =+VLOOKUP($C11,'Données MSDL'!$C$13:$O$148,6,FALSE) -> Dakar | H11: =+VLOOKUP($C11,'Données MSDL'!$C$13:$O$148,7,FALSE) -> 78 105 03 63 | I11: =+VLOOKUP($C11,'Données MSDL'!$C$13:$O$148,8,FALSE) -> 2000 | J11: =+VLOOKUP($C11,'Données MSDL'!$C$13:$O$148,9,FALSE) -> 1000 | K11: =+VLOOKUP($C11,'Données MSDL'!$C$13:$O$148,10,FALSE) -> 0 | L11: =+VLOOKUP($C11,'Données MSDL'!$C$13:$O$148,11,FALSE) -> A JOUR | M11: =+VLOOKUP($C11,'Données MSDL'!$C$13:$O$148,12,FALSE) -> 0 | N11: =+VLOOKUP($C11,'Données MSDL'!$C$13:$O$148,13,FALSE) -> A JOUR
B12: 8 | C12: N°-0008-2024 | D12: =+VLOOKUP($C12,'Données MSDL'!$C$13:$O$148,3,FALSE) -> Mr | E12: =+VLOOKUP($C12,'Données MSDL'!$C$13:$O$148,4,FALSE) -> Abdoul salam ibn karamoko Daouda | F12: =+VLOOKUP($C12,'Données MSDL'!$C$13:$O$148,5,FALSE) -> Pétel | G12: =+VLOOKUP($C12,'Données MSDL'!$C$13:$O$148,6,FALSE) -> Gabon | H12: =+VLOOKUP($C12,'Données MSDL'!$C$13:$O$148,7,FALSE) -> +241 04 50 65 55 | I12: =+VLOOKUP($C12,'Données MSDL'!$C$13:$O$148,8,FALSE) -> 5000 | J12: =+VLOOKUP($C12,'Données MSDL'!$C$13:$O$148,9,FALSE) -> N/A | K12: =+VLOOKUP($C12,'Données MSDL'!$C$13:$O$148,10,FALSE) -> 0 | L12: =+VLOOKUP($C12,'Données MSDL'!$C$13:$O$148,11,FALSE) -> A JOUR | M12: =+VLOOKUP($C12,'Données MSDL'!$C$13:$O$148,12,FALSE) -> 0 | N12: =+VLOOKUP($C12,'Données MSDL'!$C$13:$O$148,13,FALSE) -> A JOUR
B13: 9 | C13: N°-0009-2024 | D13: =+VLOOKUP($C13,'Données MSDL'!$C$13:$O$148,3,FALSE) -> Mr | E13: =+VLOOKUP($C13,'Données MSDL'!$C$13:$O$148,4,FALSE) -> Abdoul salam petit | F13: =+VLOOKUP($C13,'Données MSDL'!$C$13:$O$148,5,FALSE) -> Pétel | G13: =+VLOOKUP($C13,'Données MSDL'!$C$13:$O$148,6,FALSE) -> Dakar | H13: =+VLOOKUP($C13,'Données MSDL'!$C$13:$O$148,7,FALSE) -> 77 478 90 94 | I13: =+VLOOKUP($C13,'Données MSDL'!$C$13:$O$148,8,FALSE) -> 2000 | J13: =+VLOOKUP($C13,'Données MSDL'!$C$13:$O$148,9,FALSE) -> 1000 | K13: =+VLOOKUP($C13,'Données MSDL'!$C$13:$O$148,10,FALSE) -> 0 | L13: =+VLOOKUP($C13,'Données MSDL'!$C$13:$O$148,11,FALSE) -> A JOUR | M13: =+VLOOKUP($C13,'Données MSDL'!$C$13:$O$148,12,FALSE) -> 0 | N13: =+VLOOKUP($C13,'Données MSDL'!$C$13:$O$148,13,FALSE) -> A JOUR
B14: 10 | C14: N°-0010-2024 | D14: =+VLOOKUP($C14,'Données MSDL'!$C$13:$O$148,3,FALSE) -> Mr | E14: =+VLOOKUP($C14,'Données MSDL'!$C$13:$O$148,4,FALSE) -> Abdoul salam PP | F14: =+VLOOKUP($C14,'Données MSDL'!$C$13:$O$148,5,FALSE) -> Dieydiyabhe | G14: =+VLOOKUP($C14,'Données MSDL'!$C$13:$O$148,6,FALSE) -> Dakar | H14: =+VLOOKUP($C14,'Données MSDL'!$C$13:$O$148,7,FALSE) -> 77 679 26 24 | I14: =+VLOOKUP($C14,'Données MSDL'!$C$13:$O$148,8,FALSE) -> 1000 | J14: =+VLOOKUP($C14,'Données MSDL'!$C$13:$O$148,9,FALSE) -> 1000 | K14: =+VLOOKUP($C14,'Données MSDL'!$C$13:$O$148,10,FALSE) -> 0 | L14: =+VLOOKUP($C14,'Données MSDL'!$C$13:$O$148,11,FALSE) -> A JOUR | M14: =+VLOOKUP($C14,'Données MSDL'!$C$13:$O$148,12,FALSE) -> 0 | N14: =+VLOOKUP($C14,'Données MSDL'!$C$13:$O$148,13,FALSE) -> A JOUR
B15: 11 | C15: N°-0011-2024 | D15: =+VLOOKUP($C15,'Données MSDL'!$C$13:$O$148,3,FALSE) -> Mr | E15: =+VLOOKUP($C15,'Données MSDL'!$C$13:$O$148,4,FALSE) -> Abdoul salam PP (ivoire) | F15: =+VLOOKUP($C15,'Données MSDL'!$C$13:$O$148,5,FALSE) -> Dowsaré | G15: =+VLOOKUP($C15,'Données MSDL'!$C$13:$O$148,6,FALSE) -> Dakar | H15: =+VLOOKUP($C15,'Données MSDL'!$C$13:$O$148,7,FALSE) -> 77 577 99 80 | I15: =+VLOOKUP($C15,'Données MSDL'!$C$13:$O$148,8,FALSE) -> 1000 | J15: =+VLOOKUP($C15,'Données MSDL'!$C$13:$O$148,9,FALSE) -> 1000 | K15: =+VLOOKUP($C15,'Données MSDL'!$C$13:$O$148,10,FALSE) -> -2 | L15: =+VLOOKUP($C15,'Données MSDL'!$C$13:$O$148,11,FALSE) -> -4000 | M15: =+VLOOKUP($C15,'Données MSDL'!$C$13:$O$148,12,FALSE) -> 0 | N15: =+VLOOKUP($C15,'Données MSDL'!$C$13:$O$148,13,FALSE) -> -6000
B16: 12 | C16: N°-0012-2024 | D16: =+VLOOKUP($C16,'Données MSDL'!$C$13:$O$148,3,FALSE) -> Mr | E16: =+VLOOKUP($C16,'Données MSDL'!$C$13:$O$148,4,FALSE) -> Abdoulaye | F16: =+VLOOKUP($C16,'Données MSDL'!$C$13:$O$148,5,FALSE) -> Daandé Mboully | G16: =+VLOOKUP($C16,'Données MSDL'!$C$13:$O$148,6,FALSE) -> Guinée | H16: =+VLOOKUP($C16,'Données MSDL'!$C$13:$O$148,7,FALSE) -> 0 | I16: =+VLOOKUP($C16,'Données MSDL'!$C$13:$O$148,8,FALSE) -> 0 | J16: =+VLOOKUP($C16,'Données MSDL'!$C$13:$O$148,9,FALSE) -> 1000 | K16: =+VLOOKUP($C16,'Données MSDL'!$C$13:$O$148,10,FALSE) -> VG | L16: =+VLOOKUP($C16,'Données MSDL'!$C$13:$O$148,11,FALSE) -> A JOUR | M16: =+VLOOKUP($C16,'Données MSDL'!$C$13:$O$148,12,FALSE) -> 0 | N16: =+VLOOKUP($C16,'Données MSDL'!$C$13:$O$148,13,FALSE) -> A JOUR
... B137: 133 | C137: N°-0133-2024 | D137: =+VLOOKUP($C137,'Données MSDL'!$C$13:$O$148,3,FALSE) -> Koto | E137: =+VLOOKUP($C137,'Données MSDL'!$C$13:$O$148,4,FALSE) -> Woury | F137: =+VLOOKUP($C137,'Données MSDL'!$C$13:$O$148,5,FALSE) -> Dowsaré | G137: =+VLOOKUP($C137,'Données MSDL'!$C$13:$O$148,6,FALSE) -> Guinée | H137: =+VLOOKUP($C137,'Données MSDL'!$C$13:$O$148,7,FALSE) -> xxxxxxxx | I137: =+VLOOKUP($C137,'Données MSDL'!$C$13:$O$148,8,FALSE) -> N/A | J137: =+VLOOKUP($C137,'Données MSDL'!$C$13:$O$148,9,FALSE) -> N/A | K137: =+VLOOKUP($C137,'Données MSDL'!$C$13:$O$148,10,FALSE) -> 0 | L137: =+VLOOKUP($C137,'Données MSDL'!$C$13:$O$148,11,FALSE) -> A JOUR | M137: =+VLOOKUP($C137,'Données MSDL'!$C$13:$O$148,12,FALSE) -> 0 | N137: =+VLOOKUP($C137,'Données MSDL'!$C$13:$O$148,13,FALSE) -> A JOUR

Sheet Feuil2
B5: SOLDE ANTERIEUR
B6: DEPENSES DU MOIS
B7: VERSEMENT DU MOIS
B8: REVENUS SUPPLEMENTAIRE DU MOIS
B9: TOTAL SOLDE ACTUEL
B11: SOLDE ANTERIEUR
B12: DEPENSES DU MOIS
B13: VERSEMENT DU MOIS
B14: REVENUS SUPPLEMENTAIRE DU MOIS
B15: TOTAL SOLDE ACTUEL

Sheet Données MSDL (2)
B6: UNION DES JEUNES DE DOUKA SELEYABE
G8: =+TODAY() -> 46001
B10: LISTE OFFICIELLE DES MEMBRES
M12: 2000 | O12: =SUM(O14:O148) -> 280500 | U12: A JOUR | V12: GUINEE | W12: NT | X12: DETTE
B13: N° | C13: Code | D13: Téléphone | E13: Titre | F13: Désignation | G13: Missidé | H13: Pays/région | I13: Téléphone | J13: Montant mensuel MSD | K13: Montant mensuel UJDS | L13: Nbre de mois retard | M13: Amande | N13: Versement | O13: Avance | P13: Montant dû au 28 02 25 | Q13: UJDS | R13: MOUSSIDAL | S13: STATUT | Z13: 45689 | AA13: 45717 | AB13: 45748 | AC13: 45778 | AD13: 45809 | AE13: 45839 | AF13: 45870 | AG13: 45901 | AH13: 45931 | AI13: 45962 | AJ13: 45992 | AK13: 46023 | AL13: 46054 | AM13: 46082 | AN13: 46113 | AO13: 46143 | AP13: 46174 | AQ13: 45962 | AR13: 45992
B14: 1 | C14: =CONCATENATE("N°-","000",B14,"-2024") -> N°-0001-2024 | D14: 778779867 | E14: Mr | F14: Abdoul aziz ibn Elhadji Ibrahima | G14: Pétel | H14: Dakar | I14: 77 877 98 67 | J14: 1000 | K14: N/A | L14: =+IF(SUM($Z14:$AR14)>0,0,SUM($Z14:$AR14)) -> -57 | M14: =IF(L14>=0,"A JOUR",($L14*($M$12))) -> -114000 | N14: =IF(L14>0,SUM($Z14:$AR14)*$J14,0) -> 0 | O14: =+IF(L14>0,L14*J14,0) -> 0 | P14: =IF(L14>=0,"A JOUR",($L14*($M$12+J14)+O14)) -> -171000 | R14: x | U14: #N/A | V14: #N/A | W14: #N/A | X14: 1000 | Y14: 56 | Z14: -57
B15: 2 | C15: =CONCATENATE("N°-","000",B15,"-2024") -> N°-0002-2024 | D15: 772175292 | E15: Koto | F15: Abdoul ghadry | G15: Leysaré | H15: Dakar | I15: 77 217 52 92 | J15: 2000 | K15: 1000 | L15: 0 | M15: =IF(L15>=0,"A JOUR",($L15*($M$12))) -> A JOUR | N15: =IF(L15>0,SUM($Z15:$AR15)*$J15,0) -> 0 | O15: =+IF(L15>0,L15*J15,0) -> 0 | P15: =IF(L15>=0,"A JOUR",($L15*($M$12+J15)+O15)) -> A JOUR | Q15: x | R15: x | U15: A JOUR | Z15: 1
B16: 3 | C16: =CONCATENATE("N°-","000",B16,"-2024") -> N°-0003-2024 | D16: xxxxxxxx | E16: Mr | F16: Abdoul goudoussy | G16: Kourawoye | H16: Guinée | I16: xxxxxxxx | K16: 1000 | L16: VG | M16: =IF(L16>=0,"A JOUR",($L16*($M$12))) -> A JOUR | N16: =IF(L16>0,SUM($Z16:$AR16)*$J16,0) -> 0 | P16: =IF(L16>=0,"A JOUR",($L16*($M$12+J16)+O16)) -> A JOUR | Q16: x | S16: VG | U16: #N/A | V16: #N/A | W16: #N/A | X16: #N/A | Y16: #N/A | Z16: VG
B17: 4 | C17: =CONCATENATE("N°-","000",B17,"-2024") -> N°-0004-2024 | D17: 773528333 | E17: Kaou | F17: Abdoul malipan | G17: Dowsaré | H17: Dakar | I17: 77 352 83 33 | J17: 2000 | K17: N/A | L17: =+SUM($Z17:$AR17) -> -27 | M17: =IF(L17>=0,"A JOUR",($L17*($M$12))) -> -54000 | N17: =IF(L17>0,SUM($Z17:$AR17)*$J17,0) -> 0 | O17: =+IF(L17>0,L17*J17,0) -> 0 | P17: =IF(L17>=0,"A JOUR",($L17*($M$12+J17)+O17)) -> -108000 | R17: x | U17: #N/A | V17: #N/A | W17: #N/A | X17: 2000 | Y17: 25 | Z17: -27
B18: 5 | C18: =CONCATENATE("N°-","000",B18,"-2024") -> N°-0005-2024 | D18: xxxxxxxx | E18: Koto | F18: Abdoul salam | G18: Gobihi | H18: Gambie | I18: xxxxxxxx | J18: 2000 | K18: 1000 | M18: =IF(L18>=0,"A JOUR",($L18*($M$12))) -> A JOUR | N18: =IF(L18>0,SUM($Z18:$AR18)*$J18,0) -> 0 | O18: =+IF(L18>0,L18*J18,0) -> 0 | P18: =IF(L18>=0,"A JOUR",($L18*($M$12+J18)+O18)) -> A JOUR | R18: x | U18: #N/A | V18: #N/A | W18: #N/A | X18: #N/A | Y18: #N/A
B19: 6 | C19: =CONCATENATE("N°-","000",B19,"-2024") -> N°-0006-2024 | D19: 774789094 | E19: Mr | F19: Abdoul salam petit ibn bappa bala | G19: Pétel | H19: Dakar | I19: 77 478 90 94 | J19: 2000 | K19: 1000 | L19: 0 | M19: =IF(L19>=0,"A JOUR",($L19*($M$12))) -> A JOUR | N19: =IF(L19>0,SUM($Z19:$AR19)*$J19,0) -> 0 | O19: =+IF(L19>0,L19*J19,0) -> 0 | P19: =IF(L19>=0,"A JOUR",($L19*($M$12+J19)+O19)) -> A JOUR | Q19: x | R19: x | U19: A JOUR
B20: 7 | C20: =CONCATENATE("N°-","000",B20,"-2024") -> N°-0007-2024 | D20: 781050363 | E20: Koto | F20: Abdoul salam ibn Elhadji M. Woury VP | G20: Pétel | H20: Dakar | I20: 78 105 03 63 | J20: 2000 | K20: 1000 | L20: 0 | M20: =IF(L20>=0,"A JOUR",($L20*($M$12))) -> A JOUR | N20: =IF(L20>0,SUM($Z20:$AR20)*$J20,0) -> 0 | O20: =+IF(L20>0,L20*J20,0) -> 0 | P20: =IF(L20>=0,"A JOUR",($L20*($M$12+J20)+O20)) -> A JOUR | Q20: x | R20: x | U20: A JOUR | Z20: 1
B21: 8 | C21: =CONCATENATE("N°-","000",B21,"-2024") -> N°-0008-2024 | D21: +24104506555 | E21: Mr | F21: Abdoul salam ibn karamoko Daouda | G21: Pétel | H21: Gabon | I21: +241 04 50 65 55 | J21: 5000 | K21: N/A | M21: =IF(L21>=0,"A JOUR",($L21*($M$12))) -> A JOUR | N21: =IF(L21>0,SUM($Z21:$AR21)*$J21,0) -> 0 | P21: =IF(L21>=0,"A JOUR",($L21*($M$12+J21)+O21)) -> A JOUR | R21: x | U21: #N/A | V21: #N/A | W21: #N/A | X21: #N/A | Y21: #N/A
B22: 9 | C22: =CONCATENATE("N°-","000",B22,"-2024") -> N°-0009-2024 | D22: 774789094 | E22: Mr | F22: Abdoul salam petit | G22: Pétel | H22: Dakar | I22: 77 478 90 94 | J22: 2000 | K22: 1000 | L22: 0 | M22: =IF(L22>=0,"A JOUR",($L22*($M$12))) -> A JOUR | N22: =IF(L22>0,SUM($Z22:$AR22)*$J22,0) -> 0 | O22: =+IF(L22>0,L22*J22,0) -> 0 | P22: =IF(L22>=0,"A JOUR",($L22*($M$12+J22)+O22)) -> A JOUR | Q22: x | R22: x | U22: A JOUR | Z22: NT
B23: 10 | C23: =CONCATENATE("N°-","00",B23,"-2024") -> N°-0010-2024 | D23: 776792624 | E23: Mr | F23: Abdoul salam PP | G23: Dieydiyabhe | H23: Dakar | I23: 77 679 26 24 | J23: 1000 | K23: 1000 | L23: 0 | M23: =IF(L23>=0,"A JOUR",($L23*($M$12))) -> A JOUR | N23: =IF(L23>0,SUM($Z23:$AR23)*$J23,0) -> 0 | O23: =+IF(L23>0,L23*J23,0) -> 0 | P23: =IF(L23>=0,"A JOUR",($L23*($M$12+J23)+O23)) -> A JOUR | Q23: x | R23: x | U23: A JOUR
B24: 11 | C24: =CONCATENATE("N°-","00",B24,"-2024") -> N°-0011-2024 | D24: 775779980 | E24: Mr | F24: Abdoul salam PP (ivoire) | G24: Dowsaré | H24: Dakar | I24: 77 577 99 80 | J24: 1000 | K24: 1000 | L24: =+SUM($Z24:$AR24) -> -4 | M24: =IF(L24>=0,"A JOUR",($L24*($M$12))) -> -8000 | N24: =IF(L24>0,SUM($Z24:$AR24)*$J24,0) -> 0 | P24: =IF(L24>=0,"A JOUR",($L24*($M$12+J24)+O24)) -> -12000 | Q24: x | R24: x | U24: #N/A | V24: #N/A | W24: #N/A | X24: 1000 | Y24: 2 | Z24: -4
B25: 12 | C25: =CONCATENATE("N°-","00",B25,"-2024") -> N°-0012-2024 | E25: Mr | F25: Abdoulaye | G25: Daandé Mboully | H25: Guinée | K25: 1000 | L25: VG | M25: =IF(L25>=0,"A JOUR",($L25*($M$12))) -> A JOUR | N25: =IF(L25>0,SUM($Z25:$AR25)*$J25,0) -> 0 | P25: =IF(L25>=0,"A JOUR",($L25*($M$12+J25)+O25)) -> A JOUR | Q25: x | S25: VG | U25: #N/A | V25: #N/A | W25: #N/A | X25: #N/A | Y25: #N/A | Z25: VG
B26: 13 | C26: =CONCATENATE("N°-","00",B26,"-2024") -> N°-0013-2024 | D26: xxxxxxxx | E26: Mr | F26: Abdoulaye | G26: Kourawoye | H26: Côte d'ivoire | I26: xxxxxxxx | J26: 1000 | K26: N/A | M26: =IF(L26>=0,"A JOUR",($L26*($M$12))) -> A JOUR | N26: =IF(L26>0,SUM($Z26:$AR26)*$J26,0) -> 0 | P26: =IF(L26>=0,"A JOUR",($L26*($M$12+J26)+O26)) -> A JOUR | Q26: x | U26: #N/A | V26: #N/A | W26: #N/A | X26: #N/A | Y26: #N/A
B27: 14 | C27: =CONCATENATE("N°-","00",B27,"-2024") -> N°-0014-2024 | D27: 781413617 | E27: Grand | F27: Abdoulaye (Laye) | G27: Biilaa | H27: Guinée | I27: 78 141 36 17 | J27: 1000 | K27: 1000 | L27: 0 | M27: =IF(L27>=0,"A JOUR",($L27*($M$12))) -> A JOUR | N27: =IF(L27>0,SUM($Z27:$AR27)*$J27,0) -> 0 | O27: =+IF(L27>0,L27*J27,0) -> 0 | P27: =IF(L27>=0,"A JOUR",($L27*($M$12+J27)+O27)) -> A JOUR | Q27: x | R27: x | U27: #N/A | V27: GUINEE | Z27: VG
B28: 15 | C28: =CONCATENATE("N°-","00",B28,"-2024") -> N°-0015-2024 | D28: +24106399421 | E28: Grand | F28: Abdoulaye (Laye) gabonais | G28: Pétel | H28: Dakar | I28: +241 06 39 94 21 | J28: 2000 | K28: N/A | L28: =+SUM($Z28:$AR28) -> -6 | M28: =IF(L28>=0,"A JOUR",($L28*($M$12))) -> -12000 | N28: =IF(L28>0,SUM($Z28:$AR28)*$J28,0) -> 0 | P28: =IF(L28>=0,"A JOUR",($L28*($M$12+J28)+O28)) -> -24000 | R28: x | U28: #N/A | V28: #N/A | W28: #N/A | X28: 2000 | Y28: 4 | Z28: -6
B29: 16 | C29: =CONCATENATE("N°-","00",B29,"-2024") -> N°-0016-2024 | D29: 777255426 | E29: Mr | F29: Abdoulaye djibril KZA ibnou samara | G29: Dowsaré | H29: Casamance | I29: 77 725 54 26 | J29: 1500 | K29: N/A | L29: 11 | M29: =IF(L29>=0,"A JOUR",($L29*($M$12))) -> A JOUR | N29: =IF(L29>0,SUM($Z29:$AR29)*$J29,0) -> 16500 | O29: =+IF(L29>0,L29*J29,0) -> 16500 | P29: =IF(L29>=0,"A JOUR",($L29*($M$12+J29)+O29)) -> A JOUR | Q29: x | R29: x | S29: =+IF(L29>0,L29*J29,0) -> 16500 | U29: A JOUR | Z29: 1 | AA29: 1 | AB29: 1 | AC29: 1 | AD29: 1 | AE29: 1 | AF29: 1 | AG29: 1 | AH29: 1 | AI29: 1 | AJ29: 1
B30: 17 | C30: =CONCATENATE("N°-","00",B30,"-2024") -> N°-0017-2024 | E30: Mr | F30: Abdoulaye ka gallé | G30: Biilaa | H30: Guinée | K30: N/A | L30: VG | M30: =IF(L30>=0,"A JOUR",($L30*($M$12))) -> A JOUR | N30: =IF(L30>0,SUM($Z30:$AR30)*$J30,0) -> 0 | P30: =IF(L30>=0,"A JOUR",($L30*($M$12+J30)+O30)) -> A JOUR | S30: VG | U30: #N/A | V30: #N/A | W30: #N/A | X30: #N/A | Y30: #N/A | Z30: VG
B31: 18 | C31: =CONCATENATE("N°-","00",B31,"-2024") -> N°-0018-2024 | D31: 774042497 | E31: Mr | F31: Abdourahmane TRS | G31: Mamasamba | H31: Dakar | I31: 77 404 24 97 | J31: 5000 | K31: 1000 | L31: 0 | M31: =IF(L31>=0,"A JOUR",($L31*($M$12))) -> A JOUR | N31: =IF(L31>0,SUM($Z31:$AR31)*$J31,0) -> 0 | O31: =+IF(L31>0,L31*J31,0) -> 0 | P31: =IF(L31>=0,"A JOUR",($L31*($M$12+J31)+O31)) -> A JOUR | Q31: x | R31: x | U31: #N/A | V31: #N/A | W31: #N/A | X31: #N/A | Y31: #N/A | Z31: 1 | AA31: 1 | AB31: 1 | AC31: 1 | AD31: 1 | AE31: 1 | AF31: 1 | AG31: 1 | AH31: 1 | AI31: 1 | AJ31: 1
B32: 19 | C32: =CONCATENATE("N°-","00",B32,"-2024") -> N°-0019-2024 | D32: 774473167 | E32: Koto | F32: Ablaye TSA | G32: Bolorrou | H32: Dakar | I32: 77 447 31 67 | J32: 1500 | K32: 1000 | L32: 0 | M32: =IF(L32>=0,"A JOUR",($L32*($M$12))) -> A JOUR | N32: =IF(L32>0,SUM($Z32:$AR32)*$J32,0) -> 0 | O32: =+IF(L32>0,L32*J32,0) -> 0 | P32: =IF(L32>=0,"A JOUR",($L32*($M$12+J32)+O32)) -> A JOUR | Q32: x | R32: x | U32: A JOUR | Z32: 1
B33: 20 | C33: =CONCATENATE("N°-","00",B33,"-2024") -> N°-0020-2024 | D33: 777119328 | E33: Kaou | F33: Ahmadou Korka ibn bappa bala | G33: Pétel | H33: Dakar | I33: 777119328 | J33: 1000 | K33: 1000 | L33: =+SUM($Z33:$AR33) -> -6 | M33: =IF(L33>=0,"A JOUR",($L33*($M$12))) -> -12000 | N33: =IF(L33>0,SUM($Z33:$AR33)*$J33,0) -> 0 | O33: =+IF(L33>0,L33*J33,0) -> 0 | P33: =IF(L33>=0,"A JOUR",($L33*($M$12+J33)+O33)) -> -18000 | U33: #N/A | V33: #N/A | W33: #N/A | X33: 1000 | Y33: 3 | Z33: -6
B34: 21 | C34: =CONCATENATE("N°-","00",B34,"-2024") -> N°-0021-2024 | D34: 783520425 | E34: Mr | F34: Alassana ibn Elhadji M. Woury | G34: Pétel | H34: Dakar | I34: 78 352 04 25 | J34: 1000 | K34: 1000 | L34: 0 | M34: =IF(L34>=0,"A JOUR",($L34*($M$12))) -> A JOUR | N34: =IF(L34>0,SUM($Z34:$AR34)*$J34,0) -> 0 | O34: =+IF(L34>0,L34*J34,0) -> 0 | P34: =IF(L34>=0,"A JOUR",($L34*($M$12+J34)+O34)) -> A JOUR | R34: x | S34: NT | U34: #N/A | V34: #N/A | W34: NT | Z34: NT
B35: 22 | C35: =CONCATENATE("N°-","00",B35,"-2024") -> N°-0022-2024 | D35: 767652193 | E35: Mr | F35: Alassana Macoss | G35: Dowsaré | H35: Dakar | I35: 76 765 21 93 | J35: 1000 | K35: 1000 | L35: 0 | M35: =IF(L35>=0,"A JOUR",($L35*($M$12))) -> A JOUR | N35: =IF(L35>0,SUM($Z35:$AR35)*$J35,0) -> 0 | O35: =+IF(L35>0,L35*J35,0) -> 0 | P35: =IF(L35>=0,"A JOUR",($L35*($M$12+J35)+O35)) -> A JOUR | Q35: x | R35: x | S35: NT | U35: #N/A | V35: #N/A | W35: NT | Z35: NT
B36: 23 | C36: =CONCATENATE("N°-","00",B36,"-2024") -> N°-0023-2024 | D36: 783520425 | E36: Mr | F36: Alousseynou ibn Elhadji M. Woury | G36: Pétel | H36: Dakar | I36: 78 352 04 25 | J36: 1000 | K36: 1000 | L36: 0 | M36: =IF(L36>=0,"A JOUR",($L36*($M$12))) -> A JOUR | N36: =IF(L36>0,SUM($Z36:$AR36)*$J36,0) -> 0 | O36: =+IF(L36>0,L36*J36,0) -> 0 | P36: =IF(L36>=0,"A JOUR",($L36*($M$12+J36)+O36)) -> A JOUR | R36: x | S36: NT | U36: #N/A | V36: #N/A | W36: NT | Z36: NT
B37: 24 | C37: =CONCATENATE("N°-","00",B37,"-2024") -> N°-0024-2024 | E37: Mr | F37: Alousseynou Pecosse | G37: Dowsaré | H37: Guinée | K37: N/A | L37: VG | M37: =IF(L37>=0,"A JOUR",($L37*($M$12))) -> A JOUR | N37: =IF(L37>0,SUM($Z37:$AR37)*$J37,0) -> 0 | P37: =IF(L37>=0,"A JOUR",($L37*($M$12+J37)+O37)) -> A JOUR | Q37: x | S37: VG | U37: #N/A | V37: #N/A | W37: #N/A | X37: #N/A | Y37: #N/A | Z37: VG
B38: 25 | C38: =CONCATENATE("N°-","00",B38,"-2024") -> N°-0025-2024 | E38: Mr | F38: Alpha (France) | G38: Dieydiyabhe | H38: France | K38: 1000 | M38: =IF(L38>=0,"A JOUR",($L38*($M$12))) -> A JOUR | N38: =IF(L38>0,SUM($Z38:$AR38)*$J38,0) -> 0 | O38: =+IF(L38>0,L38*J38,0) -> 0 | P38: =IF(L38>=0,"A JOUR",($L38*($M$12+J38)+O38)) -> A JOUR | U38: #N/A | V38: #N/A | W38: #N/A | X38: #N/A | Y38: #N/A
B39: 26 | C39: =CONCATENATE("N°-","00",B39,"-2024") -> N°-0026-2024 | D39: 772289487 | E39: Mr | F39: Alpha amadou ibn bappa bala | G39: Pétel | H39: Dakar | I39: 77 228 94 87 | J39: 1000 | K39: 1000 | L39: 0 | M39: =IF(L39>=0,"A JOUR",($L39*($M$12))) -> A JOUR | N39: =IF(L39>0,SUM($Z39:$AR39)*$J39,0) -> 0 | O39: =+IF(L39>0,L39*J39,0) -> 0 | P39: =IF(L39>=0,"A JOUR",($L39*($M$12+J39)+O39)) -> A JOUR | Q39: x | R39: x | U39: A JOUR | Z39: 1 | AA39: 1 | AB39: 1 | AC39: 1 | AD39: 1 | AE39: 1 | AF39: 1 | AG39: 1 | AH39: 1 | AI39: 1 | AJ39: 1
B40: 27 | C40: =CONCATENATE("N°-","00",B40,"-2024") -> N°-0027-2024 | D40: 781261182 | E40: Mr | F40: Alpha Amirou ibn Elhadji Ibrahima | G40: Pétel | H40: Dakar | I40: 78 126 11 82 | J40: 1000 | K40: 1000 | L40: =+SUM($Z40:$AR40) -> -6 | M40: =IF(L40>=0,"A JOUR",($L40*($M$12))) -> -12000 | N40: =IF(L40>0,SUM($Z40:$AR40)*$J40,0) -> 0 | O40: =+IF(L40>0,L40*J40,0) -> 0 | P40: =IF(L40>=0,"A JOUR",($L40*($M$12+J40)+O40)) -> -18000 | R40: x | S40: NT | U40: #N/A | V40: #N/A | W40: #N/A | X40: 1000 | Y40: 6 | Z40: -6
B41: 28 | C41: =CONCATENATE("N°-","00",B41,"-2024") -> N°-0028-2024 | D41: 772202046 | E41: Koto | F41: alpha KZA ibnou samara | G41: Dowsaré | H41: Casamance | I41: 77 220 20 46 | J41: 2000 | K41: 1000 | L41: 11 | M41: =IF(L41>=0,"A JOUR",($L41*($M$12))) -> A JOUR | N41: =IF(L41>0,SUM($Z41:$AR41)*$J41,0) -> 2000 | O41: =+IF(L41>0,L41*J41,0) -> 22000 | P41: =IF(L41>=0,"A JOUR",($L41*($M$12+J41)+O41)) -> A JOUR | Q41: x | R41: x | U41: A JOUR | Z41: 1
B42: 29 | C42: =CONCATENATE("N°-","00",B42,"-2024") -> N°-0029-2024 | D42: 781346347 | E42: Bappa | F42: Alpha oumar | G42: Mamasamba | H42: Dakar | I42: 78 134 63 47 | J42: 2000 | K42: 1000 | L42: =4-4 -> 0 | M42: =IF(L42>=0,"A JOUR",($L42*($M$12))) -> A JOUR | N42: =IF(L42>0,SUM($Z42:$AR42)*$J42,0) -> 0 | O42: =+IF(L42>0,L42*J42,0) -> 0 | P42: =IF(L42>=0,"A JOUR",($L42*($M$12+J42)+O42)) -> A JOUR | Q42: x | R42: x | U42: A JOUR | Z42: 1
B43: 30 | C43: =CONCATENATE("N°-","00",B43,"-2024") -> N°-0030-2024 | D43: xxxxxxxx | E43: Koto | F43: Alpha oumar gabonais | G43: Dowsaré | H43: Togo | I43: xxxxxxxx | J43: 4000 | K43: 1000 | M43: =IF(L43>=0,"A JOUR",($L43*($M$12))) -> A JOUR | N43: =IF(L43>0,SUM($Z43:$AR43)*$J43,0) -> 0 | P43: =IF(L43>=0,"A JOUR",($L43*($M$12+J43)+O43)) -> A JOUR | Q43: x | R43: x | U43: #N/A | V43: #N/A | W43: #N/A | X43: #N/A | Y43: #N/A
B44: 31 | C44: =CONCATENATE("N°-","00",B44,"-2024") -> N°-0031-2024 | D44: +24102253222 | E44: Koto | F44: Alpha oumar ibn karamoko Daouda | G44: Pétel | H44: Gabon | I44: +241 02 25 32 22 | J44: 5000 | K44: N/A | M44: =IF(L44>=0,"A JOUR",($L44*($M$12))) -> A JOUR | N44: =IF(L44>0,SUM($Z44:$AR44)*$J44,0) -> 0 | P44: =IF(L44>=0,"A JOUR",($L44*($M$12+J44)+O44)) -> A JOUR | R44: x | U44: #N/A | V44: #N/A | W44: #N/A | X44: #N/A | Y44: #N/A
B45: 32 | C45: =CONCATENATE("N°-","00",B45,"-2024") -> N°-0032-2024 | D45: 774997775 | E45: Koto | F45: Alpha Oumar togolais | G45: Dowsaré | H45: Dakar | I45: 77 499 77 75 | J45: 2000 | K45: 1000 | L45: 2 | M45: =IF(L45>=0,"A JOUR",($L45*($M$12))) -> A JOUR | N45: =IF(L45>0,SUM($Z45:$AR45)*$J45,0) -> 2000 | O45: =+IF(L45>0,L45*J45,0) -> 4000 | P45: =IF(L45>=0,"A JOUR",($L45*($M$12+J45)+O45)) -> A JOUR | Q45: x | R45: x | U45: A JOUR | Z45: 1
B46: 33 | C46: =CONCATENATE("N°-","00",B46,"-2024") -> N°-0033-2024 | E46: Mr | F46: Alpha Saliou ibn Elhadji M. Woury | G46: Pétel | H46: Guinée | K46: 1000 | L46: VG | M46: =IF(L46>=0,"A JOUR",($L46*($M$12))) -> A JOUR | N46: =IF(L46>0,SUM($Z46:$AR46)*$J46,0) -> 0 | P46: =IF(L46>=0,"A JOUR",($L46*($M$12+J46)+O46)) -> A JOUR | S46: VG | U46: #N/A | V46: #N/A | W46: #N/A | X46: #N/A | Y46: #N/A | Z46: VG
B47: 34 | C47: =CONCATENATE("N°-","00",B47,"-2024") -> N°-0034-2024 | D47: 776709584 | E47: Oustaz | F47: Amadou | G47: Bowell | H47: Guinée | I47: 77 670 95 84 | J47: 2500 | K47: 1000 | L47: 0 | M47: =IF(L47>=0,"A JOUR",($L47*($M$12))) -> A JOUR | N47: =IF(L47>0,SUM($Z47:$AR47)*$J47,0) -> 0 | O47: =+IF(L47>0,L47*J47,0) -> 0 | P47: =IF(L47>=0,"A JOUR",($L47*($M$12+J47)+O47)) -> A JOUR | Q47: x | R47: x | S47: NT | U47: #N/A | V47: GUINEE | Z47: VG
B48: 35 | C48: =CONCATENATE("N°-","00",B48,"-2024") -> N°-0035-2024 | D48: 776623868 | E48: Mr | F48: Amadou bobo (mariste) | G48: Dowsaré | H48: Dakar | I48: 77 662 38 68 | J48: 2000 | K48: 1000 | L48: 0 | M48: =IF(L48>=0,"A JOUR",($L48*($M$12))) -> A JOUR | N48: =IF(L48>0,SUM($Z48:$AR48)*$J48,0) -> 0 | O48: =+IF(L48>0,L48*J48,0) -> 0 | P48: =IF(L48>=0,"A JOUR",($L48*($M$12+J48)+O48)) -> A JOUR | Q48: x | R48: x | U48: A JOUR | Z48: 1 | AA48: 1 | AB48: 1 | AC48: 1 | AD48: 1 | AE48: 1 | AF48: 1 | AG48: 1 | AH48: 1 | AI48: 1 | AJ48: 1
B49: 36 | C49: =CONCATENATE("N°-","00",B49,"-2024") -> N°-0036-2024 | D49: 774272026 | E49: Koto | F49: Amadou bobo N°1 | G49: Dowsaré | H49: Dakar | I49: 77 427 20 26 | J49: 2000 | K49: 1000 | L49: 0 | M49: =IF(L49>=0,"A JOUR",($L49*($M$12))) -> A JOUR | N49: =IF(L49>0,SUM($Z49:$AR49)*$J49,0) -> 0 | O49: =+IF(L49>0,L49*J49,0) -> 0 | P49: =IF(L49>=0,"A JOUR",($L49*($M$12+J49)+O49)) -> A JOUR | Q49: x | R49: x | U49: #N/A | V49: #N/A | W49: #N/A | X49: 2000 | Y49: 4 | Z49: 1
B50: 37 | C50: =CONCATENATE("N°-","00",B50,"-2024") -> N°-0037-2024 | D50: xxxxxxxx | E50: Mr | F50: Amadou diogo | G50: Gobihi | H50: Guinée | I50: xxxxxxxx | J50: 2000 | K50: 1000 | M50: =IF(L50>=0,"A JOUR",($L50*($M$12))) -> A JOUR | N50: =IF(L50>0,SUM($Z50:$AR50)*$J50,0) -> 0 | P50: =IF(L50>=0,"A JOUR",($L50*($M$12+J50)+O50)) -> A JOUR | R50: x | S50: VG | U50: #N/A | V50: #N/A | W50: #N/A | X50: #N/A | Y50: #N/A
B51: 38 | C51: =CONCATENATE("N°-","00",B51,"-2024") -> N°-0038-2024 | D51: 775218573 | E51: Mr | F51: Amadou Djoulde - PR | G51: Dowsaré | H51: Dakar | I51: 77 521 85 73 | J51: 3000 | K51: 1000 | L51: 0 | M51: =IF(L51>=0,"A JOUR",($L51*($M$12))) -> A JOUR | N51: =IF(L51>0,SUM($Z51:$AR51)*$J51,0) -> 0 | O51: =+IF(L51>0,L51*J51,0) -> 0 | P51: =IF(L51>=0,"A JOUR",($L51*($M$12+J51)+O51)) -> A JOUR | Q51: x | R51: x | U51: A JOUR | Z51: 1 | AA51: 1 | AB51: 1 | AC51: 1 | AD51: 1 | AE51: 1 | AF51: 1 | AG51: 1 | AH51: 1 | AI51: 1 | AJ51: 1
B52: 39 | C52: =CONCATENATE("N°-","00",B52,"-2024") -> N°-0039-2024 | D52: 778550234 | E52: Koto | F52: Amadou korka CC | G52: Diabbhéhi | H52: Dakar | I52: 77 855 02 34 | J52: 2000 | K52: 1000 | L52: 0 | M52: =IF(L52>=0,"A JOUR",($L52*($M$12))) -> A JOUR | N52: =IF(L52>0,SUM($Z52:$AR52)*$J52,0) -> 0 | O52: =+IF(L52>0,L52*J52,0) -> 0 | P52: =IF(L52>=0,"A JOUR",($L52*($M$12+J52)+O52)) -> A JOUR | Q52: x | R52: x | U52: A JOUR | Z52: 1
B53: 40 | C53: =CONCATENATE("N°-","00",B53,"-2024") -> N°-0040-2024 | D53: 778151869 | E53: Koto | F53: Amadou korka | G53: Biilaa | H53: Dakar | I53: 77 815 18 69 | J53: 1000 | K53: 1000 | L53: 0 | M53: =IF(L53>=0,"A JOUR",($L53*($M$12))) -> A JOUR | N53: =IF(L53>0,SUM($Z53:$AR53)*$J53,0) -> 0 | O53: =+IF(L53>0,L53*J53,0) -> 0 | P53: =IF(L53>=0,"A JOUR",($L53*($M$12+J53)+O53)) -> A JOUR | Q53: x | R53: x | U53: A JOUR | Z53: 1
B54: 41 | C54: =CONCATENATE("N°-","00",B54,"-2024") -> N°-0041-2024 | D54: 786333092 | E54: Mr | F54: Amadou korka | G54: Porétély | H54: Dakar | I54: 78 633 30 92 | J54: 1000 | K54: N/A | L54: =+SUM($Z54:$AR54) -> -23 | M54: =IF(L54>=0,"A JOUR",($L54*($M$12))) -> -46000 | N54: =IF(L54>0,SUM($Z54:$AR54)*$J54,0) -> 0 | P54: =IF(L54>=0,"A JOUR",($L54*($M$12+J54)+O54)) -> -69000 | Q54: x | R54: x | T54: Avance 8000 | U54: #N/A | V54: #N/A | W54: #N/A | X54: 1000 | Y54: 21 | Z54: -23
B55: 42 | C55: =CONCATENATE("N°-","00",B55,"-2024") -> N°-0042-2024 | D55: 778021767 | E55: Mr | F55: Amadou mouctar | G55: Yayemadou | H55: Dakar | I55: 77 802 17 67 | J55: 2000 | K55: N/A | L55: =+SUM($Z55:$AR55) -> -47 | M55: =IF(L55>=0,"A JOUR",($L55*($M$12))) -> -94000 | N55: =IF(L55>0,SUM($Z55:$AR55)*$J55,0) -> 0 | P55: =IF(L55>=0,"A JOUR",($L55*($M$12+J55)+O55)) -> -188000 | Q55: x | R55: x | U55: #N/A | V55: #N/A | W55: #N/A | X55: 2000 | Y55: 45 | Z55: -47
B56: 43 | C56: =CONCATENATE("N°-","00",B56,"-2024") -> N°-0043-2024 | D56: 771009642 | E56: Mr | F56: Amadou mouctar ibn Elhadji Ibrahima | G56: Pétel | H56: Dakar | I56: 77 100 96 42 | J56: 1000 | K56: N/A | L56: =+SUM($Z56:$AR56) -> -47 | M56: =IF(L56>=0,"A JOUR",($L56*($M$12))) -> -94000 | N56: =IF(L56>0,SUM($Z56:$AR56)*$J56,0) -> 0 | P56: =IF(L56>=0,"A JOUR",($L56*($M$12+J56)+O56)) -> -141000 | R56: x | U56: #N/A | V56: #N/A | W56: #N/A | X56: 1000 | Y56: 45 | Z56: -47
B57: 44 | C57: =CONCATENATE("N°-","00",B57,"-2024") -> N°-0044-2024 | D57: 778637835 | E57: Mr | F57: Amadou tanou | G57: Dieydiyabhe | H57: Dakar | I57: 77 863 78 35 | J57: 1000 | K57: 1000 | L57: 0 | M57: =IF(L57>=0,"A JOUR",($L57*($M$12))) -> A JOUR | N57: =IF(L57>0,SUM($Z57:$AR57)*$J57,0) -> 0 | O57: =+IF(L57>0,L57*J57,0) -> 0 | P57: =IF(L57>=0,"A JOUR",($L57*($M$12+J57)+O57)) -> A JOUR | Q57: x | R57: x | S57: NT | U57: #N/A | V57: #N/A | W57: NT | Z57: 1 | AA57: 1 | AB57: 1 | AC57: 1
B58: 45 | C58: =CONCATENATE("N°-","00",B58,"-2024") -> N°-0045-2024 | D58: 773499877 | E58: Mody | F58: Amadou TC | G58: Mamasamba | H58: Dakar | I58: 77 349 98 77 | J58: 2000 | K58: 1000 | L58: 0 | M58: =IF(L58>=0,"A JOUR",($L58*($M$12))) -> A JOUR | N58: =IF(L58>0,SUM($Z58:$AR58)*$J58,0) -> 0 | O58: =+IF(L58>0,L58*J58,0) -> 0 | P58: =IF(L58>=0,"A JOUR",($L58*($M$12+J58)+O58)) -> A JOUR | Q58: x | R58: x | U58: #N/A | V58: GUINEE | Z58: VG
B59: 46 | C59: =CONCATENATE("N°-","00",B59,"-2024") -> N°-0046-2024 | D59: xxxxxxxx | E59: Mr | F59: Amadou Woury | G59: Ka missidé | H59: Côte d'ivoire | I59: xxxxxxxx | J59: 2000 | K59: 1000 | L59: 0 | M59: =IF(L59>=0,"A JOUR",($L59*($M$12))) -> A JOUR | N59: =IF(L59>0,SUM($Z59:$AR59)*$J59,0) -> 0 | O59: =+IF(L59>0,L59*J59,0) -> 0 | P59: =IF(L59>=0,"A JOUR",($L59*($M$12+J59)+O59)) -> A JOUR | R59: x | U59: #N/A | V59: #N/A | W59: #N/A | X59: #N/A | Y59: #N/A
B60: 47 | C60: =CONCATENATE("N°-","00",B60,"-2024") -> N°-0047-2024 | D60: 772392440 | E60: Mr | F60: Amadou Woury boukary | G60: Yayemadou | H60: Dakar | I60: 77 239 24 40 | J60: 2000 | K60: N/A | L60: =+SUM($Z60:$AR60) -> -42 | M60: =IF(L60>=0,"A JOUR",($L60*($M$12))) -> -84000 | N60: =IF(L60>0,SUM($Z60:$AR60)*$J60,0) -> 0 | P60: =IF(L60>=0,"A JOUR",($L60*($M$12+J60)+O60)) -> -168000 | R60: x | U60: #N/A | V60: #N/A | W60: #N/A | X60: 2000 | Y60: 40 | Z60: -42
B61: 48 | C61: =CONCATENATE("N°-","00",B61,"-2024") -> N°-0048-2024 | D61: 779593845 | E61: Mr | F61: Boubacar | G61: Biilaa | H61: Dakar | I61: 77 959 38 45 | J61: 1000 | K61: N/A | L61: =+SUM($Z61:$AR61) -> -6 | M61: =IF(L61>=0,"A JOUR",($L61*($M$12))) -> -12000 | N61: =IF(L61>0,SUM($Z61:$AR61)*$J61,0) -> 0 | P61: =IF(L61>=0,"A JOUR",($L61*($M$12+J61)+O61)) -> -18000 | Q61: x | R61: x | U61: #N/A | V61: #N/A | W61: #N/A | X61: 1000 | Y61: 5 | Z61: -6 | AA61: NT
B62: 49 | C62: =CONCATENATE("N°-","00",B62,"-2024") -> N°-0049-2024 | D62: 778018331 | E62: Mr | F62: Boubacar (mariste ) | G62: Kourawoye | H62: Dakar | I62: 77 801 83 31 | J62: 2000 | K62: 1000 | L62: 0 | M62: =IF(L62>=0,"A JOUR",($L62*($M$12))) -> A JOUR | N62: =IF(L62>0,SUM($Z62:$AR62)*$J62,0) -> 0 | O62: =+IF(L62>0,L62*J62,0) -> 0 | P62: =IF(L62>=0,"A JOUR",($L62*($M$12+J62)+O62)) -> A JOUR | Q62: x | R62: x | U62: #N/A | V62: #N/A | W62: #N/A | X62: #N/A | Y62: #N/A
B63: 50 | C63: =CONCATENATE("N°-","00",B63,"-2024") -> N°-0050-2024 | D63: 774494968 | E63: Mr | F63: Boubacar ibn bappa bala CC | G63: Pétel | H63: Dakar | I63: 77 449 49 68 | J63: 3000 | K63: 1000 | L63: 0 | M63: =IF(L63>=0,"A JOUR",($L63*($M$12))) -> A JOUR | N63: =IF(L63>0,SUM($Z63:$AR63)*$J63,0) -> 0 | O63: =+IF(L63>0,L63*J63,0) -> 0 | P63: =IF(L63>=0,"A JOUR",($L63*($M$12+J63)+O63)) -> A JOUR | Q63: x | R63: x | U63: A JOUR | Z63: 1
B64: 51 | C64: =CONCATENATE("N°-","00",B64,"-2024") -> N°-0051-2024 | D64: 779862991 | E64: Koto | F64: Boubacar ibn Elhadji Ibrahima | G64: Pétel | H64: Dakar | I64: 77 986 29 91 | J64: 2000 | K64: N/A | L64: 0 | M64: =IF(L64>=0,"A JOUR",($L64*($M$12))) -> A JOUR | N64: =IF(L64>0,SUM($Z64:$AR64)*$J64,0) -> 0 | O64: =+IF(L64>0,L64*J64,0) -> 0 | P64: =IF(L64>=0,"A JOUR",($L64*($M$12+J64)+O64)) -> A JOUR | R64: x | U64: A JOUR | Z64: 1
B65: 52 | C65: =CONCATENATE("N°-","00",B65,"-2024") -> N°-0052-2024 | D65: 776779519 | E65: Mr | F65: Boubacar Kowloun | G65: Kowloune | H65: Dakar | I65: 77 677 95 19 | J65: 1000 | K65: 1000 | L65: 0 | M65: =IF(L65>=0,"A JOUR",($L65*($M$12))) -> A JOUR | N65: =IF(L65>0,SUM($Z65:$AR65)*$J65,0) -> 0 | O65: =+IF(L65>0,L65*J65,0) -> 0 | P65: =IF(L65>=0,"A JOUR",($L65*($M$12+J65)+O65)) -> A JOUR | U65: A JOUR | Z65: 1
B66: 53 | C66: =CONCATENATE("N°-","00",B66,"-2024") -> N°-0053-2024 | D66: 773137431 | E66: Koto | F66: Boubacar méékohi | G66: Dowsaré | H66: Dakar | I66: 77 313 74 31 | J66: 2000 | K66: 1000 | L66: 0 | M66: =IF(L66>=0,"A JOUR",($L66*($M$12))) -> A JOUR | N66: =IF(L66>0,SUM($Z66:$AR66)*$J66,0) -> 0 | O66: =+IF(L66>0,L66*J66,0) -> 0 | P66: =IF(L66>=0,"A JOUR",($L66*($M$12+J66)+O66)) -> A JOUR | Q66: x | R66: x | S66: NT | U66: #N/A | V66: #N/A | W66: #N/A | X66: 2000 | Y66: 2 | Z66: 1
B67: 54 | C67: =CONCATENATE("N°-","00",B67,"-2024") -> N°-0054-2024 | E67: Mr | F67: Boubacar Ngarahi | G67: Dowsaré | H67: Dakar | J67: 1000 | K67: 1000 | M67: =IF(L67>=0,"A JOUR",($L67*($M$12))) -> A JOUR | N67: =IF(L67>0,SUM($Z67:$AR67)*$J67,0) -> 0 | P67: =IF(L67>=0,"A JOUR",($L67*($M$12+J67)+O67)) -> A JOUR | U67: #N/A | V67: #N/A | W67: #N/A | X67: #N/A | Y67: #N/A
B68: 55 | C68: =CONCATENATE("N°-","00",B68,"-2024") -> N°-0055-2024 | D68: 776669090 | E68: Mr | F68: Bourhane | G68: Pétel | H68: Dakar | I68: 77 666 90 90 | J68: 1000 | K68: 1000 | L68: =+SUM($Z68:$AR68) -> 0 | M68: =IF(L68>=0,"A JOUR",($L68*($M$12))) -> A JOUR | N68: =IF(L68>0,SUM($Z68:$AR68)*$J68,0) -> 0 | O68: =+IF(L68>0,L68*J68,0) -> 0 | P68: =IF(L68>=0,"A JOUR",($L68*($M$12+J68)+O68)) -> A JOUR | Q68: x | R68: x | U68: #N/A | V68: #N/A | W68: #N/A | X68: 1000 | Y68: 8
B69: 56 | C69: =CONCATENATE("N°-","00",B69,"-2024") -> N°-0056-2024 | E69: Mr | F69: Cheikh ibn Elhadji Aliou | G69: Kourawoye | H69: Dakar | J69: N/A | K69: N/A | M69: =IF(L69>=0,"A JOUR",($L69*($M$12))) -> A JOUR | N69: =IF(L69>0,SUM($Z69:$AR69)*$J69,0) -> 0 | P69: =IF(L69>=0,"A JOUR",($L69*($M$12+J69)+O69)) -> A JOUR | Q69: x | R69: x | S69: NT | U69: #N/A | V69: #N/A | W69: #N/A | X69: #N/A | Y69: #N/A
B70: 57 | C70: =CONCATENATE("N°-","00",B70,"-2024") -> N°-0057-2024 | D70: 774885353 | E70: Mr | F70: Cheikh tidiane ibn Elhadji Ibrahima | G70: Pétel | H70: Dakar | I70: 77 488 53 53 | J70: 1000 | K70: 1000 | L70: =+SUM($Z70:$AR70) -> -1 | M70: =IF(L70>=0,"A JOUR",($L70*($M$12))) -> -2000 | N70: =IF(L70>0,SUM($Z70:$AR70)*$J70,0) -> 0 | P70: =IF(L70>=0,"A JOUR",($L70*($M$12+J70)+O70)) -> -3000 | Q70: x | R70: x | U70: #N/A | V70: #N/A | W70: #N/A | X70: 1000 | Y70: 4 | Z70: -1
B71: 58 | C71: =CONCATENATE("N°-","00",B71,"-2024") -> N°-0058-2024 | E71: Mr | F71: Daouda | G71: Dowsaré | H71: Casamance | J71: N/A | K71: N/A | M71: =IF(L71>=0,"A JOUR",($L71*($M$12))) -> A JOUR | N71: =IF(L71>0,SUM($Z71:$AR71)*$J71,0) -> 0 | P71: =IF(L71>=0,"A JOUR",($L71*($M$12+J71)+O71)) -> A JOUR | R71: x | U71: #N/A | V71: #N/A | W71: #N/A | X71: #N/A | Y71: #N/A
B72: 59 | C72: =CONCATENATE("N°-","00",B72,"-2024") -> N°-0059-2024 | D72: 774767085 | E72: Mr | F72: Daouda (Parcelles) | G72: Kourawoye | H72: Dakar | I72: 77 476 70 85 | J72: 1000 | K72: 1000 | L72: 0 | M72: =IF(L72>=0,"A JOUR",($L72*($M$12))) -> A JOUR | N72: =IF(L72>0,SUM($Z72:$AR72)*$J72,0) -> 0 | O72: =+IF(L72>0,L72*J72,0) -> 0 | P72: =IF(L72>=0,"A JOUR",($L72*($M$12+J72)+O72)) -> A JOUR | Q72: x | R72: x | U72: A JOUR | Z72: 1
B73: 60 | C73: =CONCATENATE("N°-","00",B73,"-2024") -> N°-0060-2024 | E73: Mr | F73: Daouda ibn Elhadji M. Woury | G73: Pétel | H73: Guinée | J73: N/A | K73: 1000 | L73: VG | M73: =IF(L73>=0,"A JOUR",($L73*($M$12))) -> A JOUR | N73: =IF(L73>0,SUM($Z73:$AR73)*$J73,0) -> #VALUE! | P73: =IF(L73>=0,"A JOUR",($L73*($M$12+J73)+O73)) -> A JOUR | Q73: x | S73: VG | U73: #N/A | V73: #N/A | W73: #N/A | X73: #N/A | Y73: #N/A | Z73: VG
B74: 61 | C74: =CONCATENATE("N°-","00",B74,"-2024") -> N°-0061-2024 | D74: 776790248 | E74: Mr | F74: Elh ibrahima N°2 ibn karamoko Daouda DC | G74: Pétel | H74: Dakar | I74: 77 679 02 48 | J74: 2000 | K74: 1000 | L74: 0 | M74: =IF(L74>=0,"A JOUR",($L74*($M$12))) -> A JOUR | N74: =IF(L74>0,SUM($Z74:$AR74)*$J74,0) -> 0 | O74: =+IF(L74>0,L74*J74,0) -> 0 | P74: =IF(L74>=0,"A JOUR",($L74*($M$12+J74)+O74)) -> A JOUR | Q74: x | R74: x | U74: A JOUR | Z74: 1
B75: 62 | C75: =CONCATENATE("N°-","00",B75,"-2024") -> N°-0062-2024 | D75: 781656755 | E75: Mr | F75: Elhadji abdoulaye | G75: Dieydiyabhe | H75: Dakar | I75: 78 165 67 55 | J75: 1000 | K75: 1000 | L75: 0 | M75: =IF(L75>=0,"A JOUR",($L75*($M$12))) -> A JOUR | N75: =IF(L75>0,SUM($Z75:$AR75)*$J75,0) -> 0 | O75: =+IF(L75>0,L75*J75,0) -> 0 | P75: =IF(L75>=0,"A JOUR",($L75*($M$12+J75)+O75)) -> A JOUR | Q75: x | R75: x | T75: 78 326 04 13 | U75: A JOUR | Z75: 1
B76: 63 | C76: =CONCATENATE("N°-","00",B76,"-2024") -> N°-0063-2024 | D76: 781313842 | E76: Mr | F76: Elhadji ablaye coiffeur | G76: Dieydiyabhe | H76: Dakar | I76: 78 131 38 42 | J76: 1000 | K76: 1000 | L76: 0 | M76: =IF(L76>=0,"A JOUR",($L76*($M$12))) -> A JOUR | N76: =IF(L76>0,SUM($Z76:$AR76)*$J76,0) -> 0 | O76: =+IF(L76>0,L76*J76,0) -> 0 | P76: =IF(L76>=0,"A JOUR",($L76*($M$12+J76)+O76)) -> A JOUR | Q76: x | R76: x | U76: A JOUR | Z76: 1 | AA76: 1 | AB76: 1 | AC76: 1 | AD76: 1 | AE76: 1 | AF76: 1 | AG76: 1 | AH76: 1 | AI76: 1 | AJ76: 1
B77: 64 | C77: =CONCATENATE("N°-","00",B77,"-2024") -> N°-0064-2024 | D77: xxxxxxxx | E77: Mr | F77: Elhadji aliou ibn bappa Siradio | G77: Dowsaré | H77: France | I77: xxxxxxxx | J77: 5000 | K77: 1000 | M77: =IF(L77>=0,"A JOUR",($L77*($M$12))) -> A JOUR | N77: =IF(L77>0,SUM($Z77:$AR77)*$J77,0) -> 0 | P77: =IF(L77>=0,"A JOUR",($L77*($M$12+J77)+O77)) -> A JOUR | R77: x | U77: #N/A | V77: #N/A | W77: #N/A | X77: #N/A | Y77: #N/A
B78: 65 | C78: =CONCATENATE("N°-","00",B78,"-2024") -> N°-0065-2024 | D78: 773012928 | E78: Mr | F78: Elhadji amadou | G78: Biilaa | H78: Dakar | I78: 77 301 29 28 | J78: 1000 | K78: 1000 | L78: =+SUM($Z78:$AR78) -> -36 | M78: =IF(L78>=0,"A JOUR",($L78*($M$12))) -> -72000 | N78: =IF(L78>0,SUM($Z78:$AR78)*$J78,0) -> 0 | P78: =IF(L78>=0,"A JOUR",($L78*($M$12+J78)+O78)) -> -108000 | Q78: x | R78: x | U78: #N/A | V78: #N/A | W78: #N/A | X78: 1000 | Y78: 34 | Z78: -36
B79: 66 | C79: =CONCATENATE("N°-","00",B79,"-2024") -> N°-0066-2024 | D79: 761722302 | E79: Mr | F79: Elhadji Boubacar mo moussou | G79: Pétel | H79: Dakar | I79: 76 172 23 02 | J79: 1000 | K79: 1000 | L79: =+SUM($Z79:$AR79) -> -46 | M79: =IF(L79>=0,"A JOUR",($L79*($M$12))) -> -92000 | N79: =IF(L79>0,SUM($Z79:$AR79)*$J79,0) -> 0 | P79: =IF(L79>=0,"A JOUR",($L79*($M$12+J79)+O79)) -> -138000 | Q79: x | R79: x | T79: 2 FOIS | U79: #N/A | V79: #N/A | W79: #N/A | X79: 1000 | Y79: 44 | Z79: -46
B80: 67 | C80: =CONCATENATE("N°-","00",B80,"-2024") -> N°-0067-2024 | D80: 622417844 | E80: Mr | F80: Elhadji douka chauffeur | G80: Dowsaré | H80: Guinée | I80: 622 41 78 44 | J80: 2000 | K80: 1000 | L80: 0 | M80: =IF(L80>=0,"A JOUR",($L80*($M$12))) -> A JOUR | N80: =IF(L80>0,SUM($Z80:$AR80)*$J80,0) -> 0 | O80: =+IF(L80>0,L80*J80,0) -> 0 | P80: =IF(L80>=0,"A JOUR",($L80*($M$12+J80)+O80)) -> A JOUR | Q80: x | R80: x | S80: VG | U80: #N/A | V80: GUINEE | Z80: VG
B81: 68 | C81: =CONCATENATE("N°-","00",B81,"-2024") -> N°-0068-2024 | D81: 784087096 | E81: Mr | F81: Elhadji ibrahima ibn Elhadji M. Woury | G81: Pétel | H81: Dakar | I81: 78 408 70 96 | J81: 1000 | K81: 1000 | L81: =+SUM($Z81:$AR81) -> -6 | M81: =IF(L81>=0,"A JOUR",($L81*($M$12))) -> -12000 | N81: =IF(L81>0,SUM($Z81:$AR81)*$J81,0) -> 0 | P81: =IF(L81>=0,"A JOUR",($L81*($M$12+J81)+O81)) -> -18000 | R81: x | U81: #N/A | V81: #N/A | W81: #N/A | X81: 1000 | Y81: 4 | Z81: -6
B82: 69 | C82: =CONCATENATE("N°-","00",B82,"-2024") -> N°-0069-2024 | D82: 776549856 | E82: Bappa | F82: Elhadji siradio | G82: Dowsaré | H82: Dakar | I82: 77 654 98 56 | J82: 5000 | K82: N/A | L82: 0 | M82: =IF(L82>=0,"A JOUR",($L82*($M$12))) -> A JOUR | N82: =IF(L82>0,SUM($Z82:$AR82)*$J82,0) -> 0 | O82: =+IF(L82>0,L82*J82,0) -> 0 | P82: =IF(L82>=0,"A JOUR",($L82*($M$12+J82)+O82)) -> A JOUR | R82: x | U82: A JOUR | Z82: 1
B83: 70 | C83: =CONCATENATE("N°-","00",B83,"-2024") -> N°-0070-2024 | D83: xxxxxxxx | E83: Mr | F83: Elhadji woury | G83: Dowsaré | H83: Gambie | I83: xxxxxxxx | J83: 2000 | K83: 1000 | M83: =IF(L83>=0,"A JOUR",($L83*($M$12))) -> A JOUR | N83: =IF(L83>0,SUM($Z83:$AR83)*$J83,0) -> 0 | P83: =IF(L83>=0,"A JOUR",($L83*($M$12+J83)+O83)) -> A JOUR | R83: x | U83: #N/A | V83: #N/A | W83: #N/A | X83: #N/A | Y83: #N/A | Z83: -7
B84: 71 | C84: =CONCATENATE("N°-","00",B84,"-2024") -> N°-0071-2024 | D84: 783260413 | E84: Mr | F84: Elhadji woury ibn bappa korka & yan safietou | G84: Dowsaré | H84: Dakar | I84: 78 326 04 13 | J84: 1000 | K84: 1000 | L84: =+SUM($Z84:$AR84) -> 0 | M84: =IF(L84>=0,"A JOUR",($L84*($M$12))) -> A JOUR | N84: =IF(L84>0,SUM($Z84:$AR84)*$J84,0) -> 0 | O84: =+IF(L84>0,L84*J84,0) -> 0 | P84: =IF(L84>=0,"A JOUR",($L84*($M$12+J84)+O84)) -> A JOUR | Q84: x | R84: x | U84: #N/A | V84: #N/A | W84: #N/A | X84: 1000 | Y84: 4
B85: 72 | C85: =CONCATENATE("N°-","00",B85,"-2024") -> N°-0072-2024 | D85: +393314576228 | E85: Mr | F85: Elhadji woury ibn Elhadji Ibrahima | G85: Pétel | H85: Italie | I85: +39 33 14 57 62 28 | J85: 5000 | K85: N/A | M85: =IF(L85>=0,"A JOUR",($L85*($M$12))) -> A JOUR | N85: =IF(L85>0,SUM($Z85:$AR85)*$J85,0) -> 0 | P85: =IF(L85>=0,"A JOUR",($L85*($M$12+J85)+O85)) -> A JOUR | R85: x | U85: #N/A | V85: #N/A | W85: #N/A | X85: #N/A | Y85: #N/A
B86: 73 | C86: =CONCATENATE("N°-","00",B86,"-2024") -> N°-0073-2024 | D86: 776049360 | E86: Mr | F86: Elhadji woury parcelles | G86: Kourawoye | H86: Dakar | I86: 77 604 93 60 | J86: 1000 | K86: 1000 | L86: 0 | M86: =IF(L86>=0,"A JOUR",($L86*($M$12))) -> A JOUR | N86: =IF(L86>0,SUM($Z86:$AR86)*$J86,0) -> 0 | O86: =+IF(L86>0,L86*J86,0) -> 0 | P86: =IF(L86>=0,"A JOUR",($L86*($M$12+J86)+O86)) -> A JOUR | Q86: x | R86: x | U86: A JOUR | Z86: 1
B87: 74 | C87: =CONCATENATE("N°-","00",B87,"-2024") -> N°-0074-2024 | D87: 774965371 | E87: Mr | F87: Elhadji woury petel ibn MD hamidou | G87: Pétel | H87: Dakar | I87: 77 496 53 71 | J87: 1000 | K87: 1000 | L87: =+SUM($Z87:$AR87) -> -6 | M87: =IF(L87>=0,"A JOUR",($L87*($M$12))) -> -12000 | N87: =IF(L87>0,SUM($Z87:$AR87)*$J87,0) -> 0 | P87: =IF(L87>=0,"A JOUR",($L87*($M$12+J87)+O87)) -> -18000 | Q87: x | R87: x | U87: #N/A | V87: #N/A | W87: #N/A | X87: 1000 | Y87: 3 | Z87: -6
B88: 75 | C88: =CONCATENATE("N°-","00",B88,"-2024") -> N°-0075-2024 | E88: Mr | F88: Elhaji aliou (lazo) | G88: Kourawoye | H88: Guinée | J88: N/A | K88: N/A | L88: VG | M88: =IF(L88>=0,"A JOUR",($L88*($M$12))) -> A JOUR | N88: =IF(L88>0,SUM($Z88:$AR88)*$J88,0) -> #VALUE! | P88: =IF(L88>=0,"A JOUR",($L88*($M$12+J88)+O88)) -> A JOUR | Q88: x | S88: VG | U88: #N/A | V88: #N/A | W88: #N/A | X88: #N/A | Y88: #N/A | Z88: VG
B89: 76 | C89: =CONCATENATE("N°-","00",B89,"-2024") -> N°-0076-2024 | D89: 773851455 | E89: Mr | F89: Hamidou | G89: Dowsaré | H89: Dakar | I89: 77 385 14 55 | J89: 1000 | K89: 1000 | L89: 0 | M89: =IF(L89>=0,"A JOUR",($L89*($M$12))) -> A JOUR | N89: =IF(L89>0,SUM($Z89:$AR89)*$J89,0) -> 0 | O89: =+IF(L89>0,L89*J89,0) -> 0 | P89: =IF(L89>=0,"A JOUR",($L89*($M$12+J89)+O89)) -> A JOUR | Q89: x | R89: x | U89: A JOUR | Z89: NT
B90: 77 | C90: =CONCATENATE("N°-","00",B90,"-2024") -> N°-0077-2024 | D90: 776232888 | E90: Oustaz | F90: Ibrahima | G90: Daandé Mboully | H90: Dakar | I90: 77 623 28 88 | J90: 2000 | K90: 1000 | L90: 0 | M90: =IF(L90>=0,"A JOUR",($L90*($M$12))) -> A JOUR | N90: =IF(L90>0,SUM($Z90:$AR90)*$J90,0) -> 0 | O90: =+IF(L90>0,L90*J90,0) -> 0 | P90: =IF(L90>=0,"A JOUR",($L90*($M$12+J90)+O90)) -> A JOUR | Q90: x | R90: x | U90: A JOUR | Z90: 1
B91: 78 | C91: =CONCATENATE("N°-","00",B91,"-2024") -> N°-0078-2024 | D91: 775220275 | E91: Koto | F91: Ibrahima | G91: Kourawoye | H91: Dakar | I91: 77 522 02 75 | J91: 2000 | K91: N/A | L91: =+SUM($Z91:$AR91) -> -41 | M91: =IF(L91>=0,"A JOUR",($L91*($M$12))) -> -82000 | N91: =IF(L91>0,SUM($Z91:$AR91)*$J91,0) -> 0 | P91: =IF(L91>=0,"A JOUR",($L91*($M$12+J91)+O91)) -> -164000 | Q91: x | R91: x | U91: #N/A | V91: #N/A | W91: #N/A | X91: 2000 | Y91: 41 | Z91: -41
B92: 79 | C92: =CONCATENATE("N°-","00",B92,"-2024") -> N°-0079-2024 | D92: 778018660 | E92: Mr | F92: Ibrahima | G92: Diabbhéhi | H92: Guinée | I92: 77 801 86 60 | J92: 1000 | K92: 1000 | L92: =+SUM($Z92:$AR92) -> -14 | M92: =IF(L92>=0,"A JOUR",($L92*($M$12))) -> -28000 | N92: =IF(L92>0,SUM($Z92:$AR92)*$J92,0) -> 0 | P92: =IF(L92>=0,"A JOUR",($L92*($M$12+J92)+O92)) -> -42000 | Q92: x | R92: x | S92: NT | U92: #N/A | V92: #N/A | W92: #N/A | X92: 1000 | Y92: 14 | Z92: -14 | AA92: VG
B93: 80 | C93: =CONCATENATE("N°-","00",B93,"-2024") -> N°-0080-2024 | D93: 773809784 | E93: Koto | F93: Ibrahima | G93: Leysaré | H93: Dakar | I93: 77 380 97 84 | J93: 2000 | K93: 1000 | L93: 0 | M93: =IF(L93>=0,"A JOUR",($L93*($M$12))) -> A JOUR | N93: =IF(L93>0,SUM($Z93:$AR93)*$J93,0) -> 0 | O93: =+IF(L93>0,L93*J93,0) -> 0 | P93: =IF(L93>=0,"A JOUR",($L93*($M$12+J93)+O93)) -> A JOUR | Q93: x | R93: x | U93: #N/A | V93: GUINEE | Z93: VG
B94: 81 | C94: =CONCATENATE("N°-","00",B94,"-2024") -> N°-0081-2024 | D94: 777551504 | E94: Koto | F94: Ibrahima | G94: Porétély | H94: Dakar | I94: 77 755 15 04 | J94: 2000 | K94: 1000 | L94: =+SUM($Z94:$AR94) -> -37 | M94: =IF(L94>=0,"A JOUR",($L94*($M$12))) -> -74000 | N94: =IF(L94>0,SUM($Z94:$AR94)*$J94,0) -> 0 | P94: =IF(L94>=0,"A JOUR",($L94*($M$12+J94)+O94)) -> -148000 | Q94: x | R94: x | U94: #N/A | V94: #N/A | W94: #N/A | X94: 2000 | Y94: 35 | Z94: -37
B95: 82 | C95: =CONCATENATE("N°-","00",B95,"-2024") -> N°-0082-2024 | D95: 788380743 | E95: Mr | F95: Ibrahima ibn bappa Siradio | G95: Dowsaré | H95: Dakar | I95: 78 838 07 43 | J95: 1000 | K95: 1000 | L95: 0 | M95: =IF(L95>=0,"A JOUR",($L95*($M$12))) -> A JOUR | N95: =IF(L95>0,SUM($Z95:$AR95)*$J95,0) -> 0 | O95: =+IF(L95>0,L95*J95,0) -> 0 | P95: =IF(L95>=0,"A JOUR",($L95*($M$12+J95)+O95)) -> A JOUR | U95: A JOUR | Z95: NT
B96: 83 | C96: =CONCATENATE("N°-","00",B96,"-2024") -> N°-0083-2024 | D96: 781292637 | E96: Koto | F96: Ibrahima KZA ibnou samara | G96: Dowsaré | H96: Casamance | I96: 78 129 26 37 | J96: 2000 | K96: 1000 | L96: 11 | M96: =IF(L96>=0,"A JOUR",($L96*($M$12))) -> A JOUR | N96: =IF(L96>0,SUM($Z96:$AR96)*$J96,0) -> 2000 | O96: =+IF(L96>0,L96*J96,0) -> 22000 | P96: =IF(L96>=0,"A JOUR",($L96*($M$12+J96)+O96)) -> A JOUR | Q96: x | R96: x | U96: A JOUR | Z96: 1
B97: 84 | C97: =CONCATENATE("N°-","00",B97,"-2024") -> N°-0084-2024 | D97: 774370979 | E97: Koto | F97: Ibrahima N°1 ibn bappa bala | G97: Pétel | H97: Dakar | I97: 77 437 09 79 | J97: 2000 | K97: 1000 | L97: 0 | M97: =IF(L97>=0,"A JOUR",($L97*($M$12))) -> A JOUR | N97: =IF(L97>0,SUM($Z97:$AR97)*$J97,0) -> 0 | O97: =+IF(L97>0,L97*J97,0) -> 0 | P97: =IF(L97>=0,"A JOUR",($L97*($M$12+J97)+O97)) -> A JOUR | Q97: x | R97: x | S97: NT | U97: #N/A | V97: #N/A | W97: NT | Z97: NT
B98: 85 | C98: =CONCATENATE("N°-","00",B98,"-2024") -> N°-0085-2024 | D98: 774069087 | E98: Mr | F98: Ibrahima Sory | G98: Biilaa | H98: Dakar | I98: 77 406 90 87 | J98: 2000 | K98: 1000 | L98: 0 | M98: =IF(L98>=0,"A JOUR",($L98*($M$12))) -> A JOUR | N98: =IF(L98>0,SUM($Z98:$AR98)*$J98,0) -> 0 | O98: =+IF(L98>0,L98*J98,0) -> 0 | P98: =IF(L98>=0,"A JOUR",($L98*($M$12+J98)+O98)) -> A JOUR | Q98: x | R98: x | U98: #N/A | V98: #N/A | W98: NT | Z98: NT
B99: 86 | C99: =CONCATENATE("N°-","00",B99,"-2024") -> N°-0086-2024 | D99: 750190226 | E99: Koto | F99: Ismaila | G99: Pétel | H99: Dakar | I99: 75 019 02 26 | J99: 1000 | K99: 1000 | L99: 0 | M99: =IF(L99>=0,"A JOUR",($L99*($M$12))) -> A JOUR | N99: =IF(L99>0,SUM($Z99:$AR99)*$J99,0) -> 0 | O99: =+IF(L99>0,L99*J99,0) -> 0 | P99: =IF(L99>=0,"A JOUR",($L99*($M$12+J99)+O99)) -> A JOUR | Q99: x | R99: x | S99: NT | U99: #N/A | V99: #N/A | W99: NT | Z99: NT
B100: 87 | C100: =CONCATENATE("N°-","00",B100,"-2024") -> N°-0087-2024 | D100: 775379233 | E100: Dr | F100: Korka | G100: Kourawoye | H100: Dakar | I100: 77 537 92 33 | J100: 5000 | K100: N/A | L100: 0 | M100: =IF(L100>=0,"A JOUR",($L100*($M$12))) -> A JOUR | N100: =IF(L100>0,SUM($Z100:$AR100)*$J100,0) -> 0 | O100: =+IF(L100>0,L100*J100,0) -> 0 | P100: =IF(L100>=0,"A JOUR",($L100*($M$12+J100)+O100)) -> A JOUR | R100: x | U100: A JOUR | Z100: 1
B101: 88 | C101: =CONCATENATE("N°-","00",B101,"-2024") -> N°-0088-2024 | D101: 777814802 | E101: Koto | F101: korka | G101: Bowell | H101: Dakar | I101: 77 781 48 02 | J101: 1500 | K101: N/A | L101: 0 | M101: =IF(L101>=0,"A JOUR",($L101*($M$12))) -> A JOUR | N101: =IF(L101>0,SUM($Z101:$AR101)*$J101,0) -> 0 | O101: =+IF(L101>0,L101*J101,0) -> 0 | P101: =IF(L101>=0,"A JOUR",($L101*($M$12+J101)+O101)) -> A JOUR | R101: x | U101: A JOUR | Z101: VG
B102: 89 | C102: =CONCATENATE("N°-","00",B102,"-2024") -> N°-0089-2024 | D102: 771740329 | E102: Koto | F102: Lamarana | G102: Daandé Mboully | H102: Dakar | I102: 77 174 03 29 | J102: 1500 | K102: N/A | L102: 0 | M102: =IF(L102>=0,"A JOUR",($L102*($M$12))) -> A JOUR | N102: =IF(L102>0,SUM($Z102:$AR102)*$J102,0) -> 0 | O102: =+IF(L102>0,L102*J102,0) -> 0 | P102: =IF(L102>=0,"A JOUR",($L102*($M$12+J102)+O102)) -> A JOUR | R102: x | U102: A JOUR | Z102: 1
B103: 90 | C103: =CONCATENATE("N°-","00",B103,"-2024") -> N°-0090-2024 | D103: 781344236 | E103: Koto | F103: Lamarana | G103: Pétel | H103: Dakar | I103: 78 134 42 36 | J103: 2000 | K103: 1000 | L103: 0 | M103: =IF(L103>=0,"A JOUR",($L103*($M$12))) -> A JOUR | N103: =IF(L103>0,SUM($Z103:$AR103)*$J103,0) -> 0 | O103: =+IF(L103>0,L103*J103,0) -> 0 | P103: =IF(L103>=0,"A JOUR",($L103*($M$12+J103)+O103)) -> A JOUR | Q103: x | R103: x | S103: NT | U103: #N/A | V103: #N/A | W103: NT | Z103: NT
B104: 91 | C104: =CONCATENATE("N°-","00",B104,"-2024") -> N°-0091-2024 | D104: 778870311 | E104: Koto | F104: Mamadou Aliou | G104: Biilaa | H104: Dakar | I104: 77 887 03 11 | J104: 1000 | K104: 1000 | L104: =2-2 -> 0 | M104: =IF(L104>=0,"A JOUR",($L104*($M$12))) -> A JOUR | N104: =IF(L104>0,SUM($Z104:$AR104)*$J104,0) -> 0 | O104: =+IF(L104>0,L104*J104,0) -> 0 | P104: =IF(L104>=0,"A JOUR",($L104*($M$12+J104)+O104)) -> A JOUR | Q104: x | R104: x | U104: A JOUR | Z104: 1
B105: 92 | C105: =CONCATENATE("N°-","00",B105,"-2024") -> N°-0092-2024 | D105: +393384244960 | E105: Grand | F105: Mamadou aliou ibn Elhadji M. Woury | G105: Pétel | H105: Italie | I105: +39 338 424 49 60 | J105: 5000 | K105: N/A | M105: =IF(L105>=0,"A JOUR",($L105*($M$12))) -> A JOUR | N105: =IF(L105>0,SUM($Z105:$AR105)*$J105,0) -> 0 | P105: =IF(L105>=0,"A JOUR",($L105*($M$12+J105)+O105)) -> A JOUR | R105: x | U105: #N/A | V105: #N/A | W105: #N/A | X105: #N/A | Y105: #N/A
B106: 93 | C106: =CONCATENATE("N°-","00",B106,"-2024") -> N°-0093-2024 | D106: 775957597 | E106: Mr | F106: Mamadou aliou ibnu mamoudou | G106: Biilaa | H106: Dakar | I106: 77 595 75 97 | J106: 1000 | K106: 1000 | L106: =+SUM($Z106:$AR106) -> -18 | M106: =IF(L106>=0,"A JOUR",($L106*($M$12))) -> -36000 | N106: =IF(L106>0,SUM($Z106:$AR106)*$J106,0) -> 0 | P106: =IF(L106>=0,"A JOUR",($L106*($M$12+J106)+O106)) -> -54000 | Q106: x | U106: #N/A | V106: #N/A | W106: #N/A | X106: 1000 | Y106: 17 | Z106: -18 | AA106: VG
B107: 94 | C107: =CONCATENATE("N°-","00",B107,"-2024") -> N°-0094-2024 | D107: 781313280 | E107: Koto | F107: Mamadou alpha | G107: Dieydiyabhe | H107: Dakar | I107: 78 131 32 80 | J107: 2000 | K107: N/A | L107: 0 | M107: =IF(L107>=0,"A JOUR",($L107*($M$12))) -> A JOUR | N107: =IF(L107>0,SUM($Z107:$AR107)*$J107,0) -> 0 | O107: =+IF(L107>0,L107*J107,0) -> 0 | P107: =IF(L107>=0,"A JOUR",($L107*($M$12+J107)+O107)) -> A JOUR | R107: x | U107: A JOUR | Z107: 1
B108: 95 | C108: =CONCATENATE("N°-","00",B108,"-2024") -> N°-0095-2024 | D108: 773138810 | E108: Mr | F108: Mamadou alpha ibn Elhadji Ibrahima | G108: Pétel | H108: Dakar | I108: 77 313 88 10 | J108: 1000 | K108: 1000 | L108: =-34+9+25 -> 0 | M108: =IF(L108>=0,"A JOUR",($L108*($M$12))) -> A JOUR | N108: =IF(L108>0,SUM($Z108:$AR108)*$J108,0) -> 0 | O108: =+IF(L108>0,L108*J108,0) -> 0 | P108: =IF(L108>=0,"A JOUR",($L108*($M$12+J108)+O108)) -> A JOUR | R108: x | U108: A JOUR
...

Sheet Données MSDL BON
B6: UNION DES JEUNES DE DOUKA SELEYABE
G8: =+TODAY() -> 46001
B10: LISTE OFFICIELLE DES MEMBRES
U11: 9000 DU PAR DAOUDA + 50K + AMENDE
M12: 2000
B13: N° | C13: Code | D13: Téléphone | E13: Titre | F13: Désignation | G13: Missidé | H13: Pays/région | I13: Téléphone | J13: Montant mensuel MSD | K13: Montant mensuel UJDS | L13: Nbre de mois retard | M13: Amande | N13: Avance Ancien | O13: Avance | P13: Amande MSDL | Q13: Montant versé | R13: Montant dû au 31 12 25 | S13: UJDS | T13: MOUSSIDAL | U13: STATUT | V13: 45689 | W13: 45717 | X13: 45748 | Y13: 45778 | Z13: 45809 | AA13: 45839 | AB13: 45870 | AC13: 45901 | AD13: 45931 | AE13: 45962 | AF13: 45992 | AH13: 45717 | AI13: 45748 | AJ13: 45778 | AK13: 45809 | AL13: 45839 | AM13: 45870 | AN13: 45901 | AO13: 45931 | AP13: 45962 | AQ13: 45992
B14: 1 | C14: =CONCATENATE("N°-","000",B14,"-2024") -> N°-0001-2024 | D14: 778779867 | E14: Mr | F14: Abdoul aziz ibn Elhadji Ibrahima | G14: Pétel | H14: Dakar | I14: 77 877 98 67 | J14: 1000 | K14: N/A | L14: =+IF(SUM($V14:$AO14)>0,0,SUM($V14:$AO14)) -> -67 | M14: =IF(L14>=0,"A JOUR",(SUM($V14:$Y14)*($M$12))) -> -120000 | O14: =+IF(L14>0,L14*J14,0) -> 0 | Q14: =SUBTOTAL(9,$AH14:$AQ14) -> 0 | R14: =IF(L14>=0,"A JOUR",($L14*($J14)+N14+O14+$M14)) -> -187000 | T14: x | U14: 228000 | V14: -57 | W14: -1 | X14: -1 | Y14: -1 | Z14: -1 | AA14: -1 | AB14: -1 | AC14: -1 | AD14: -1 | AE14: -1 | AF14: -1 | AH14: =+IFERROR(IF(W14*$J14<0,0,W14*$J14),0) -> 0 | AI14: =+IFERROR(IF(X14*$J14<0,0,X14*$J14),0) -> 0 | AJ14: =+IFERROR(IF(Y14*$J14<0,0,Y14*$J14),0) -> 0 | AK14: =+IFERROR(IF(Z14*$J14<0,0,Z14*$J14),0) -> 0 | AL14: =+IFERROR(IF(AA14*$J14<0,0,AA14*$J14),0) -> 0 | AM14: =+IFERROR(IF(AB14*$J14<0,0,AB14*$J14),0) -> 0 | AN14: =+IFERROR(IF(AC14*$J14<0,0,AC14*$J14),0) -> 0 | AO14: =+IFERROR(IF(AD14*$J14<0,0,AD14*$J14),0) -> 0 | ... AQ14: =+IFERROR(IF(AF14*$J14<0,0,AF14*$J14),0) -> 0
B15: 2 | C15: =CONCATENATE("N°-","000",B15,"-2024") -> N°-0002-2024 | D15: 772175292 | E15: Koto | F15: Abdoul ghadry | G15: Leysaré | H15: Dakar | I15: 77 217 52 92 | J15: 2000 | K15: 1000 | L15: 0 | M15: =IF(L15>=0,"A JOUR",(SUM($V15:$Y15)*($M$12))) -> A JOUR | O15: =+IF(L15>0,L15*J15,0) -> 0 | Q15: =SUBTOTAL(9,$AH15:$AQ15) -> 20000 | R15: =IF(L15>=0,"A JOUR",($L15*($J15)+N15+O15+$M15)) -> A JOUR | S15: x | T15: x | V15: 1 | W15: 1 | X15: 1 | Y15: 1 | Z15: 1 | AA15: 1 | AB15: 1 | AC15: 1 | AD15: 1 | AE15: 1 | AF15: 1 | AH15: =+IFERROR(IF(W15*$J15<0,0,W15*$J15),0) -> 2000 | AI15: =+IFERROR(IF(X15*$J15<0,0,X15*$J15),0) -> 2000 | AJ15: =+IFERROR(IF(Y15*$J15<0,0,Y15*$J15),0) -> 2000 | AK15: =+IFERROR(IF(Z15*$J15<0,0,Z15*$J15),0) -> 2000 | AL15: =+IFERROR(IF(AA15*$J15<0,0,AA15*$J15),0) -> 2000 | AM15: =+IFERROR(IF(AB15*$J15<0,0,AB15*$J15),0) -> 2000 | AN15: =+IFERROR(IF(AC15*$J15<0,0,AC15*$J15),0) -> 2000 | AO15: =+IFERROR(IF(AD15*$J15<0,0,AD15*$J15),0) -> 2000 | ... AQ15: =+IFERROR(IF(AF15*$J15<0,0,AF15*$J15),0) -> 2000
B16: 3 | C16: =CONCATENATE("N°-","000",B16,"-2024") -> N°-0003-2024 | D16: xxxxxxxx | E16: Mr | F16: Abdoul goudoussy | G16: Kourawoye | H16: Guinée | I16: xxxxxxxx | K16: 1000 | L16: VG | M16: =IF(L16>=0,"A JOUR",(SUM($V16:$Y16)*($M$12))) -> A JOUR | Q16: =SUBTOTAL(9,$AH16:$AQ16) -> 0 | R16: =IF(L16>=0,"A JOUR",($L16*($J16)+N16+O16+$M16)) -> A JOUR | S16: x | V16: VG
B17: 4 | C17: =CONCATENATE("N°-","000",B17,"-2024") -> N°-0004-2024 | D17: 773528333 | E17: Kaou | F17: Abdoul malipan | G17: Dowsaré | H17: Dakar | I17: 77 352 83 33 | J17: 2000 | K17: N/A | L17: =-27-5 -> -32 | M17: =IF(L17>=0,"A JOUR",(SUM($V17:$Y17)*($M$12))) -> -48000 | O17: 75000 | Q17: =SUBTOTAL(9,$AH17:$AQ17) -> 20000 | R17: =IF(L17>=0,"A JOUR",($L17*($J17)+N17+O17+$M17)) -> -37000 | T17: x | V17: -27 | W17: 1 | X17: 1 | Y17: 1 | Z17: 1 | AA17: 1 | AB17: 1 | AC17: 1 | AD17: 1 | AE17: 1 | AF17: 1 | AH17: =+IFERROR(IF(W17*$J17<0,0,W17*$J17),0) -> 2000 | AI17: =+IFERROR(IF(X17*$J17<0,0,X17*$J17),0) -> 2000 | AJ17: =+IFERROR(IF(Y17*$J17<0,0,Y17*$J17),0) -> 2000 | AK17: =+IFERROR(IF(Z17*$J17<0,0,Z17*$J17),0) -> 2000 | AL17: =+IFERROR(IF(AA17*$J17<0,0,AA17*$J17),0) -> 2000 | AM17: =+IFERROR(IF(AB17*$J17<0,0,AB17*$J17),0) -> 2000 | AN17: =+IFERROR(IF(AC17*$J17<0,0,AC17*$J17),0) -> 2000 | AO17: =+IFERROR(IF(AD17*$J17<0,0,AD17*$J17),0) -> 2000 | ... AQ17: =+IFERROR(IF(AF17*$J17<0,0,AF17*$J17),0) -> 2000
B18: 5 | C18: =CONCATENATE("N°-","000",B18,"-2024") -> N°-0005-2024 | D18: xxxxxxxx | E18: Koto | F18: Abdoul salam | G18: Gobihi | H18: Gambie | I18: xxxxxxxx | J18: 2000 | K18: 1000 | M18: =IF(L18>=0,"A JOUR",(SUM($V18:$Y18)*($M$12))) -> A JOUR | O18: =+IF(L18>0,L18*J18,0) -> 0 | Q18: =SUBTOTAL(9,$AH18:$AQ18) -> 0 | R18: =IF(L18>=0,"A JOUR",($L18*($J18)+N18+O18+$M18)) -> A JOUR | T18: x
B19: 6 | C19: =CONCATENATE("N°-","000",B19,"-2024") -> N°-0006-2024 | D19: 774789094 | E19: Mr | F19: Abdoul salam petit ibn bappa bala | G19: Pétel | H19: Dakar | I19: 77 478 90 94 | J19: 2000 | K19: 1000 | L19: 0 | M19: =IF(L19>=0,"A JOUR",(SUM($V19:$Y19)*($M$12))) -> A JOUR | O19: =+IF(L19>0,L19*J19,0) -> 0 | Q19: =SUBTOTAL(9,$AH19:$AQ19) -> 0 | R19: =IF(L19>=0,"A JOUR",($L19*($J19)+N19+O19+$M19)) -> A JOUR | S19: x | T19: x
B20: 7 | C20: =CONCATENATE("N°-","000",B20,"-2024") -> N°-0007-2024 | D20: 781050363 | E20: Koto | F20: Abdoul salam ibn Elhadji M. Woury VP | G20: Pétel | H20: Dakar | I20: 78 105 03 63 | J20: 2000 | K20: 1000 | L20: 0 | M20: =IF(L20>=0,"A JOUR",(SUM($V20:$Y20)*($M$12))) -> A JOUR | O20: =+IF(L20>0,L20*J20,0) -> 0 | Q20: =SUBTOTAL(9,$AH20:$AQ20) -> 20000 | R20: =IF(L20>=0,"A JOUR",($L20*($J20)+N20+O20+$M20)) -> A JOUR | S20: x | T20: x | V20: 1 | W20: 1 | X20: 1 | Y20: 1 | Z20: 1 | AA20: 1 | AB20: 1 | AC20: 1 | AD20: 1 | AE20: 1 | AF20: 1 | AH20: =+IFERROR(IF(W20*$J20<0,0,W20*$J20),0) -> 2000 | AI20: =+IFERROR(IF(X20*$J20<0,0,X20*$J20),0) -> 2000 | AJ20: =+IFERROR(IF(Y20*$J20<0,0,Y20*$J20),0) -> 2000 | AK20: =+IFERROR(IF(Z20*$J20<0,0,Z20*$J20),0) -> 2000 | AL20: =+IFERROR(IF(AA20*$J20<0,0,AA20*$J20),0) -> 2000 | AM20: =+IFERROR(IF(AB20*$J20<0,0,AB20*$J20),0) -> 2000 | AN20: =+IFERROR(IF(AC20*$J20<0,0,AC20*$J20),0) -> 2000 | AO20: =+IFERROR(IF(AD20*$J20<0,0,AD20*$J20),0) -> 2000 | ... AQ20: =+IFERROR(IF(AF20*$J20<0,0,AF20*$J20),0) -> 2000
B21: 8 | C21: =CONCATENATE("N°-","000",B21,"-2024") -> N°-0008-2024 | D21: +24104506555 | E21: Mr | F21: Abdoul salam ibn karamoko Daouda | G21: Pétel | H21: Gabon | I21: +241 04 50 65 55 | J21: 5000 | K21: N/A | M21: =IF(L21>=0,"A JOUR",(SUM($V21:$Y21)*($M$12))) -> A JOUR | Q21: =SUBTOTAL(9,$AH21:$AQ21) -> 0 | R21: =IF(L21>=0,"A JOUR",($L21*($J21)+N21+O21+$M21)) -> A JOUR | T21: x
B22: 9 | C22: =CONCATENATE("N°-","000",B22,"-2024") -> N°-0009-2024 | D22: 774789094 | E22: Mr | F22: Abdoul salam petit | G22: Pétel | H22: Dakar | I22: 77 478 90 94 | J22: 2000 | K22: 1000 | L22: 0 | M22: =IF(L22>=0,"A JOUR",(SUM($V22:$Y22)*($M$12))) -> A JOUR | O22: =+IF(L22>0,L22*J22,0) -> 0 | Q22: =SUBTOTAL(9,$AH22:$AQ22) -> 0 | R22: =IF(L22>=0,"A JOUR",($L22*($J22)+N22+O22+$M22)) -> A JOUR | S22: x | T22: x | V22: NT | W22: NT | X22: NT | Y22: NT | Z22: NT | AA22: NT | AB22: NT | AC22: NT | AD22: NT | AE22: NT | AF22: NT | AH22: =+IFERROR(IF(W22*$J22<0,0,W22*$J22),0) -> 0 | AI22: =+IFERROR(IF(X22*$J22<0,0,X22*$J22),0) -> 0 | AJ22: =+IFERROR(IF(Y22*$J22<0,0,Y22*$J22),0) -> 0 | AK22: =+IFERROR(IF(Z22*$J22<0,0,Z22*$J22),0) -> 0 | AL22: =+IFERROR(IF(AA22*$J22<0,0,AA22*$J22),0) -> 0 | AM22: =+IFERROR(IF(AB22*$J22<0,0,AB22*$J22),0) -> 0 | AN22: =+IFERROR(IF(AC22*$J22<0,0,AC22*$J22),0) -> 0 | AO22: =+IFERROR(IF(AD22*$J22<0,0,AD22*$J22),0) -> 0 | ... AQ22: =+IFERROR(IF(AF22*$J22<0,0,AF22*$J22),0) -> 0
B23: 10 | C23: =CONCATENATE("N°-","00",B23,"-2024") -> N°-0010-2024 | D23: 776792624 | E23: Mr | F23: Abdoul salam PP | G23: Dieydiyabhe | H23: Dakar | I23: 77 679 26 24 | J23: 1000 | K23: 1000 | L23: 0 | M23: =IF(L23>=0,"A JOUR",(SUM($V23:$Y23)*($M$12))) -> A JOUR | O23: =+IF(L23>0,L23*J23,0) -> 0 | Q23: =SUBTOTAL(9,$AH23:$AQ23) -> 0 | R23: =IF(L23>=0,"A JOUR",($L23*($J23)+N23+O23+$M23)) -> A JOUR | S23: x | T23: x | V23: VG | W23: VG | X23: VG | Y23: VG | Z23: VG | AA23: VG | AB23: VG | AC23: VG | AD23: VG | AE23: VG | AF23: VG | AH23: =+IFERROR(IF(W23*$J23<0,0,W23*$J23),0) -> 0 | AI23: =+IFERROR(IF(X23*$J23<0,0,X23*$J23),0) -> 0 | AJ23: =+IFERROR(IF(Y23*$J23<0,0,Y23*$J23),0) -> 0 | AK23: =+IFERROR(IF(Z23*$J23<0,0,Z23*$J23),0) -> 0 | AL23: =+IFERROR(IF(AA23*$J23<0,0,AA23*$J23),0) -> 0 | AM23: =+IFERROR(IF(AB23*$J23<0,0,AB23*$J23),0) -> 0 | AN23: =+IFERROR(IF(AC23*$J23<0,0,AC23*$J23),0) -> 0 | AO23: =+IFERROR(IF(AD23*$J23<0,0,AD23*$J23),0) -> 0 | ... AQ23: =+IFERROR(IF(AF23*$J23<0,0,AF23*$J23),0) -> 0
B24: 11 | C24: =CONCATENATE("N°-","00",B24,"-2024") -> N°-0011-2024 | D24: 775779980 | E24: Mr | F24: Abdoul salam PP (ivoire) | G24: Dowsaré | H24: Dakar | I24: 77 577 99 80 | J24: 1000 | K24: 1000 | L24: =+SUM($V24:$AO24) -> -4 | M24: =IF(L24>=0,"A JOUR",(SUM($V24:$Y24)*($M$12))) -> -8000 | Q24: =SUBTOTAL(9,$AH24:$AQ24) -> 0 | R24: =IF(L24>=0,"A JOUR",($L24*($J24)+N24+O24+$M24)) -> -12000 | S24: x | T24: x | V24: -4 | W24: VG | X24: VG | Y24: VG | Z24: VG | AA24: VG | AB24: VG | AC24: VG | AD24: VG | AE24: VG | AF24: VG | AH24: =+IFERROR(IF(W24*$J24<0,0,W24*$J24),0) -> 0 | AI24: =+IFERROR(IF(X24*$J24<0,0,X24*$J24),0) -> 0 | AJ24: =+IFERROR(IF(Y24*$J24<0,0,Y24*$J24),0) -> 0 | AK24: =+IFERROR(IF(Z24*$J24<0,0,Z24*$J24),0) -> 0 | AL24: =+IFERROR(IF(AA24*$J24<0,0,AA24*$J24),0) -> 0 | AM24: =+IFERROR(IF(AB24*$J24<0,0,AB24*$J24),0) -> 0 | AN24: =+IFERROR(IF(AC24*$J24<0,0,AC24*$J24),0) -> 0 | AO24: =+IFERROR(IF(AD24*$J24<0,0,AD24*$J24),0) -> 0 | ... AQ24: =+IFERROR(IF(AF24*$J24<0,0,AF24*$J24),0) -> 0
B25: 12 | C25: =CONCATENATE("N°-","00",B25,"-2024") -> N°-0012-2024 | E25: Mr | F25: Abdoulaye | G25: Daandé Mboully | H25: Guinée | K25: 1000 | L25: VG | M25: =IF(L25>=0,"A JOUR",(SUM($V25:$Y25)*($M$12))) -> A JOUR | Q25: =SUBTOTAL(9,$AH25:$AQ25) -> 0 | R25: =IF(L25>=0,"A JOUR",($L25*($J25)+N25+O25+$M25)) -> A JOUR | S25: x | V25: VG
B26: 13 | C26: =CONCATENATE("N°-","00",B26,"-2024") -> N°-0013-2024 | D26: xxxxxxxx | E26: Mr | F26: Abdoulaye | G26: Kourawoye | H26: Côte d'ivoire | I26: xxxxxxxx | J26: 1000 | K26: N/A | M26: =IF(L26>=0,"A JOUR",(SUM($V26:$Y26)*($M$12))) -> A JOUR | Q26: =SUBTOTAL(9,$AH26:$AQ26) -> 0 | R26: =IF(L26>=0,"A JOUR",($L26*($J26)+N26+O26+$M26)) -> A JOUR | S26: x | T26: x
B27: 14 | C27: =CONCATENATE("N°-","00",B27,"-2024") -> N°-0014-2024 | D27: 781413617 | E27: Grand | F27: Abdoulaye (Laye) | G27: Biilaa | H27: Guinée | I27: 78 141 36 17 | J27: 1000 | K27: 1000 | L27: 0 | M27: =IF(L27>=0,"A JOUR",(SUM($V27:$Y27)*($M$12))) -> A JOUR | O27: =+IF(L27>0,L27*J27,0) -> 0 | Q27: =SUBTOTAL(9,$AH27:$AQ27) -> 0 | R27: =IF(L27>=0,"A JOUR",($L27*($J27)+N27+O27+$M27)) -> A JOUR | S27: x | T27: x | V27: VG | W27: VG | X27: VG | Y27: VG | Z27: VG | AA27: VG | AB27: VG | AC27: VG | AD27: VG | AE27: VG | AF27: VG | AH27: =+IFERROR(IF(W27*$J27<0,0,W27*$J27),0) -> 0 | AI27: =+IFERROR(IF(X27*$J27<0,0,X27*$J27),0) -> 0 | AJ27: =+IFERROR(IF(Y27*$J27<0,0,Y27*$J27),0) -> 0 | AK27: =+IFERROR(IF(Z27*$J27<0,0,Z27*$J27),0) -> 0 | AL27: =+IFERROR(IF(AA27*$J27<0,0,AA27*$J27),0) -> 0 | AM27: =+IFERROR(IF(AB27*$J27<0,0,AB27*$J27),0) -> 0 | AN27: =+IFERROR(IF(AC27*$J27<0,0,AC27*$J27),0) -> 0 | AO27: =+IFERROR(IF(AD27*$J27<0,0,AD27*$J27),0) -> 0 | ... AQ27: =+IFERROR(IF(AF27*$J27<0,0,AF27*$J27),0) -> 0
B28: 15 | C28: =CONCATENATE("N°-","00",B28,"-2024") -> N°-0015-2024 | D28: +24106399421 | E28: Grand | F28: Abdoulaye (Laye) gabonais | G28: Pétel | H28: Dakar | I28: +241 06 39 94 21 | J28: 2000 | K28: N/A | L28: =+SUM($V28:$AO28) -> 0 | M28: =IF(L28>=0,"A JOUR",(SUM($V28:$Y28)*($M$12))) -> A JOUR | Q28: =SUBTOTAL(9,$AH28:$AQ28) -> 0 | R28: =IF(L28>=0,"A JOUR",($L28*($J28)+N28+O28+$M28)) -> A JOUR | T28: x | V28: NT | W28: NT | X28: NT | Y28: NT | Z28: NT | AA28: NT | AB28: NT | AC28: NT | AD28: NT | AE28: NT | AF28: NT | AH28: =+IFERROR(IF(W28*$J28<0,0,W28*$J28),0) -> 0 | AI28: =+IFERROR(IF(X28*$J28<0,0,X28*$J28),0) -> 0 | AJ28: =+IFERROR(IF(Y28*$J28<0,0,Y28*$J28),0) -> 0 | AK28: =+IFERROR(IF(Z28*$J28<0,0,Z28*$J28),0) -> 0 | AL28: =+IFERROR(IF(AA28*$J28<0,0,AA28*$J28),0) -> 0 | AM28: =+IFERROR(IF(AB28*$J28<0,0,AB28*$J28),0) -> 0 | AN28: =+IFERROR(IF(AC28*$J28<0,0,AC28*$J28),0) -> 0 | AO28: =+IFERROR(IF(AD28*$J28<0,0,AD28*$J28),0) -> 0 | ... AQ28: =+IFERROR(IF(AF28*$J28<0,0,AF28*$J28),0) -> 0
B29: 16 | C29: =CONCATENATE("N°-","00",B29,"-2024") -> N°-0016-2024 | D29: 777255426 | E29: Mr | F29: Abdoulaye djibril KZA ibnou samara | G29: Dowsaré | H29: Casamance | I29: 77 725 54 26 | J29: 1500 | K29: N/A | L29: 0 | M29: =IF(L29>=0,"A JOUR",(SUM($V29:$Y29)*($M$12))) -> A JOUR | O29: =+IF(L29>0,L29*J29,0) -> 0 | Q29: =SUBTOTAL(9,$AH29:$AQ29) -> 0 | R29: =IF(L29>=0,"A JOUR",($L29*($J29)+N29+O29+$M29)) -> A JOUR | S29: x | T29: x | U29: =+IF(L29>0,L29*J29,0) -> 0 | V29: 11 | AH29: =+IF(W29*$J29<0,0,W29*$J29) -> 0 | AI29: =+IF(X29*$J29<0,0,X29*$J29) -> 0 | AJ29: =+IF(Y29*$J29<0,0,Y29*$J29) -> 0 | AK29: =+IF(Z29*$J29<0,0,Z29*$J29) -> 0 | AL29: =+IF(AA29*$J29<0,0,AA29*$J29) -> 0 | AM29: =+IF(AB29*$J29<0,0,AB29*$J29) -> 0 | AN29: =+IF(AC29*$J29<0,0,AC29*$J29) -> 0 | AO29: =+IF(AD29*$J29<0,0,AD29*$J29) -> 0 | ... AQ29: =+IF(AF29*$J29<0,0,AF29*$J29) -> 0
B30: 17 | C30: =CONCATENATE("N°-","00",B30,"-2024") -> N°-0017-2024 | E30: Mr | F30: Abdoulaye ka gallé | G30: Biilaa | H30: Guinée | K30: N/A | L30: VG | M30: =IF(L30>=0,"A JOUR",(SUM($V30:$Y30)*($M$12))) -> A JOUR | Q30: =SUBTOTAL(9,$AH30:$AQ30) -> 0 | R30: =IF(L30>=0,"A JOUR",($L30*($J30)+N30+O30+$M30)) -> A JOUR | V30: VG
B31: 18 | C31: =CONCATENATE("N°-","00",B31,"-2024") -> N°-0018-2024 | D31: 774042497 | E31: Mr | F31: Abdourahmane TRS | G31: Mamasamba | H31: Dakar | I31: 77 404 24 97 | J31: 5000 | K31: 1000 | L31: 0 | M31: =IF(L31>=0,"A JOUR",(SUM($V31:$Y31)*($M$12))) -> A JOUR | O31: =+IF(L31>0,L31*J31,0) -> 0 | Q31: =SUBTOTAL(9,$AH31:$AQ31) -> 50000 | R31: =IF(L31>=0,"A JOUR",($L31*($J31)+N31+O31+$M31)) -> A JOUR | S31: x | T31: x | V31: 1 | W31: 1 | X31: 1 | Y31: 1 | Z31: 1 | AA31: 1 | AB31: 1 | AC31: 1 | AD31: 1 | AE31: 1 | AF31: 1 | AH31: =+IFERROR(IF(W31*$J31<0,0,W31*$J31),0) -> 5000 | AI31: =+IFERROR(IF(X31*$J31<0,0,X31*$J31),0) -> 5000 | AJ31: =+IFERROR(IF(Y31*$J31<0,0,Y31*$J31),0) -> 5000 | AK31: =+IFERROR(IF(Z31*$J31<0,0,Z31*$J31),0) -> 5000 | AL31: =+IFERROR(IF(AA31*$J31<0,0,AA31*$J31),0) -> 5000 | AM31: =+IFERROR(IF(AB31*$J31<0,0,AB31*$J31),0) -> 5000 | AN31: =+IFERROR(IF(AC31*$J31<0,0,AC31*$J31),0) -> 5000 | AO31: =+IFERROR(IF(AD31*$J31<0,0,AD31*$J31),0) -> 5000 | ... AQ31: =+IFERROR(IF(AF31*$J31<0,0,AF31*$J31),0) -> 5000
B32: 19 | C32: =CONCATENATE("N°-","00",B32,"-2024") -> N°-0019-2024 | D32: 774473167 | E32: Koto | F32: Ablaye TSA | G32: Bolorrou | H32: Dakar | I32: 77 447 31 67 | J32: 1500 | K32: 1000 | L32: 0 | M32: =IF(L32>=0,"A JOUR",(SUM($V32:$Y32)*($M$12))) -> A JOUR | O32: =+IF(L32>0,L32*J32,0) -> 0 | Q32: =SUBTOTAL(9,$AH32:$AQ32) -> 15000 | R32: =IF(L32>=0,"A JOUR",($L32*($J32)+N32+O32+$M32)) -> A JOUR | S32: x | T32: x | V32: 1 | W32: 1 | X32: 1 | Y32: 1 | Z32: 1 | AA32: 1 | AB32: 1 | AC32: 1 | AD32: 1 | AE32: 1 | AF32: 1 | AH32: =+IFERROR(IF(W32*$J32<0,0,W32*$J32),0) -> 1500 | AI32: =+IFERROR(IF(X32*$J32<0,0,X32*$J32),0) -> 1500 | AJ32: =+IFERROR(IF(Y32*$J32<0,0,Y32*$J32),0) -> 1500 | AK32: =+IFERROR(IF(Z32*$J32<0,0,Z32*$J32),0) -> 1500 | AL32: =+IFERROR(IF(AA32*$J32<0,0,AA32*$J32),0) -> 1500 | AM32: =+IFERROR(IF(AB32*$J32<0,0,AB32*$J32),0) -> 1500 | AN32: =+IFERROR(IF(AC32*$J32<0,0,AC32*$J32),0) -> 1500 | AO32: =+IFERROR(IF(AD32*$J32<0,0,AD32*$J32),0) -> 1500 | ... AQ32: =+IFERROR(IF(AF32*$J32<0,0,AF32*$J32),0) -> 1500
B33: 20 | C33: =CONCATENATE("N°-","00",B33,"-2024") -> N°-0020-2024 | D33: 777119328 | E33: Kaou | F33: Ahmadou Korka ibn bappa bala | G33: Pétel | H33: Dakar | I33: 777119328 | J33: 1000 | K33: 1000 | L33: =+SUM($V33:$AO33) -> 2990 | M33: =IF(L33>=0,"A JOUR",(SUM($V33:$Y33)*($M$12))) -> A JOUR | O33: 10000 | Q33: =SUBTOTAL(9,$AH33:$AQ33) -> 3000 | R33: =IF(L33>=0,"A JOUR",($L33*($J33)+N33+O33+$M33)) -> A JOUR | T33: x | V33: -6 | W33: 1 | X33: 1 | Y33: 1 | Z33: -1 | AA33: -1 | AB33: -1 | AC33: -1 | AD33: -1 | AE33: -1 | AF33: -1 | AH33: =+IFERROR(IF(W33*$J33<0,0,W33*$J33),0) -> 1000 | AI33: =+IFERROR(IF(X33*$J33<0,0,X33*$J33),0) -> 1000 | AJ33: =+IFERROR(IF(Y33*$J33<0,0,Y33*$J33),0) -> 1000 | AK33: =+IFERROR(IF(Z33*$J33<0,0,Z33*$J33),0) -> 0 | AL33: =+IFERROR(IF(AA33*$J33<0,0,AA33*$J33),0) -> 0 | AM33: =+IFERROR(IF(AB33*$J33<0,0,AB33*$J33),0) -> 0 | AN33: =+IFERROR(IF(AC33*$J33<0,0,AC33*$J33),0) -> 0 | AO33: =+IFERROR(IF(AD33*$J33<0,0,AD33*$J33),0) -> 0 | ... AQ33: =+IFERROR(IF(AF33*$J33<0,0,AF33*$J33),0) -> 0
B34: 21 | C34: =CONCATENATE("N°-","00",B34,"-2024") -> N°-0021-2024 | D34: 783520425 | E34: Mr | F34: Alassana ibn Elhadji M. Woury | G34: Pétel | H34: Dakar | I34: 78 352 04 25 | J34: 1000 | K34: 1000 | L34: 0 | M34: =IF(L34>=0,"A JOUR",(SUM($V34:$Y34)*($M$12))) -> A JOUR | O34: 27500 | Q34: =SUBTOTAL(9,$AH34:$AQ34) -> 7000 | R34: =IF(L34>=0,"A JOUR",($L34*($J34)+N34+O34+$M34)) -> A JOUR | T34: x | U34: Voir les 500 | V34: -9 | W34: NT | X34: NT | Y34: NT | Z34: 1 | AA34: 1 | AB34: 1 | AC34: 1 | AD34: 1 | AE34: 1 | AF34: 1 | AH34: =+IFERROR(IF(W34*$J34<0,0,W34*$J34),0) -> 0 | AI34: =+IFERROR(IF(X34*$J34<0,0,X34*$J34),0) -> 0 | AJ34: =+IFERROR(IF(Y34*$J34<0,0,Y34*$J34),0) -> 0 | AK34: =+IFERROR(IF(Z34*$J34<0,0,Z34*$J34),0) -> 1000 | AL34: =+IFERROR(IF(AA34*$J34<0,0,AA34*$J34),0) -> 1000 | AM34: =+IFERROR(IF(AB34*$J34<0,0,AB34*$J34),0) -> 1000 | AN34: =+IFERROR(IF(AC34*$J34<0,0,AC34*$J34),0) -> 1000 | AO34: =+IFERROR(IF(AD34*$J34<0,0,AD34*$J34),0) -> 1000 | ... AQ34: =+IFERROR(IF(AF34*$J34<0,0,AF34*$J34),0) -> 1000
B35: 22 | C35: =CONCATENATE("N°-","00",B35,"-2024") -> N°-0022-2024 | D35: 767652193 | E35: Mr | F35: Alassana Macoss | G35: Dowsaré | H35: Dakar | I35: 76 765 21 93 | J35: 1000 | K35: 1000 | L35: 0 | M35: =IF(L35>=0,"A JOUR",(SUM($V35:$Y35)*($M$12))) -> A JOUR | O35: =+IF(L35>0,L35*J35,0) -> 0 | Q35: =SUBTOTAL(9,$AH35:$AQ35) -> 0 | R35: =IF(L35>=0,"A JOUR",($L35*($J35)+N35+O35+$M35)) -> A JOUR | S35: x | T35: x | U35: 41000 DÛ | V35: -3 | AH35: =+IF(W35*$J35<0,0,W35*$J35) -> 0 | AI35: =+IF(X35*$J35<0,0,X35*$J35) -> 0 | AJ35: =+IF(Y35*$J35<0,0,Y35*$J35) -> 0 | AK35: =+IF(Z35*$J35<0,0,Z35*$J35) -> 0 | AL35: =+IF(AA35*$J35<0,0,AA35*$J35) -> 0 | AM35: =+IF(AB35*$J35<0,0,AB35*$J35) -> 0 | AN35: =+IF(AC35*$J35<0,0,AC35*$J35) -> 0 | AO35: =+IF(AD35*$J35<0,0,AD35*$J35) -> 0 | ... AQ35: =+IF(AF35*$J35<0,0,AF35*$J35) -> 0
B36: 23 | C36: =CONCATENATE("N°-","00",B36,"-2024") -> N°-0023-2024 | D36: 783520425 | E36: Mr | F36: Alousseynou ibn Elhadji M. Woury | G36: Pétel | H36: Dakar | I36: 78 352 04 25 | J36: 1000 | K36: 1000 | L36: 0 | M36: =IF(L36>=0,"A JOUR",(SUM($V36:$Y36)*($M$12))) -> A JOUR | O36: =+IF(L36>0,L36*J36,0) -> 0 | Q36: =SUBTOTAL(9,$AH36:$AQ36) -> 7000 | R36: =IF(L36>=0,"A JOUR",($L36*($J36)+N36+O36+$M36)) -> A JOUR | T36: x | V36: NT | W36: NT | X36: NT | Y36: NT | Z36: 1 | AA36: 1 | AB36: 1 | AC36: 1 | AD36: 1 | AE36: 1 | AF36: 1 | AH36: =+IFERROR(IF(W36*$J36<0,0,W36*$J36),0) -> 0 | AI36: =+IFERROR(IF(X36*$J36<0,0,X36*$J36),0) -> 0 | AJ36: =+IFERROR(IF(Y36*$J36<0,0,Y36*$J36),0) -> 0 | AK36: =+IFERROR(IF(Z36*$J36<0,0,Z36*$J36),0) -> 1000 | AL36: =+IFERROR(IF(AA36*$J36<0,0,AA36*$J36),0) -> 1000 | AM36: =+IFERROR(IF(AB36*$J36<0,0,AB36*$J36),0) -> 1000 | AN36: =+IFERROR(IF(AC36*$J36<0,0,AC36*$J36),0) -> 1000 | AO36: =+IFERROR(IF(AD36*$J36<0,0,AD36*$J36),0) -> 1000 | ... AQ36: =+IFERROR(IF(AF36*$J36<0,0,AF36*$J36),0) -> 1000
B37: 24 | C37: =CONCATENATE("N°-","00",B37,"-2024") -> N°-0024-2024 | E37: Mr | F37: Alousseynou Pecosse | G37: Dowsaré | H37: Guinée | K37: N/A | L37: VG | M37: =IF(L37>=0,"A JOUR",(SUM($V37:$Y37)*($M$12))) -> A JOUR | Q37: =SUBTOTAL(9,$AH37:$AQ37) -> 0 | R37: =IF(L37>=0,"A JOUR",($L37*($J37)+N37+O37+$M37)) -> A JOUR | S37: x | V37: VG
B38: 25 | C38: =CONCATENATE("N°-","00",B38,"-2024") -> N°-0025-2024 | E38: Mr | F38: Alpha (France) | G38: Dieydiyabhe | H38: France | K38: 1000 | M38: =IF(L38>=0,"A JOUR",(SUM($V38:$Y38)*($M$12))) -> A JOUR | O38: =+IF(L38>0,L38*J38,0) -> 0 | Q38: =SUBTOTAL(9,$AH38:$AQ38) -> 0 | R38: =IF(L38>=0,"A JOUR",($L38*($J38)+N38+O38+$M38)) -> A JOUR
B39: 26 | C39: =CONCATENATE("N°-","00",B39,"-2024") -> N°-0026-2024 | D39: 772289487 | E39: Mr | F39: Alpha amadou ibn bappa bala | G39: Pétel | H39: Dakar | I39: 77 228 94 87 | J39: 1000 | K39: 1000 | L39: 0 | M39: =IF(L39>=0,"A JOUR",(SUM($V39:$Y39)*($M$12))) -> A JOUR | O39: =+IF(L39>0,L39*J39,0) -> 0 | Q39: =SUBTOTAL(9,$AH39:$AQ39) -> 10000 | R39: =IF(L39>=0,"A JOUR",($L39*($J39)+N39+O39+$M39)) -> A JOUR | S39: x | T39: x | V39: 1 | W39: 1 | X39: 1 | Y39: 1 | Z39: 1 | AA39: 1 | AB39: 1 | AC39: 1 | AD39: 1 | AE39: 1 | AF39: 1 | AH39: =+IFERROR(IF(W39*$J39<0,0,W39*$J39),0) -> 1000 | AI39: =+IFERROR(IF(X39*$J39<0,0,X39*$J39),0) -> 1000 | AJ39: =+IFERROR(IF(Y39*$J39<0,0,Y39*$J39),0) -> 1000 | AK39: =+IFERROR(IF(Z39*$J39<0,0,Z39*$J39),0) -> 1000 | AL39: =+IFERROR(IF(AA39*$J39<0,0,AA39*$J39),0) -> 1000 | AM39: =+IFERROR(IF(AB39*$J39<0,0,AB39*$J39),0) -> 1000 | AN39: =+IFERROR(IF(AC39*$J39<0,0,AC39*$J39),0) -> 1000 | AO39: =+IFERROR(IF(AD39*$J39<0,0,AD39*$J39),0) -> 1000 | ... AQ39: =+IFERROR(IF(AF39*$J39<0,0,AF39*$J39),0) -> 1000
B40: 27 | C40: =CONCATENATE("N°-","00",B40,"-2024") -> N°-0027-2024 | D40: 781261182 | E40: Mr | F40: Alpha Amirou ibn Elhadji Ibrahima | G40: Pétel | H40: Dakar | I40: 78 126 11 82 | J40: 1000 | K40: 1000 | L40: =+IF(SUM($V40:$AO40)>0,0,SUM($V40:$AO40)) -> -16 | M40: =IF(L40>=0,"A JOUR",(SUM($V40:$Y40)*($M$12))) -> -18000 | O40: =+IF(L40>0,L40*J40,0) -> 0 | Q40: =SUBTOTAL(9,$AH40:$AQ40) -> 0 | R40: =IF(L40>=0,"A JOUR",($L40*($J40)+N40+O40+$M40)) -> -34000 | T40: x | U40: 101000 | V40: -6 | W40: -1 | X40: -1 | Y40: -1 | Z40: -1 | AA40: -1 | AB40: -1 | AC40: -1 | AD40: -1 | AE40: -1 | AF40: -1 | AH40: =+IFERROR(IF(W40*$J40<0,0,W40*$J40),0) -> 0 | AI40: =+IFERROR(IF(X40*$J40<0,0,X40*$J40),0) -> 0 | AJ40: =+IFERROR(IF(Y40*$J40<0,0,Y40*$J40),0) -> 0 | AK40: =+IFERROR(IF(Z40*$J40<0,0,Z40*$J40),0) -> 0 | AL40: =+IFERROR(IF(AA40*$J40<0,0,AA40*$J40),0) -> 0 | AM40: =+IFERROR(IF(AB40*$J40<0,0,AB40*$J40),0) -> 0 | AN40: =+IFERROR(IF(AC40*$J40<0,0,AC40*$J40),0) -> 0 | AO40: =+IFERROR(IF(AD40*$J40<0,0,AD40*$J40),0) -> 0 | ... AQ40: =+IFERROR(IF(AF40*$J40<0,0,AF40*$J40),0) -> 0
B41: 28 | C41: =CONCATENATE("N°-","00",B41,"-2024") -> N°-0028-2024 | D41: 772202046 | E41: Koto | F41: alpha KZA ibnou samara | G41: Dowsaré | H41: Casamance | I41: 77 220 20 46 | J41: 2000 | K41: 1000 | L41: 0 | M41: =IF(L41>=0,"A JOUR",(SUM($V41:$Y41)*($M$12))) -> A JOUR | O41: =+IF(L41>0,L41*J41,0) -> 0 | Q41: =SUBTOTAL(9,$AH41:$AQ41) -> 0 | R41: =IF(L41>=0,"A JOUR",($L41*($J41)+N41+O41+$M41)) -> A JOUR | S41: x | T41: x | V41: 11 | AH41: =+IF(W41*$J41<0,0,W41*$J41) -> 0 | AI41: =+IF(X41*$J41<0,0,X41*$J41) -> 0 | AJ41: =+IF(Y41*$J41<0,0,Y41*$J41) -> 0 | AK41: =+IF(Z41*$J41<0,0,Z41*$J41) -> 0 | AL41: =+IF(AA41*$J41<0,0,AA41*$J41) -> 0 | AM41: =+IF(AB41*$J41<0,0,AB41*$J41) -> 0 | AN41: =+IF(AC41*$J41<0,0,AC41*$J41) -> 0 | AO41: =+IF(AD41*$J41<0,0,AD41*$J41) -> 0 | ... AQ41: =+IF(AF41*$J41<0,0,AF41*$J41) -> 0
B42: 29 | C42: =CONCATENATE("N°-","00",B42,"-2024") -> N°-0029-2024 | D42: 781346347 | E42: Bappa | F42: Alpha oumar | G42: Mamasamba | H42: Dakar | I42: 78 134 63 47 | J42: 2000 | K42: 1000 | L42: =4-4 -> 0 | M42: =IF(L42>=0,"A JOUR",(SUM($V42:$Y42)*($M$12))) -> A JOUR | O42: =+IF(L42>0,L42*J42,0) -> 0 | Q42: =SUBTOTAL(9,$AH42:$AQ42) -> 20000 | R42: =IF(L42>=0,"A JOUR",($L42*($J42)+N42+O42+$M42)) -> A JOUR | S42: x | T42: x | V42: 1 | W42: 1 | X42: 1 | Y42: 1 | Z42: 1 | AA42: 1 | AB42: 1 | AC42: 1 | AD42: 1 | AE42: 1 | AF42: 1 | AH42: =+IFERROR(IF(W42*$J42<0,0,W42*$J42),0) -> 2000 | AI42: =+IFERROR(IF(X42*$J42<0,0,X42*$J42),0) -> 2000 | AJ42: =+IFERROR(IF(Y42*$J42<0,0,Y42*$J42),0) -> 2000 | AK42: =+IFERROR(IF(Z42*$J42<0,0,Z42*$J42),0) -> 2000 | AL42: =+IFERROR(IF(AA42*$J42<0,0,AA42*$J42),0) -> 2000 | AM42: =+IFERROR(IF(AB42*$J42<0,0,AB42*$J42),0) -> 2000 | AN42: =+IFERROR(IF(AC42*$J42<0,0,AC42*$J42),0) -> 2000 | AO42: =+IFERROR(IF(AD42*$J42<0,0,AD42*$J42),0) -> 2000 | ... AQ42: =+IFERROR(IF(AF42*$J42<0,0,AF42*$J42),0) -> 2000
B43: 30 | C43: =CONCATENATE("N°-","00",B43,"-2024") -> N°-0030-2024 | D43: xxxxxxxx | E43: Koto | F43: Alpha oumar gabonais | G43: Dowsaré | H43: Togo | I43: xxxxxxxx | J43: 4000 | K43: 1000 | M43: =IF(L43>=0,"A JOUR",(SUM($V43:$Y43)*($M$12))) -> A JOUR | Q43: =SUBTOTAL(9,$AH43:$AQ43) -> 0 | R43: =IF(L43>=0,"A JOUR",($L43*($J43)+N43+O43+$M43)) -> A JOUR | S43: x | T43: x
B44: 31 | C44: =CONCATENATE("N°-","00",B44,"-2024") -> N°-0031-2024 | D44: +24102253222 | E44: Koto | F44: Alpha oumar ibn karamoko Daouda | G44: Pétel | H44: Gabon | I44: +241 02 25 32 22 | J44: 5000 | K44: N/A | M44: =IF(L44>=0,"A JOUR",(SUM($V44:$Y44)*($M$12))) -> A JOUR | Q44: =SUBTOTAL(9,$AH44:$AQ44) -> 0 | R44: =IF(L44>=0,"A JOUR",($L44*($J44)+N44+O44+$M44)) -> A JOUR | T44: x
B45: 32 | C45: =CONCATENATE("N°-","00",B45,"-2024") -> N°-0032-2024 | D45: 774997775 | E45: Koto | F45: Alpha Oumar togolais | G45: Dowsaré | H45: Dakar | I45: 77 499 77 75 | J45: 2000 | K45: 1000 | L45: 0 | M45: =IF(L45>=0,"A JOUR",(SUM($V45:$Y45)*($M$12))) -> A JOUR | O45: =+IF(L45>0,L45*J45,0) -> 0 | Q45: =SUBTOTAL(9,$AH45:$AQ45) -> 2000 | R45: =IF(L45>=0,"A JOUR",($L45*($J45)+N45+O45+$M45)) -> A JOUR | S45: x | T45: x | V45: 2 | W45: -1 | X45: -1 | Y45: 1 | Z45: VG | AA45: VG | AB45: VG | AC45: VG | AD45: VG | AE45: VG | AF45: VG | AH45: =+IFERROR(IF(W45*$J45<0,0,W45*$J45),0) -> 0 | AI45: =+IFERROR(IF(X45*$J45<0,0,X45*$J45),0) -> 0 | AJ45: =+IFERROR(IF(Y45*$J45<0,0,Y45*$J45),0) -> 2000 | AK45: =+IFERROR(IF(Z45*$J45<0,0,Z45*$J45),0) -> 0 | AL45: =+IFERROR(IF(AA45*$J45<0,0,AA45*$J45),0) -> 0 | AM45: =+IFERROR(IF(AB45*$J45<0,0,AB45*$J45),0) -> 0 | AN45: =+IFERROR(IF(AC45*$J45<0,0,AC45*$J45),0) -> 0 | AO45: =+IFERROR(IF(AD45*$J45<0,0,AD45*$J45),0) -> 0 | ... AQ45: =+IFERROR(IF(AF45*$J45<0,0,AF45*$J45),0) -> 0
B46: 33 | C46: =CONCATENATE("N°-","00",B46,"-2024") -> N°-0033-2024 | E46: Mr | F46: Alpha Saliou ibn Elhadji M. Woury | G46: Pétel | H46: Guinée | K46: 1000 | L46: VG | M46: =IF(L46>=0,"A JOUR",(SUM($V46:$Y46)*($M$12))) -> A JOUR | Q46: =SUBTOTAL(9,$AH46:$AQ46) -> 0 | R46: =IF(L46>=0,"A JOUR",($L46*($J46)+N46+O46+$M46)) -> A JOUR | U46: VG | V46: VG
B47: 34 | C47: =CONCATENATE("N°-","00",B47,"-2024") -> N°-0034-2024 | D47: 776709584 | E47: Oustaz | F47: Amadou | G47: Bowell | H47: Guinée | I47: 77 670 95 84 | J47: 2500 | K47: 1000 | L47: 0 | M47: =IF(L47>=0,"A JOUR",(SUM($V47:$Y47)*($M$12))) -> A JOUR | O47: =+IF(L47>0,L47*J47,0) -> 0 | Q47: =SUBTOTAL(9,$AH47:$AQ47) -> 0 | R47: =IF(L47>=0,"A JOUR",($L47*($J47)+N47+O47+$M47)) -> A JOUR | S47: x | T47: x | U47: NT | V47: VG | W47: VG | X47: VG | Y47: VG | Z47: VG | AA47: VG | AB47: VG | AC47: VG | AD47: VG | AE47: VG | AF47: VG | AH47: =+IFERROR(IF(W47*$J47<0,0,W47*$J47),0) -> 0 | AI47: =+IFERROR(IF(X47*$J47<0,0,X47*$J47),0) -> 0 | AJ47: =+IFERROR(IF(Y47*$J47<0,0,Y47*$J47),0) -> 0 | AK47: =+IFERROR(IF(Z47*$J47<0,0,Z47*$J47),0) -> 0 | AL47: =+IFERROR(IF(AA47*$J47<0,0,AA47*$J47),0) -> 0 | AM47: =+IFERROR(IF(AB47*$J47<0,0,AB47*$J47),0) -> 0 | AN47: =+IFERROR(IF(AC47*$J47<0,0,AC47*$J47),0) -> 0 | AO47: =+IFERROR(IF(AD47*$J47<0,0,AD47*$J47),0) -> 0 | ... AQ47: =+IFERROR(IF(AF47*$J47<0,0,AF47*$J47),0) -> 0
B48: 35 | C48: =CONCATENATE("N°-","00",B48,"-2024") -> N°-0035-2024 | D48: 776623868 | E48: Mr | F48: Amadou bobo (mariste) | G48: Dowsaré | H48: Dakar | I48: 77 662 38 68 | J48: 2000 | K48: 1000 | L48: 0 | M48: =IF(L48>=0,"A JOUR",(SUM($V48:$Y48)*($M$12))) -> A JOUR | O48: =+IF(L48>0,L48*J48,0) -> 0 | Q48: =SUBTOTAL(9,$AH48:$AQ48) -> 20000 | R48: =IF(L48>=0,"A JOUR",($L48*($J48)+N48+O48+$M48)) -> A JOUR | S48: x | T48: x | V48: 1 | W48: 1 | X48: 1 | Y48: 1 | Z48: 1 | AA48: 1 | AB48: 1 | AC48: 1 | AD48: 1 | AE48: 1 | AF48: 1 | AH48: =+IFERROR(IF(W48*$J48<0,0,W48*$J48),0) -> 2000 | AI48: =+IFERROR(IF(X48*$J48<0,0,X48*$J48),0) -> 2000 | AJ48: =+IFERROR(IF(Y48*$J48<0,0,Y48*$J48),0) -> 2000 | AK48: =+IFERROR(IF(Z48*$J48<0,0,Z48*$J48),0) -> 2000 | AL48: =+IFERROR(IF(AA48*$J48<0,0,AA48*$J48),0) -> 2000 | AM48: =+IFERROR(IF(AB48*$J48<0,0,AB48*$J48),0) -> 2000 | AN48: =+IFERROR(IF(AC48*$J48<0,0,AC48*$J48),0) -> 2000 | AO48: =+IFERROR(IF(AD48*$J48<0,0,AD48*$J48),0) -> 2000 | ... AQ48: =+IFERROR(IF(AF48*$J48<0,0,AF48*$J48),0) -> 2000
B49: 36 | C49: =CONCATENATE("N°-","00",B49,"-2024") -> N°-0036-2024 | D49: 774272026 | E49: Koto | F49: Amadou bobo N°1 | G49: Dowsaré | H49: Dakar | I49: 77 427 20 26 | J49: 2000 | K49: 1000 | L49: 0 | M49: =IF(L49>=0,"A JOUR",(SUM($V49:$Y49)*($M$12))) -> A JOUR | O49: =+IF(L49>0,L49*J49,0) -> 0 | Q49: =SUBTOTAL(9,$AH49:$AQ49) -> 12500 | R49: =IF(L49>=0,"A JOUR",($L49*($J49)+N49+O49+$M49)) -> A JOUR | S49: x | T49: x | U49: 7500DETTE | V49: 1 | W49: -1 | X49: -1 | Y49: -1 | Z49: 0.25 | AA49: 1 | AB49: 1 | AC49: 1 | AD49: 1 | AE49: 1 | AF49: 1 | AH49: =+IFERROR(IF(W49*$J49<0,0,W49*$J49),0) -> 0 | AI49: =+IFERROR(IF(X49*$J49<0,0,X49*$J49),0) -> 0 | AJ49: =+IFERROR(IF(Y49*$J49<0,0,Y49*$J49),0) -> 0 | AK49: =+IFERROR(IF(Z49*$J49<0,0,Z49*$J49),0) -> 500 | AL49: =+IFERROR(IF(AA49*$J49<0,0,AA49*$J49),0) -> 2000 | AM49: =+IFERROR(IF(AB49*$J49<0,0,AB49*$J49),0) -> 2000 | AN49: =+IFERROR(IF(AC49*$J49<0,0,AC49*$J49),0) -> 2000 | AO49: =+IFERROR(IF(AD49*$J49<0,0,AD49*$J49),0) -> 2000 | ... AQ49: =+IFERROR(IF(AF49*$J49<0,0,AF49*$J49),0) -> 2000
B50: 37 | C50: =CONCATENATE("N°-","00",B50,"-2024") -> N°-0037-2024 | D50: xxxxxxxx | E50: Mr | F50: Amadou diogo | G50: Gobihi | H50: Guinée | I50: xxxxxxxx | J50: 2000 | K50: 1000 | M50: =IF(L50>=0,"A JOUR",(SUM($V50:$Y50)*($M$12))) -> A JOUR | Q50: =SUBTOTAL(9,$AH50:$AQ50) -> 0 | R50: =IF(L50>=0,"A JOUR",($L50*($J50)+N50+O50+$M50)) -> A JOUR | T50: x | U50: VG
B51: 38 | C51: =CONCATENATE("N°-","00",B51,"-2024") -> N°-0038-2024 | D51: 775218573 | E51: Mr | F51: Amadou Djoulde - PR | G51: Dowsaré | H51: Dakar | I51: 77 521 85 73 | J51: 3000 | K51: 1000 | L51: 0 | M51: =IF(L51>=0,"A JOUR",(SUM($V51:$Y51)*($M$12))) -> A JOUR | O51: =+IF(L51>0,L51*J51,0) -> 0 | Q51: =SUBTOTAL(9,$AH51:$AQ51) -> 9000 | R51: =IF(L51>=0,"A JOUR",($L51*($J51)+N51+O51+$M51)) -> A JOUR | S51: x | T51: x | V51: 1 | W51: 1 | X51: 1 | Y51: 1 | Z51: VG | AA51: VG | AB51: VG | AC51: VG | AD51: VG | AE51: VG | AF51: VG | AH51: =+IFERROR(IF(W51*$J51<0,0,W51*$J51),0) -> 3000 | AI51: =+IFERROR(IF(X51*$J51<0,0,X51*$J51),0) -> 3000 | AJ51: =+IFERROR(IF(Y51*$J51<0,0,Y51*$J51),0) -> 3000 | AK51: =+IFERROR(IF(Z51*$J51<0,0,Z51*$J51),0) -> 0 | AL51: =+IFERROR(IF(AA51*$J51<0,0,AA51*$J51),0) -> 0 | AM51: =+IFERROR(IF(AB51*$J51<0,0,AB51*$J51),0) -> 0 | AN51: =+IFERROR(IF(AC51*$J51<0,0,AC51*$J51),0) -> 0 | AO51: =+IFERROR(IF(AD51*$J51<0,0,AD51*$J51),0) -> 0 | ... AQ51: =+IFERROR(IF(AF51*$J51<0,0,AF51*$J51),0) -> 0
B52: 39 | C52: =CONCATENATE("N°-","00",B52,"-2024") -> N°-0039-2024 | D52: 778550234 | E52: Koto | F52: Amadou korka CC | G52: Diabbhéhi | H52: Dakar | I52: 77 855 02 34 | J52: 2000 | K52: 1000 | L52: 0 | M52: =IF(L52>=0,"A JOUR",(SUM($V52:$Y52)*($M$12))) -> A JOUR | O52: =+IF(L52>0,L52*J52,0) -> 0 | Q52: =SUBTOTAL(9,$AH52:$AQ52) -> 13000 | R52: =IF(L52>=0,"A JOUR",($L52*($J52)+N52+O52+$M52)) -> A JOUR | S52: x | T52: x | V52: 1 | W52: 1 | X52: 1 | Y52: 1 | Z52: 0.5 | AA52: 0.5 | AB52: 0.5 | AC52: 0.5 | AD52: 0.5 | AE52: 0.5 | AF52: 0.5 | AH52: =+IFERROR(IF(W52*$J52<0,0,W52*$J52),0) -> 2000 | AI52: =+IFERROR(IF(X52*$J52<0,0,X52*$J52),0) -> 2000 | AJ52: =+IFERROR(IF(Y52*$J52<0,0,Y52*$J52),0) -> 2000 | AK52: =+IFERROR(IF(Z52*$J52<0,0,Z52*$J52),0) -> 1000 | AL52: =+IFERROR(IF(AA52*$J52<0,0,AA52*$J52),0) -> 1000 | AM52: =+IFERROR(IF(AB52*$J52<0,0,AB52*$J52),0) -> 1000 | AN52: =+IFERROR(IF(AC52*$J52<0,0,AC52*$J52),0) -> 1000 | AO52: =+IFERROR(IF(AD52*$J52<0,0,AD52*$J52),0) -> 1000 | ... AQ52: =+IFERROR(IF(AF52*$J52<0,0,AF52*$J52),0) -> 1000
B53: 40 | C53: =CONCATENATE("N°-","00",B53,"-2024") -> N°-0040-2024 | D53: 778151869 | E53: Koto | F53: Amadou korka | G53: Biilaa | H53: Dakar | I53: 77 815 18 69 | J53: 1000 | K53: 1000 | L53: 0 | M53: =IF(L53>=0,"A JOUR",(SUM($V53:$Y53)*($M$12))) -> A JOUR | O53: =+IF(L53>0,L53*J53,0) -> 0 | Q53: =SUBTOTAL(9,$AH53:$AQ53) -> 10000 | R53: =IF(L53>=0,"A JOUR",($L53*($J53)+N53+O53+$M53)) -> A JOUR | S53: x | T53: x | V53: 1 | W53: 1 | X53: 1 | Y53: 1 | Z53: 1 | AA53: 1 | AB53: 1 | AC53: 1 | AD53: 1 | AE53: 1 | AF53: 1 | AH53: =+IFERROR(IF(W53*$J53<0,0,W53*$J53),0) -> 1000 | AI53: =+IFERROR(IF(X53*$J53<0,0,X53*$J53),0) -> 1000 | AJ53: =+IFERROR(IF(Y53*$J53<0,0,Y53*$J53),0) -> 1000 | AK53: =+IFERROR(IF(Z53*$J53<0,0,Z53*$J53),0) -> 1000 | AL53: =+IFERROR(IF(AA53*$J53<0,0,AA53*$J53),0) -> 1000 | AM53: =+IFERROR(IF(AB53*$J53<0,0,AB53*$J53),0) -> 1000 | AN53: =+IFERROR(IF(AC53*$J53<0,0,AC53*$J53),0) -> 1000 | AO53: =+IFERROR(IF(AD53*$J53<0,0,AD53*$J53),0) -> 1000 | ... AQ53: =+IFERROR(IF(AF53*$J53<0,0,AF53*$J53),0) -> 1000
B54: 41 | C54: =CONCATENATE("N°-","00",B54,"-2024") -> N°-0041-2024 | D54: 786333092 | E54: Mr | F54: Amadou korka | G54: Porétély | H54: Dakar | I54: 78 633 30 92 | J54: 1000 | K54: N/A | L54: =+SUM($V54:$AO54) -> -33 | M54: =IF(L54>=0,"A JOUR",(SUM($V54:$Y54)*($M$12))) -> -52000 | Q54: =SUBTOTAL(9,$AH54:$AQ54) -> 0 | R54: =IF(L54>=0,"A JOUR",($L54*($J54)+N54+O54+$M54)) -> -85000 | S54: x | T54: x | V54: -23 | W54: -1 | X54: -1 | Y54: -1 | Z54: -1 | AA54: -1 | AB54: -1 | AC54: -1 | AD54: -1 | AE54: -1 | AF54: -1 | AH54: =+IFERROR(IF(W54*$J54<0,0,W54*$J54),0) -> 0 | AI54: =+IFERROR(IF(X54*$J54<0,0,X54*$J54),0) -> 0 | AJ54: =+IFERROR(IF(Y54*$J54<0,0,Y54*$J54),0) -> 0 | AK54: =+IFERROR(IF(Z54*$J54<0,0,Z54*$J54),0) -> 0 | AL54: =+IFERROR(IF(AA54*$J54<0,0,AA54*$J54),0) -> 0 | AM54: =+IFERROR(IF(AB54*$J54<0,0,AB54*$J54),0) -> 0 | AN54: =+IFERROR(IF(AC54*$J54<0,0,AC54*$J54),0) -> 0 | AO54: =+IFERROR(IF(AD54*$J54<0,0,AD54*$J54),0) -> 0 | ... AQ54: =+IFERROR(IF(AF54*$J54<0,0,AF54*$J54),0) -> 0
B55: 42 | C55: =CONCATENATE("N°-","00",B55,"-2024") -> N°-0042-2024 | D55: 778021767 | E55: Mr | F55: Amadou mouctar | G55: Yayemadou | H55: Dakar | I55: 77 802 17 67 | J55: 2000 | K55: N/A | L55: =+SUM($V55:$AO55) -> -57 | M55: =IF(L55>=0,"A JOUR",(SUM($V55:$Y55)*($M$12))) -> -100000 | Q55: =SUBTOTAL(9,$AH55:$AQ55) -> 0 | R55: =IF(L55>=0,"A JOUR",($L55*($J55)+N55+O55+$M55)) -> -214000 | S55: x | T55: x | V55: -47 | W55: -1 | X55: -1 | Y55: -1 | Z55: -1 | AA55: -1 | AB55: -1 | AC55: -1 | AD55: -1 | AE55: -1 | AF55: -1 | AH55: =+IFERROR(IF(W55*$J55<0,0,W55*$J55),0) -> 0 | AI55: =+IFERROR(IF(X55*$J55<0,0,X55*$J55),0) -> 0 | AJ55: =+IFERROR(IF(Y55*$J55<0,0,Y55*$J55),0) -> 0 | AK55: =+IFERROR(IF(Z55*$J55<0,0,Z55*$J55),0) -> 0 | AL55: =+IFERROR(IF(AA55*$J55<0,0,AA55*$J55),0) -> 0 | AM55: =+IFERROR(IF(AB55*$J55<0,0,AB55*$J55),0) -> 0 | AN55: =+IFERROR(IF(AC55*$J55<0,0,AC55*$J55),0) -> 0 | AO55: =+IFERROR(IF(AD55*$J55<0,0,AD55*$J55),0) -> 0 | ... AQ55: =+IFERROR(IF(AF55*$J55<0,0,AF55*$J55),0) -> 0
B56: 43 | C56: =CONCATENATE("N°-","00",B56,"-2024") -> N°-0043-2024 | D56: 771009642 | E56: Mr | F56: Amadou mouctar ibn Elhadji Ibrahima | G56: Pétel | H56: Dakar | I56: 77 100 96 42 | J56: 1000 | K56: N/A | L56: =+SUM($V56:$AO56) -> -57 | M56: =IF(L56>=0,"A JOUR",(SUM($V56:$Y56)*($M$12))) -> -100000 | Q56: =SUBTOTAL(9,$AH56:$AQ56) -> 0 | R56: =IF(L56>=0,"A JOUR",($L56*($J56)+N56+O56+$M56)) -> -157000 | T56: x | U56: EXCLUS + 50K | V56: -47 | W56: -1 | X56: -1 | Y56: -1 | Z56: -1 | AA56: -1 | AB56: -1 | AC56: -1 | AD56: -1 | AE56: -1 | AF56: -1 | AH56: =+IFERROR(IF(W56*$J56<0,0,W56*$J56),0) -> 0 | AI56: =+IFERROR(IF(X56*$J56<0,0,X56*$J56),0) -> 0 | AJ56: =+IFERROR(IF(Y56*$J56<0,0,Y56*$J56),0) -> 0 | AK56: =+IFERROR(IF(Z56*$J56<0,0,Z56*$J56),0) -> 0 | AL56: =+IFERROR(IF(AA56*$J56<0,0,AA56*$J56),0) -> 0 | AM56: =+IFERROR(IF(AB56*$J56<0,0,AB56*$J56),0) -> 0 | AN56: =+IFERROR(IF(AC56*$J56<0,0,AC56*$J56),0) -> 0 | AO56: =+IFERROR(IF(AD56*$J56<0,0,AD56*$J56),0) -> 0 | ... AQ56: =+IFERROR(IF(AF56*$J56<0,0,AF56*$J56),0) -> 0
B57: 44 | C57: =CONCATENATE("N°-","00",B57,"-2024") -> N°-0044-2024 | D57: 778637835 | E57: Mr | F57: Amadou tanou | G57: Dieydiyabhe | H57: Dakar | I57: 77 863 78 35 | J57: 1000 | K57: 1000 | L57: 0 | M57: =IF(L57>=0,"A JOUR",(SUM($V57:$Y57)*($M$12))) -> A JOUR | O57: =+IF(L57>0,L57*J57,0) -> 0 | Q57: =SUBTOTAL(9,$AH57:$AQ57) -> 3000 | R57: =IF(L57>=0,"A JOUR",($L57*($J57)+N57+O57+$M57)) -> A JOUR | S57: x | T57: x | V57: 1 | W57: 1 | X57: 1 | Y57: 1 | Z57: NT | AA57: NT | AB57: NT | AC57: NT | AD57: NT | AE57: NT | AF57: NT | AH57: =+IFERROR(IF(W57*$J57<0,0,W57*$J57),0) -> 1000 | AI57: =+IFERROR(IF(X57*$J57<0,0,X57*$J57),0) -> 1000 | AJ57: =+IFERROR(IF(Y57*$J57<0,0,Y57*$J57),0) -> 1000 | AK57: =+IFERROR(IF(Z57*$J57<0,0,Z57*$J57),0) -> 0 | AL57: =+IFERROR(IF(AA57*$J57<0,0,AA57*$J57),0) -> 0 | AM57: =+IFERROR(IF(AB57*$J57<0,0,AB57*$J57),0) -> 0 | AN57: =+IFERROR(IF(AC57*$J57<0,0,AC57*$J57),0) -> 0 | AO57: =+IFERROR(IF(AD57*$J57<0,0,AD57*$J57),0) -> 0 | ... AQ57: =+IFERROR(IF(AF57*$J57<0,0,AF57*$J57),0) -> 0
B58: 45 | C58: =CONCATENATE("N°-","00",B58,"-2024") -> N°-0045-2024 | D58: 773499877 | E58: Mody | F58: Amadou TC | G58: Mamasamba | H58: Dakar | I58: 77 349 98 77 | J58: 2000 | K58: 1000 | L58: 0 | M58: =IF(L58>=0,"A JOUR",(SUM($V58:$Y58)*($M$12))) -> A JOUR | O58: =+IF(L58>0,L58*J58,0) -> 0 | Q58: =SUBTOTAL(9,$AH58:$AQ58) -> 8000 | R58: =IF(L58>=0,"A JOUR",($L58*($J58)+N58+O58+$M58)) -> A JOUR | S58: x | T58: x | V58: VG | W58: VG | X58: VG | Y58: VG | Z58: VG | AA58: VG | AB58: VG | AC58: 1 | AD58: 1 | AE58: 1 | AF58: 1 | AH58: =+IFERROR(IF(W58*$J58<0,0,W58*$J58),0) -> 0 | AI58: =+IFERROR(IF(X58*$J58<0,0,X58*$J58),0) -> 0 | AJ58: =+IFERROR(IF(Y58*$J58<0,0,Y58*$J58),0) -> 0 | AK58: =+IFERROR(IF(Z58*$J58<0,0,Z58*$J58),0) -> 0 | AL58: =+IFERROR(IF(AA58*$J58<0,0,AA58*$J58),0) -> 0 | AM58: =+IFERROR(IF(AB58*$J58<0,0,AB58*$J58),0) -> 0 | AN58: =+IFERROR(IF(AC58*$J58<0,0,AC58*$J58),0) -> 2000 | AO58: =+IFERROR(IF(AD58*$J58<0,0,AD58*$J58),0) -> 2000 | ... AQ58: =+IFERROR(IF(AF58*$J58<0,0,AF58*$J58),0) -> 2000
B59: 46 | C59: =CONCATENATE("N°-","00",B59,"-2024") -> N°-0046-2024 | D59: xxxxxxxx | E59: Mr | F59: Amadou Woury | G59: Ka missidé | H59: Côte d'ivoire | I59: xxxxxxxx | J59: 2000 | K59: 1000 | L59: 0 | M59: =IF(L59>=0,"A JOUR",(SUM($V59:$Y59)*($M$12))) -> A JOUR | O59: =+IF(L59>0,L59*J59,0) -> 0 | Q59: =SUBTOTAL(9,$AH59:$AQ59) -> 0 | R59: =IF(L59>=0,"A JOUR",($L59*($J59)+N59+O59+$M59)) -> A JOUR | T59: x
B60: 47 | C60: =CONCATENATE("N°-","00",B60,"-2024") -> N°-0047-2024 | D60: 772392440 | E60: Mr | F60: Amadou Woury boukary | G60: Yayemadou | H60: Dakar | I60: 77 239 24 40 | J60: 2000 | K60: N/A | L60: =+SUM($V60:$AO60) -> -52 | M60: =IF(L60>=0,"A JOUR",(SUM($V60:$Y60)*($M$12))) -> -90000 | Q60: =SUBTOTAL(9,$AH60:$AQ60) -> 0 | R60: =IF(L60>=0,"A JOUR",($L60*($J60)+N60+O60+$M60)) -> -194000 | T60: x | V60: -42 | W60: -1 | X60: -1 | Y60: -1 | Z60: -1 | AA60: -1 | AB60: -1 | AC60: -1 | AD60: -1 | AE60: -1 | AF60: -1 | AH60: =+IFERROR(IF(W60*$J60<0,0,W60*$J60),0) -> 0 | AI60: =+IFERROR(IF(X60*$J60<0,0,X60*$J60),0) -> 0 | AJ60: =+IFERROR(IF(Y60*$J60<0,0,Y60*$J60),0) -> 0 | AK60: =+IFERROR(IF(Z60*$J60<0,0,Z60*$J60),0) -> 0 | AL60: =+IFERROR(IF(AA60*$J60<0,0,AA60*$J60),0) -> 0 | AM60: =+IFERROR(IF(AB60*$J60<0,0,AB60*$J60),0) -> 0 | AN60: =+IFERROR(IF(AC60*$J60<0,0,AC60*$J60),0) -> 0 | AO60: =+IFERROR(IF(AD60*$J60<0,0,AD60*$J60),0) -> 0 | ... AQ60: =+IFERROR(IF(AF60*$J60<0,0,AF60*$J60),0) -> 0
B61: 48 | C61: =CONCATENATE("N°-","00",B61,"-2024") -> N°-0048-2024 | D61: 779593845 | E61: Mr | F61: Boubacar | G61: Biilaa | H61: Dakar | I61: 77 959 38 45 | J61: 1000 | K61: N/A | L61: =+SUM($V61:$AO61) -> 2990 | M61: =IF(L61>=0,"A JOUR",(SUM($V61:$Y61)*($M$12))) -> A JOUR | O61: =(18000+(16000-13000))*0+13000 -> 13000 | Q61: =SUBTOTAL(9,$AH61:$AQ61) -> 3000 | R61: =IF(L61>=0,"A JOUR",($L61*($J61)+N61+O61+$M61)) -> A JOUR | S61: x | T61: x | U61: -13000 | V61: -6 | W61: 1 | X61: 1 | Y61: 1 | Z61: -1 | AA61: -1 | AB61: -1 | AC61: -1 | AD61: -1 | AE61: -1 | AF61: -1 | AH61: =+IFERROR(IF(W61*$J61<0,0,W61*$J61),0) -> 1000 | AI61: =+IFERROR(IF(X61*$J61<0,0,X61*$J61),0) -> 1000 | AJ61: =+IFERROR(IF(Y61*$J61<0,0,Y61*$J61),0) -> 1000 | AK61: =+IFERROR(IF(Z61*$J61<0,0,Z61*$J61),0) -> 0 | AL61: =+IFERROR(IF(AA61*$J61<0,0,AA61*$J61),0) -> 0 | AM61: =+IFERROR(IF(AB61*$J61<0,0,AB61*$J61),0) -> 0 | AN61: =+IFERROR(IF(AC61*$J61<0,0,AC61*$J61),0) -> 0 | AO61: =+IFERROR(IF(AD61*$J61<0,0,AD61*$J61),0) -> 0 | ... AQ61: =+IFERROR(IF(AF61*$J61<0,0,AF61*$J61),0) -> 0
B62: 49 | C62: =CONCATENATE("N°-","00",B62,"-2024") -> N°-0049-2024 | D62: 778018331 | E62: Mr | F62: Boubacar (mariste ) | G62: Kourawoye | H62: Dakar | I62: 77 801 83 31 | J62: 2000 | K62: 1000 | L62: 0 | M62: =IF(L62>=0,"A JOUR",(SUM($V62:$Y62)*($M$12))) -> A JOUR | O62: =+IF(L62>0,L62*J62,0) -> 0 | Q62: =SUBTOTAL(9,$AH62:$AQ62) -> 6000 | R62: =IF(L62>=0,"A JOUR",($L62*($J62)+N62+O62+$M62)) -> A JOUR | S62: x | T62: x | V62: 1 | W62: 1 | X62: 1 | Y62: 1 | Z62: -1 | AA62: -1 | AB62: -1 | AC62: -1 | AD62: -1 | AE62: -1 | AF62: -1 | AH62: =+IFERROR(IF(W62*$J62<0,0,W62*$J62),0) -> 2000 | AI62: =+IFERROR(IF(X62*$J62<0,0,X62*$J62),0) -> 2000 | AJ62: =+IFERROR(IF(Y62*$J62<0,0,Y62*$J62),0) -> 2000 | AK62: =+IFERROR(IF(Z62*$J62<0,0,Z62*$J62),0) -> 0 | AL62: =+IFERROR(IF(AA62*$J62<0,0,AA62*$J62),0) -> 0 | AM62: =+IFERROR(IF(AB62*$J62<0,0,AB62*$J62),0) -> 0 | AN62: =+IFERROR(IF(AC62*$J62<0,0,AC62*$J62),0) -> 0 | AO62: =+IFERROR(IF(AD62*$J62<0,0,AD62*$J62),0) -> 0 | ... AQ62: =+IFERROR(IF(AF62*$J62<0,0,AF62*$J62),0) -> 0
B63: 50 | C63: =CONCATENATE("N°-","00",B63,"-2024") -> N°-0050-2024 | D63: 774494968 | E63: Mr | F63: Boubacar ibn bappa bala CC | G63: Pétel | H63: Dakar | I63: 77 449 49 68 | J63: 3000 | K63: 1000 | L63: 0 | M63: =IF(L63>=0,"A JOUR",(SUM($V63:$Y63)*($M$12))) -> A JOUR | O63: =+IF(L63>0,L63*J63,0) -> 0 | Q63: =SUBTOTAL(9,$AH63:$AQ63) -> 30000 | R63: =IF(L63>=0,"A JOUR",($L63*($J63)+N63+O63+$M63)) -> A JOUR | S63: x | T63: x | V63: 1 | W63: 1 | X63: 1 | Y63: 1 | Z63: 1 | AA63: 1 | AB63: 1 | AC63: 1 | AD63: 1 | AE63: 1 | AF63: 1 | AH63: =+IFERROR(IF(W63*$J63<0,0,W63*$J63),0) -> 3000 | AI63: =+IFERROR(IF(X63*$J63<0,0,X63*$J63),0) -> 3000 | AJ63: =+IFERROR(IF(Y63*$J63<0,0,Y63*$J63),0) -> 3000 | AK63: =+IFERROR(IF(Z63*$J63<0,0,Z63*$J63),0) -> 3000 | AL63: =+IFERROR(IF(AA63*$J63<0,0,AA63*$J63),0) -> 3000 | AM63: =+IFERROR(IF(AB63*$J63<0,0,AB63*$J63),0) -> 3000 | AN63: =+IFERROR(IF(AC63*$J63<0,0,AC63*$J63),0) -> 3000 | AO63: =+IFERROR(IF(AD63*$J63<0,0,AD63*$J63),0) -> 3000 | ... AQ63: =+IFERROR(IF(AF63*$J63<0,0,AF63*$J63),0) -> 3000
B64: 51 | C64: =CONCATENATE("N°-","00",B64,"-2024") -> N°-0051-2024 | D64: 779862991 | E64: Koto | F64: Boubacar ibn Elhadji Ibrahima | G64: Pétel | H64: Dakar | I64: 77 986 29 91 | J64: 2000 | K64: N/A | L64: 0 | M64: =IF(L64>=0,"A JOUR",(SUM($V64:$Y64)*($M$12))) -> A JOUR | O64: =+IF(L64>0,L64*J64,0) -> 0 | Q64: =SUBTOTAL(9,$AH64:$AQ64) -> 20000 | R64: =IF(L64>=0,"A JOUR",($L64*($J64)+N64+O64+$M64)) -> A JOUR | T64: x | V64: 1 | W64: 1 | X64: 1 | Y64: 1 | Z64: 1 | AA64: 1 | AB64: 1 | AC64: 1 | AD64: 1 | AE64: 1 | AF64: 1 | AH64: =+IFERROR(IF(W64*$J64<0,0,W64*$J64),0) -> 2000 | AI64: =+IFERROR(IF(X64*$J64<0,0,X64*$J64),0) -> 2000 | AJ64: =+IFERROR(IF(Y64*$J64<0,0,Y64*$J64),0) -> 2000 | AK64: =+IFERROR(IF(Z64*$J64<0,0,Z64*$J64),0) -> 2000 | AL64: =+IFERROR(IF(AA64*$J64<0,0,AA64*$J64),0) -> 2000 | AM64: =+IFERROR(IF(AB64*$J64<0,0,AB64*$J64),0) -> 2000 | AN64: =+IFERROR(IF(AC64*$J64<0,0,AC64*$J64),0) -> 2000 | AO64: =+IFERROR(IF(AD64*$J64<0,0,AD64*$J64),0) -> 2000 | ... AQ64: =+IFERROR(IF(AF64*$J64<0,0,AF64*$J64),0) -> 2000
B65: 52 | C65: =CONCATENATE("N°-","00",B65,"-2024") -> N°-0052-2024 | D65: 776779519 | E65: Mr | F65: Boubacar Kowloun | G65: Kowloune | H65: Dakar | I65: 77 677 95 19 | J65: 1000 | K65: 1000 | L65: 0 | M65: =IF(L65>=0,"A JOUR",(SUM($V65:$Y65)*($M$12))) -> A JOUR | O65: =+IF(L65>0,L65*J65,0) -> 0 | Q65: =SUBTOTAL(9,$AH65:$AQ65) -> 10000 | R65: =IF(L65>=0,"A JOUR",($L65*($J65)+N65+O65+$M65)) -> A JOUR | V65: 1 | W65: 1 | X65: 1 | Y65: 1 | Z65: 1 | AA65: 1 | AB65: 1 | AC65: 1 | AD65: 1 | AE65: 1 | AF65: 1 | AH65: =+IFERROR(IF(W65*$J65<0,0,W65*$J65),0) -> 1000 | AI65: =+IFERROR(IF(X65*$J65<0,0,X65*$J65),0) -> 1000 | AJ65: =+IFERROR(IF(Y65*$J65<0,0,Y65*$J65),0) -> 1000 | AK65: =+IFERROR(IF(Z65*$J65<0,0,Z65*$J65),0) -> 1000 | AL65: =+IFERROR(IF(AA65*$J65<0,0,AA65*$J65),0) -> 1000 | AM65: =+IFERROR(IF(AB65*$J65<0,0,AB65*$J65),0) -> 1000 | AN65: =+IFERROR(IF(AC65*$J65<0,0,AC65*$J65),0) -> 1000 | AO65: =+IFERROR(IF(AD65*$J65<0,0,AD65*$J65),0) -> 1000 | ... AQ65: =+IFERROR(IF(AF65*$J65<0,0,AF65*$J65),0) -> 1000
B66: 53 | C66: =CONCATENATE("N°-","00",B66,"-2024") -> N°-0053-2024 | D66: 773137431 | E66: Koto | F66: Boubacar méékohi | G66: Dowsaré | H66: Dakar | I66: 77 313 74 31 | J66: 2000 | K66: 1000 | L66: 0 | M66: =IF(L66>=0,"A JOUR",(SUM($V66:$Y66)*($M$12))) -> A JOUR | O66: =+IF(L66>0,L66*J66,0) -> 0 | Q66: =SUBTOTAL(9,$AH66:$AQ66) -> 6000 | R66: =IF(L66>=0,"A JOUR",($L66*($J66)+N66+O66+$M66)) -> A JOUR | S66: x | T66: x | U66: NT | V66: 1 | W66: 1 | X66: 1 | Y66: 1 | Z66: VG | AA66: VG | AB66: VG | AC66: VG | AD66: VG | AE66: VG | AF66: VG | AH66: =+IFERROR(IF(W66*$J66<0,0,W66*$J66),0) -> 2000 | AI66: =+IFERROR(IF(X66*$J66<0,0,X66*$J66),0) -> 2000 | AJ66: =+IFERROR(IF(Y66*$J66<0,0,Y66*$J66),0) -> 2000 | AK66: =+IFERROR(IF(Z66*$J66<0,0,Z66*$J66),0) -> 0 | AL66: =+IFERROR(IF(AA66*$J66<0,0,AA66*$J66),0) -> 0 | AM66: =+IFERROR(IF(AB66*$J66<0,0,AB66*$J66),0) -> 0 | AN66: =+IFERROR(IF(AC66*$J66<0,0,AC66*$J66),0) -> 0 | AO66: =+IFERROR(IF(AD66*$J66<0,0,AD66*$J66),0) -> 0 | ... AQ66: =+IFERROR(IF(AF66*$J66<0,0,AF66*$J66),0) -> 0
B67: 54 | C67: =CONCATENATE("N°-","00",B67,"-2024") -> N°-0054-2024 | E67: Mr | F67: Boubacar Ngarahi | G67: Dowsaré | H67: Dakar | J67: 1000 | K67: 1000 | M67: =IF(L67>=0,"A JOUR",(SUM($V67:$Y67)*($M$12))) -> A JOUR | Q67: =SUBTOTAL(9,$AH67:$AQ67) -> 0 | R67: =IF(L67>=0,"A JOUR",($L67*($J67)+N67+O67+$M67)) -> A JOUR
B68: 55 | C68: =CONCATENATE("N°-","00",B68,"-2024") -> N°-0055-2024 | D68: 776669090 | E68: Mr | F68: Bourhane | G68: Pétel | H68: Dakar | I68: 77 666 90 90 | J68: 1000 | K68: N/A | M68: =IF(L68>=0,"A JOUR",(SUM($V68:$Y68)*($M$12))) -> A JOUR | N68: 6000 | Q68: =SUBTOTAL(9,$AH68:$AQ68) -> 10000 | R68: =IF(L68>=0,"A JOUR",($L68*($J68)+N68+O68+$M68)) -> A JOUR | S68: x | T68: x | V68: 1 | W68: 1 | X68: 1 | Y68: 1 | Z68: 1 | AA68: 1 | AB68: 1 | AC68: 1 | AD68: 1 | AE68: 1 | AF68: 1 | AH68: =+IFERROR(IF(W68*$J68<0,0,W68*$J68),0) -> 1000 | AI68: =+IFERROR(IF(X68*$J68<0,0,X68*$J68),0) -> 1000 | AJ68: =+IFERROR(IF(Y68*$J68<0,0,Y68*$J68),0) -> 1000 | AK68: =+IFERROR(IF(Z68*$J68<0,0,Z68*$J68),0) -> 1000 | AL68: =+IFERROR(IF(AA68*$J68<0,0,AA68*$J68),0) -> 1000 | AM68: =+IFERROR(IF(AB68*$J68<0,0,AB68*$J68),0) -> 1000 | AN68: =+IFERROR(IF(AC68*$J68<0,0,AC68*$J68),0) -> 1000 | AO68: =+IFERROR(IF(AD68*$J68<0,0,AD68*$J68),0) -> 1000 | ... AQ68: =+IFERROR(IF(AF68*$J68<0,0,AF68*$J68),0) -> 1000
B69: 56 | C69: =CONCATENATE("N°-","00",B69,"-2024") -> N°-0056-2024 | E69: Mr | F69: Cheikh ibn Elhadji Aliou | G69: Kourawoye | H69: Dakar | J69: N/A | K69: N/A | M69: =IF(L69>=0,"A JOUR",(SUM($V69:$Y69)*($M$12))) -> A JOUR | Q69: =SUBTOTAL(9,$AH69:$AQ69) -> 0 | R69: =IF(L69>=0,"A JOUR",($L69*($J69)+N69+O69+$M69)) -> A JOUR | S69: x | T69: x | V69: NT | W69: NT | X69: NT | Y69: NT | Z69: NT | AA69: NT | AB69: NT | AC69: NT | AD69: NT | AE69: NT | AF69: NT | AH69: =+IFERROR(IF(W69*$J69<0,0,W69*$J69),0) -> 0 | AI69: =+IFERROR(IF(X69*$J69<0,0,X69*$J69),0) -> 0 | AJ69: =+IFERROR(IF(Y69*$J69<0,0,Y69*$J69),0) -> 0 | AK69: =+IFERROR(IF(Z69*$J69<0,0,Z69*$J69),0) -> 0 | AL69: =+IFERROR(IF(AA69*$J69<0,0,AA69*$J69),0) -> 0 | AM69: =+IFERROR(IF(AB69*$J69<0,0,AB69*$J69),0) -> 0 | AN69: =+IFERROR(IF(AC69*$J69<0,0,AC69*$J69),0) -> 0 | AO69: =+IFERROR(IF(AD69*$J69<0,0,AD69*$J69),0) -> 0 | ... AQ69: =+IFERROR(IF(AF69*$J69<0,0,AF69*$J69),0) -> 0
B70: 57 | C70: =CONCATENATE("N°-","00",B70,"-2024") -> N°-0057-2024 | D70: 774885353 | E70: Mr | F70: Cheikh tidiane ibn Elhadji Ibrahima | G70: Pétel | H70: Dakar | I70: 77 488 53 53 | J70: 1000 | K70: 1000 | L70: =+SUM($V70:$AO70) -> 8009 | M70: =IF(L70>=0,"A JOUR",(SUM($V70:$Y70)*($M$12))) -> A JOUR | O70: 1000 | Q70: =SUBTOTAL(9,$AH70:$AQ70) -> 10000 | R70: =IF(L70>=0,"A JOUR",($L70*($J70)+N70+O70+$M70)) -> A JOUR | S70: x | T70: x | V70: -1 | W70: 1 | X70: 1 | Y70: 1 | Z70: 1 | AA70: 1 | AB70: 1 | AC70: 1 | AD70: 1 | AE70: 1 | AF70: 1 | AH70: =+IFERROR(IF(W70*$J70<0,0,W70*$J70),0) -> 1000 | AI70: =+IFERROR(IF(X70*$J70<0,0,X70*$J70),0) -> 1000 | AJ70: =+IFERROR(IF(Y70*$J70<0,0,Y70*$J70),0) -> 1000 | AK70: =+IFERROR(IF(Z70*$J70<0,0,Z70*$J70),0) -> 1000 | AL70: =+IFERROR(IF(AA70*$J70<0,0,AA70*$J70),0) -> 1000 | AM70: =+IFERROR(IF(AB70*$J70<0,0,AB70*$J70),0) -> 1000 | AN70: =+IFERROR(IF(AC70*$J70<0,0,AC70*$J70),0) -> 1000 | AO70: =+IFERROR(IF(AD70*$J70<0,0,AD70*$J70),0) -> 1000 | ... AQ70: =+IFERROR(IF(AF70*$J70<0,0,AF70*$J70),0) -> 1000
B71: 58 | C71: =CONCATENATE("N°-","00",B71,"-2024") -> N°-0058-2024 | E71: Mr | F71: Daouda | G71: Dowsaré | H71: Casamance | J71: N/A | K71: N/A | M71: =IF(L71>=0,"A JOUR",(SUM($V71:$Y71)*($M$12))) -> A JOUR | Q71: =SUBTOTAL(9,$AH71:$AQ71) -> 0 | R71: =IF(L71>=0,"A JOUR",($L71*($J71)+N71+O71+$M71)) -> A JOUR | T71: x
B72: 59 | C72: =CONCATENATE("N°-","00",B72,"-2024") -> N°-0059-2024 | D72: 774767085 | E72: Mr | F72: Daouda (Parcelles) | G72: Kourawoye | H72: Dakar | I72: 77 476 70 85 | J72: 1000 | K72: 1000 | L72: 0 | M72: =IF(L72>=0,"A JOUR",(SUM($V72:$Y72)*($M$12))) -> A JOUR | O72: =+IF(L72>0,L72*J72,0) -> 0 | Q72: =SUBTOTAL(9,$AH72:$AQ72) -> 10000 | R72: =IF(L72>=0,"A JOUR",($L72*($J72)+N72+O72+$M72)) -> A JOUR | S72: x | T72: x | V72: 1 | W72: 1 | X72: 1 | Y72: 1 | Z72: 1 | AA72: 1 | AB72: 1 | AC72: 1 | AD72: 1 | AE72: 1 | AF72: 1 | AH72: =+IFERROR(IF(W72*$J72<0,0,W72*$J72),0) -> 1000 | AI72: =+IFERROR(IF(X72*$J72<0,0,X72*$J72),0) -> 1000 | AJ72: =+IFERROR(IF(Y72*$J72<0,0,Y72*$J72),0) -> 1000 | AK72: =+IFERROR(IF(Z72*$J72<0,0,Z72*$J72),0) -> 1000 | AL72: =+IFERROR(IF(AA72*$J72<0,0,AA72*$J72),0) -> 1000 | AM72: =+IFERROR(IF(AB72*$J72<0,0,AB72*$J72),0) -> 1000 | AN72: =+IFERROR(IF(AC72*$J72<0,0,AC72*$J72),0) -> 1000 | AO72: =+IFERROR(IF(AD72*$J72<0,0,AD72*$J72),0) -> 1000 | ... AQ72: =+IFERROR(IF(AF72*$J72<0,0,AF72*$J72),0) -> 1000
B73: 60 | C73: =CONCATENATE("N°-","00",B73,"-2024") -> N°-0060-2024 | E73: Mr | F73: Daouda ibn Elhadji M. Woury | G73: Pétel | H73: Guinée | J73: 1000 | K73: 1000 | L73: =+SUM($V73:$AO73) -> -3 | M73: =IF(L73>=0,"A JOUR",(SUM($V73:$Y73)*($M$12))) -> -6000 | P73: 50000 | Q73: =SUBTOTAL(9,$AH73:$AQ73) -> 0 | R73: =IF(L73>=0,"A JOUR",($L73*($J73)+N73+O73+$M73)) -> -9000 | S73: x | T73: x | U73: VG | V73: VG | W73: -1 | X73: -1 | Y73: -1 | Z73: 0 | AA73: 0 | AB73: 0 | AC73: 0 | AD73: 0 | AE73: 0 | AF73: 0 | AH73: =+IFERROR(IF(W73*$J73<0,0,W73*$J73),0) -> 0 | AI73: =+IFERROR(IF(X73*$J73<0,0,X73*$J73),0) -> 0 | AJ73: =+IFERROR(IF(Y73*$J73<0,0,Y73*$J73),0) -> 0 | AK73: =+IFERROR(IF(Z73*$J73<0,0,Z73*$J73),0) -> 0 | AL73: =+IFERROR(IF(AA73*$J73<0,0,AA73*$J73),0) -> 0 | AM73: =+IFERROR(IF(AB73*$J73<0,0,AB73*$J73),0) -> 0 | AN73: =+IFERROR(IF(AC73*$J73<0,0,AC73*$J73),0) -> 0 | AO73: =+IFERROR(IF(AD73*$J73<0,0,AD73*$J73),0) -> 0 | ... AQ73: =+IFERROR(IF(AF73*$J73<0,0,AF73*$J73),0) -> 0
B74: 61 | C74: =CONCATENATE("N°-","00",B74,"-2024") -> N°-0061-2024 | D74: 776790248 | E74: Mr | F74: Elh ibrahima N°2 ibn karamoko Daouda DC | G74: Pétel | H74: Dakar | I74: 77 679 02 48 | J74: 2000 | K74: 1000 | L74: 0 | M74: =IF(L74>=0,"A JOUR",(SUM($V74:$Y74)*($M$12))) -> A JOUR | O74: =+IF(L74>0,L74*J74,0) -> 0 | Q74: =SUBTOTAL(9,$AH74:$AQ74) -> 20000 | R74: =IF(L74>=0,"A JOUR",($L74*($J74)+N74+O74+$M74)) -> A JOUR | S74: x | T74: x | V74: 1 | W74: 1 | X74: 1 | Y74: 1 | Z74: 1 | AA74: 1 | AB74: 1 | AC74: 1 | AD74: 1 | AE74: 1 | AF74: 1 | AH74: =+IFERROR(IF(W74*$J74<0,0,W74*$J74),0) -> 2000 | AI74: =+IFERROR(IF(X74*$J74<0,0,X74*$J74),0) -> 2000 | AJ74: =+IFERROR(IF(Y74*$J74<0,0,Y74*$J74),0) -> 2000 | AK74: =+IFERROR(IF(Z74*$J74<0,0,Z74*$J74),0) -> 2000 | AL74: =+IFERROR(IF(AA74*$J74<0,0,AA74*$J74),0) -> 2000 | AM74: =+IFERROR(IF(AB74*$J74<0,0,AB74*$J74),0) -> 2000 | AN74: =+IFERROR(IF(AC74*$J74<0,0,AC74*$J74),0) -> 2000 | AO74: =+IFERROR(IF(AD74*$J74<0,0,AD74*$J74),0) -> 2000 | ... AQ74: =+IFERROR(IF(AF74*$J74<0,0,AF74*$J74),0) -> 2000
B75: 62 | C75: =CONCATENATE("N°-","00",B75,"-2024") -> N°-0062-2024 | D75: 781656755 | E75: Mr | F75: Elhadji abdoulaye | G75: Dieydiyabhe | H75: Dakar | I75: 78 165 67 55 | J75: 1000 | K75: 1000 | L75: 0 | M75: =IF(L75>=0,"A JOUR",(SUM($V75:$Y75)*($M$12))) -> A JOUR | O75: =+IF(L75>0,L75*J75,0) -> 0 | Q75: =SUBTOTAL(9,$AH75:$AQ75) -> 10000 | R75: =IF(L75>=0,"A JOUR",($L75*($J75)+N75+O75+$M75)) -> A JOUR | S75: x | T75: x | V75: 1 | W75: 1 | X75: 1 | Y75: 1 | Z75: 1 | AA75: 1 | AB75: 1 | AC75: 1 | AD75: 1 | AE75: 1 | AF75: 1 | AH75: =+IFERROR(IF(W75*$J75<0,0,W75*$J75),0) -> 1000 | AI75: =+IFERROR(IF(X75*$J75<0,0,X75*$J75),0) -> 1000 | AJ75: =+IFERROR(IF(Y75*$J75<0,0,Y75*$J75),0) -> 1000 | AK75: =+IFERROR(IF(Z75*$J75<0,0,Z75*$J75),0) -> 1000 | AL75: =+IFERROR(IF(AA75*$J75<0,0,AA75*$J75),0) -> 1000 | AM75: =+IFERROR(IF(AB75*$J75<0,0,AB75*$J75),0) -> 1000 | AN75: =+IFERROR(IF(AC75*$J75<0,0,AC75*$J75),0) -> 1000 | AO75: =+IFERROR(IF(AD75*$J75<0,0,AD75*$J75),0) -> 1000 | ... AQ75: =+IFERROR(IF(AF75*$J75<0,0,AF75*$J75),0) -> 1000
B76: 63 | C76: =CONCATENATE("N°-","00",B76,"-2024") -> N°-0063-2024 | D76: 781313842 | E76: Mr | F76: Elhadji ablaye coiffeur | G76: Dieydiyabhe | H76: Dakar | I76: 78 131 38 42 | J76: 1000 | K76: 1000 | L76: 0 | M76: =IF(L76>=0,"A JOUR",(SUM($V76:$Y76)*($M$12))) -> A JOUR | O76: =+IF(L76>0,L76*J76,0) -> 0 | Q76: =SUBTOTAL(9,$AH76:$AQ76) -> 10000 | R76: =IF(L76>=0,"A JOUR",($L76*($J76)+N76+O76+$M76)) -> A JOUR | S76: x | T76: x | V76: 1 | W76: 1 | X76: 1 | Y76: 1 | Z76: 1 | AA76: 1 | AB76: 1 | AC76: 1 | AD76: 1 | AE76: 1 | AF76: 1 | AH76: =+IFERROR(IF(W76*$J76<0,0,W76*$J76),0) -> 1000 | AI76: =+IFERROR(IF(X76*$J76<0,0,X76*$J76),0) -> 1000 | AJ76: =+IFERROR(IF(Y76*$J76<0,0,Y76*$J76),0) -> 1000 | AK76: =+IFERROR(IF(Z76*$J76<0,0,Z76*$J76),0) -> 1000 | AL76: =+IFERROR(IF(AA76*$J76<0,0,AA76*$J76),0) -> 1000 | AM76: =+IFERROR(IF(AB76*$J76<0,0,AB76*$J76),0) -> 1000 | AN76: =+IFERROR(IF(AC76*$J76<0,0,AC76*$J76),0) -> 1000 | AO76: =+IFERROR(IF(AD76*$J76<0,0,AD76*$J76),0) -> 1000 | ... AQ76: =+IFERROR(IF(AF76*$J76<0,0,AF76*$J76),0) -> 1000
B77: 64 | C77: =CONCATENATE("N°-","00",B77,"-2024") -> N°-0064-2024 | D77: xxxxxxxx | E77: Mr | F77: Elhadji aliou ibn bappa Siradio | G77: Dowsaré | H77: France | I77: xxxxxxxx | J77: 5000 | K77: 1000 | M77: =IF(L77>=0,"A JOUR",(SUM($V77:$Y77)*($M$12))) -> A JOUR | Q77: =SUBTOTAL(9,$AH77:$AQ77) -> 0 | R77: =IF(L77>=0,"A JOUR",($L77*($J77)+N77+O77+$M77)) -> A JOUR | T77: x
B78: 65 | C78: =CONCATENATE("N°-","00",B78,"-2024") -> N°-0065-2024 | D78: 773012928 | E78: Mr | F78: Elhadji amadou | G78: Biilaa | H78: Dakar | I78: 77 301 29 28 | J78: 1000 | K78: 1000 | L78: =+SUM($V78:$AO78) -> 7974 | M78: =IF(L78>=0,"A JOUR",(SUM($V78:$Y78)*($M$12))) -> A JOUR | Q78: =SUBTOTAL(9,$AH78:$AQ78) -> 10000 | R78: =IF(L78>=0,"A JOUR",($L78*($J78)+N78+O78+$M78)) -> A JOUR | S78: x | T78: x | V78: -36 | W78: 1 | X78: 1 | Y78: 1 | Z78: 1 | AA78: 1 | AB78: 1 | AC78: 1 | AD78: 1 | AE78: 1 | AF78: 1 | AH78: =+IFERROR(IF(W78*$J78<0,0,W78*$J78),0) -> 1000 | AI78: =+IFERROR(IF(X78*$J78<0,0,X78*$J78),0) -> 1000 | AJ78: =+IFERROR(IF(Y78*$J78<0,0,Y78*$J78),0) -> 1000 | AK78: =+IFERROR(IF(Z78*$J78<0,0,Z78*$J78),0) -> 1000 | AL78: =+IFERROR(IF(AA78*$J78<0,0,AA78*$J78),0) -> 1000 | AM78: =+IFERROR(IF(AB78*$J78<0,0,AB78*$J78),0) -> 1000 | AN78: =+IFERROR(IF(AC78*$J78<0,0,AC78*$J78),0) -> 1000 | AO78: =+IFERROR(IF(AD78*$J78<0,0,AD78*$J78),0) -> 1000 | ... AQ78: =+IFERROR(IF(AF78*$J78<0,0,AF78*$J78),0) -> 1000
B79: 66 | C79: =CONCATENATE("N°-","00",B79,"-2024") -> N°-0066-2024 | D79: 761722302 | E79: Mr | F79: Elhadji Boubacar mo moussou | G79: Pétel | H79: Dakar | I79: 76 172 23 02 | J79: 1000 | K79: 1000 | L79: =+SUM($V79:$AO79) -> -56 | M79: =IF(L79>=0,"A JOUR",(SUM($V79:$Y79)*($M$12))) -> -98000 | N79: 138000 | Q79: =SUBTOTAL(9,$AH79:$AQ79) -> 0 | R79: =IF(L79>=0,"A JOUR",($L79*($J79)+N79+O79+$M79)) -> -16000 | S79: x | T79: x | V79: -46 | W79: -1 | X79: -1 | Y79: -1 | Z79: -1 | AA79: -1 | AB79: -1 | AC79: -1 | AD79: -1 | AE79: -1 | AF79: -1 | AH79: =+IFERROR(IF(W79*$J79<0,0,W79*$J79),0) -> 0 | AI79: =+IFERROR(IF(X79*$J79<0,0,X79*$J79),0) -> 0 | AJ79: =+IFERROR(IF(Y79*$J79<0,0,Y79*$J79),0) -> 0 | AK79: =+IFERROR(IF(Z79*$J79<0,0,Z79*$J79),0) -> 0 | AL79: =+IFERROR(IF(AA79*$J79<0,0,AA79*$J79),0) -> 0 | AM79: =+IFERROR(IF(AB79*$J79<0,0,AB79*$J79),0) -> 0 | AN79: =+IFERROR(IF(AC79*$J79<0,0,AC79*$J79),0) -> 0 | AO79: =+IFERROR(IF(AD79*$J79<0,0,AD79*$J79),0) -> 0 | ... AQ79: =+IFERROR(IF(AF79*$J79<0,0,AF79*$J79),0) -> 0
B80: 67 | C80: =CONCATENATE("N°-","00",B80,"-2024") -> N°-0067-2024 | D80: 622417844 | E80: Mr | F80: Elhadji douka chauffeur | G80: Dowsaré | H80: Guinée | I80: 622 41 78 44 | J80: 2000 | K80: 1000 | L80: 0 | M80: =IF(L80>=0,"A JOUR",(SUM($V80:$Y80)*($M$12))) -> A JOUR | O80: =+IF(L80>0,L80*J80,0) -> 0 | Q80: =SUBTOTAL(9,$AH80:$AQ80) -> 0 | R80: =IF(L80>=0,"A JOUR",($L80*($J80)+N80+O80+$M80)) -> A JOUR | S80: x | T80: x | V80: VG | W80: VG | X80: VG | Y80: VG | Z80: VG | AA80: VG | AB80: VG | AC80: VG | AD80: VG | AE80: VG | AF80: VG | AH80: =+IFERROR(IF(W80*$J80<0,0,W80*$J80),0) -> 0 | AI80: =+IFERROR(IF(X80*$J80<0,0,X80*$J80),0) -> 0 | AJ80: =+IFERROR(IF(Y80*$J80<0,0,Y80*$J80),0) -> 0 | AK80: =+IFERROR(IF(Z80*$J80<0,0,Z80*$J80),0) -> 0 | AL80: =+IFERROR(IF(AA80*$J80<0,0,AA80*$J80),0) -> 0 | AM80: =+IFERROR(IF(AB80*$J80<0,0,AB80*$J80),0) -> 0 | AN80: =+IFERROR(IF(AC80*$J80<0,0,AC80*$J80),0) -> 0 | AO80: =+IFERROR(IF(AD80*$J80<0,0,AD80*$J80),0) -> 0 | ... AQ80: =+IFERROR(IF(AF80*$J80<0,0,AF80*$J80),0) -> 0
B81: 68 | C81: =CONCATENATE("N°-","00",B81,"-2024") -> N°-0068-2024 | D81: 784087096 | E81: Mr | F81: Elhadji ibrahima ibn Elhadji M. Woury | G81: Pétel | H81: Dakar | I81: 78 408 70 96 | J81: 1000 | K81: 1000 | L81: =+SUM($V81:$AO81) -> 2990 | M81: =IF(L81>=0,"A JOUR",(SUM($V81:$Y81)*($M$12))) -> A JOUR | O81: 18000 | Q81: =SUBTOTAL(9,$AH81:$AQ81) -> 3000 | R81: =IF(L81>=0,"A JOUR",($L81*($J81)+N81+O81+$M81)) -> A JOUR | T81: x | U81: A REVOIR | V81: -6 | W81: 1 | X81: 1 | Y81: 1 | Z81: -1 | AA81: -1 | AB81: -1 | AC81: -1 | AD81: -1 | AE81: -1 | AF81: -1 | AH81: =+IFERROR(IF(W81*$J81<0,0,W81*$J81),0) -> 1000 | AI81: =+IFERROR(IF(X81*$J81<0,0,X81*$J81),0) -> 1000 | AJ81: =+IFERROR(IF(Y81*$J81<0,0,Y81*$J81),0) -> 1000 | AK81: =+IFERROR(IF(Z81*$J81<0,0,Z81*$J81),0) -> 0 | AL81: =+IFERROR(IF(AA81*$J81<0,0,AA81*$J81),0) -> 0 | AM81: =+IFERROR(IF(AB81*$J81<0,0,AB81*$J81),0) -> 0 | AN81: =+IFERROR(IF(AC81*$J81<0,0,AC81*$J81),0) -> 0 | AO81: =+IFERROR(IF(AD81*$J81<0,0,AD81*$J81),0) -> 0 | ... AQ81: =+IFERROR(IF(AF81*$J81<0,0,AF81*$J81),0) -> 0
B82: 69 | C82: =CONCATENATE("N°-","00",B82,"-2024") -> N°-0069-2024 | D82: 776549856 | E82: Bappa | F82: Elhadji siradio | G82: Dowsaré | H82: Dakar | I82: 77 654 98 56 | J82: 5000 | K82: N/A | L82: 0 | M82: =IF(L82>=0,"A JOUR",(SUM($V82:$Y82)*($M$12))) -> A JOUR | O82: =+IF(L82>0,L82*J82,0) -> 0 | Q82: =SUBTOTAL(9,$AH82:$AQ82) -> 30000 | R82: =IF(L82>=0,"A JOUR",($L82*($J82)+N82+O82+$M82)) -> A JOUR | T82: x | V82: 1 | W82: 1 | X82: 1 | Y82: 1 | Z82: 1 | AA82: 1 | AB82: 1 | AC82: -1 | AD82: -1 | AE82: -1 | AF82: -1 | AH82: =+IFERROR(IF(W82*$J82<0,0,W82*$J82),0) -> 5000 | AI82: =+IFERROR(IF(X82*$J82<0,0,X82*$J82),0) -> 5000 | AJ82: =+IFERROR(IF(Y82*$J82<0,0,Y82*$J82),0) -> 5000 | AK82: =+IFERROR(IF(Z82*$J82<0,0,Z82*$J82),0) -> 5000 | AL82: =+IFERROR(IF(AA82*$J82<0,0,AA82*$J82),0) -> 5000 | AM82: =+IFERROR(IF(AB82*$J82<0,0,AB82*$J82),0) -> 5000 | AN82: =+IFERROR(IF(AC82*$J82<0,0,AC82*$J82),0) -> 0 | AO82: =+IFERROR(IF(AD82*$J82<0,0,AD82*$J82),0) -> 0 | ... AQ82: =+IFERROR(IF(AF82*$J82<0,0,AF82*$J82),0) -> 0
